Workbook

Sheet Обзор
A1: Luxhommè — Яндекс Директ на сайт: семантика, объявления, UTM (15 товаров)
A3: Параметры
A4: Сайт | B4: https://luxhomme.store
A5: Промокод | B5: DIRECT20
A6: Скидка | B6: 20% на все товары при заказе на сайте
A7: География | B7: Вся Россия
A8: Кампании | B8: Поиск по товарам · Сети (РСЯ, ЕПК) · Товарная по фиду
A9: Факты о товарах | B9: Карточки luxhomme.store, снято 09.10.2026
A10: Частотности | B10: Только Aqvion Pro — из файла семантики клиента (research/semantika-vertikalnyj-moyushhij-pylesos.csv). По остальным не снимались
A11: Конкуренты | B11: Запросы с брендами конкурентов — в минус-словах
A12: Бренд Luxhommè | B12: В минус-словах: брендовые запросы идут в действующую брендовую кампанию
A14: Структура кампаний
A15: Кампания | B15: Тип / площадки | C15: Группы | D15: utm_campaign | E15: Стратегия на старте | F15: Где в файле
A16: Lux | Поиск | Пылесосы | B16: ЕПК, только поиск | C16: Aqvion Pro, Cleneo Pro, Aerlyn | D16: lux_search_pylesosy_{campaign_id} | E16: Максимум кликов с недельным бюджетом → Максимум конверсий по цели «Заказ» после накопления конверсий | F16: Листы товаров, «Импорт Поиск»
A17: Lux | Поиск | Паровые швабры | B17: ЕПК, только поиск | C17: EcoSteam Pro, AirSteam Pro, SC-100 Max | D17: lux_search_shvabry_{campaign_id} | E17: Максимум кликов с недельным бюджетом → Максимум конверсий по цели «Заказ» после накопления конверсий | F17: Листы товаров, «Импорт Поиск»
A18: Lux | Поиск | Кофемашины | B18: ЕПК, только поиск | C18: CoffeeMaker Classic, Caffio Professional, CremaX | D18: lux_search_kofe_{campaign_id} | E18: Максимум кликов с недельным бюджетом → Максимум конверсий по цели «Заказ» после накопления конверсий | F18: Листы товаров, «Импорт Поиск»
A19: Lux | Поиск | Аэрогрили | B19: ЕПК, только поиск | C19: AirChef, AirChef Dual Pro | D19: lux_search_aerogrili_{campaign_id} | E19: Максимум кликов с недельным бюджетом → Максимум конверсий по цели «Заказ» после накопления конверсий | F19: Листы товаров, «Импорт Поиск»
A20: Lux | Поиск | Виброплатформы | B20: ЕПК, только поиск | C20: uFit 2D Standard, uFit 2D Pro, uFit 3D Max | D20: lux_search_vibro_{campaign_id} | E20: Максимум кликов с недельным бюджетом → Максимум конверсий по цели «Заказ» после накопления конверсий | F20: Листы товаров, «Импорт Поиск»
A21: Lux | Поиск | Роботы-мойщики окон | B21: ЕПК, только поиск | C21: uClean Max | D21: lux_search_okna_{campaign_id} | E21: Максимум кликов с недельным бюджетом → Максимум конверсий по цели «Заказ» после накопления конверсий | F21: Листы товаров, «Импорт Поиск»
A22: Lux | Сети | Пылесосы | B22: ЕПК, только РСЯ: автотаргетинг + фразы, картинки | C22: Aqvion Pro, Cleneo Pro, Aerlyn | D22: lux_epk_pylesosy_{campaign_id} | E22: Как в поиске | F22: Листы товаров (блок РСЯ), «Импорт Сети»
A23: Lux | Сети | Паровые швабры | B23: ЕПК, только РСЯ: автотаргетинг + фразы, картинки | C23: EcoSteam Pro, AirSteam Pro, SC-100 Max | D23: lux_epk_shvabry_{campaign_id} | E23: Как в поиске | F23: Листы товаров (блок РСЯ), «Импорт Сети»
A24: Lux | Сети | Кофемашины | B24: ЕПК, только РСЯ: автотаргетинг + фразы, картинки | C24: CoffeeMaker Classic, Caffio Professional, CremaX | D24: lux_epk_kofe_{campaign_id} | E24: Как в поиске | F24: Листы товаров (блок РСЯ), «Импорт Сети»
A25: Lux | Сети | Аэрогрили | B25: ЕПК, только РСЯ: автотаргетинг + фразы, картинки | C25: AirChef, AirChef Dual Pro | D25: lux_epk_aerogrili_{campaign_id} | E25: Как в поиске | F25: Листы товаров (блок РСЯ), «Импорт Сети»
A26: Lux | Сети | Виброплатформы | B26: ЕПК, только РСЯ: автотаргетинг + фразы, картинки | C26: uFit 2D Standard, uFit 2D Pro, uFit 3D Max | D26: lux_epk_vibro_{campaign_id} | E26: Как в поиске | F26: Листы товаров (блок РСЯ), «Импорт Сети»
... A28: Lux | Товарная | Фид | B28: Товарная кампания: поиск + РСЯ | C28: 15 офферов из фида | D28: lux_feed_{campaign_id} | E28: Как в поиске | F28: «Фид», файл luxhomme-direct-feed.yml
A30: UTM-разметка
A31: Параметр | B31: Значение | C31: Что даёт
A32: utm_source | B32: yandex | C32: Источник
A33: utm_medium | B33: cpc | C33: Платный трафик
A34: utm_campaign | B34: lux_<search|epk|feed>_<категория>_{campaign_id} | C34: Тип кампании, категория, ID кампании
A35: utm_content | B35: <модель>_{ad_id}_{source_type} | C35: Товар, ID объявления, поиск/сети
A36: utm_term | B36: {keyword} | C36: Ключевая фраза
A37: Быстрые ссылки | B37: в utm_content добавлено _sitelink | C37: Отделить переходы по быстрым ссылкам
A39: Перед запуском
A40: ☐ | B40: Завести на сайте промокод DIRECT20: −20% на все товары; указать условие на сайте (баннер или строка в карточке) — модерация сверяет скидку с посадочной.
A41: ☐ | B41: Гостевое оформление заказа и срок/стоимость доставки до входа в аккаунт (UI/UX-аудит, разделы 1–2).
A42: ☐ | B42: Гарантия: в карточках 3 года (EcoSteam Pro — 12 месяцев, uFit 2D Standard — 2 года), на /service — 12 месяцев. Привести к одному сроку; в объявлениях срок взят из карточки.
A43: ☐ | B43: Бесплатную доставку не обещать: на /delivery стоимость не рассчитывается автоматически.
A44: ☐ | B44: CremaX нет в sitemap — добавить.
A45: ☐ | B45: На /returns продавец — ИП, в подвале сайта — ООО «САУДАГАР Е-КОМ»: указать одного продавца.
A46: ☐ | B46: Виброплатформы с EMS: тексты без медицинских обещаний; модерация может запросить документы — подготовить сертификат/декларацию.
A47: ☐ | B47: Nespresso, Dolce Gusto в текстах — только как совместимые форматы капсул.
A48: ☐ | B48: Если модерация отклонит слово заглавными (DIRECT20) — заменить на вариант с одной заглавной, код на сайте сделать нечувствительным к регистру.
A49: ☐ | B49: Метрика: цели «Заказ» и «Применение промокода», счётчик подключён к кампаниям, разметка ссылок для Метрики (yclid) включена.
A50: ☐ | B50: Колонки листов «Импорт» сверить с актуальным шаблоном Директ Коммандера перед загрузкой.
A52: Листы
A53: Товары | B53: Сводка: цены, цена с промокодом, ссылки с UTM
A54: Листы товаров | B54: УТП, семантика, минус-слова товара, объявления поиска, быстрые ссылки, уточнения, РСЯ, ссылки
A55: Минус-слова | B55: Общие, конкуренты по категориям, по товарам
A56: Импорт Поиск / Импорт Сети | B56: Строки для Директ Коммандера (колонка «Кампания» — фильтр перед вставкой)
A57: Фид | B57: Офферы для товарной кампании; YML — отдельным файлом

Sheet Товары
A1: Скидка | B1: 0.2
A3: № | B3: Товар | C3: Категория | D3: SKU | E3: Цена, ₽ | F3: С промокодом, ₽ | G3: Гарантия | H3: Страница | I3: Ссылка Поиск (UTM) | J3: Ссылка Сети (UTM) | K3: Ссылка Фид (UTM)
A4: 1 | B4: Вертикальный моющий пылесос Aqvion Pro | C4: Пылесосы | D4: VACCLWASH | E4: 19990 | F4: =ROUND(E4*(1-$B$1),0) | G4: 3 года | H4: https://luxhomme.store/products/vertikalnyj-moyushhij-pylesos-aqvion-pro | I4: https://luxhomme.store/products/vertikalnyj-moyushhij-pylesos-aqvion-pro?utm_source=yandex&utm_medium=cpc&utm_campaign=lux_search_pylesosy_{campaign_id}&utm_content=aqvion-pro_{ad_id}_{source_type}&utm_term={keyword} | J4: https://luxhomme.store/products/vertikalnyj-moyushhij-pylesos-aqvion-pro?utm_source=yandex&utm_medium=cpc&utm_campaign=lux_epk_pylesosy_{campaign_id}&utm_content=aqvion-pro_{ad_id}_{source_type}&utm_term={keyword} | K4: https://luxhomme.store/products/vertikalnyj-moyushhij-pylesos-aqvion-pro?utm_source=yandex&utm_medium=cpc&utm_campaign=lux_feed_{campaign_id}&utm_content=aqvion-pro_{ad_id}_{source_type}&utm_term={keyword}
A5: 2 | B5: Компактный моющий пылесос Cleneo Pro | C5: Пылесосы | D5: VACCLCOMPACT | E5: 16990 | F5: =ROUND(E5*(1-$B$1),0) | G5: 3 года | H5: https://luxhomme.store/products/kompaktnyj-moyushhij-pylesos-cleneo-pro | I5: https://luxhomme.store/products/kompaktnyj-moyushhij-pylesos-cleneo-pro?utm_source=yandex&utm_medium=cpc&utm_campaign=lux_search_pylesosy_{campaign_id}&utm_content=cleneo-pro_{ad_id}_{source_type}&utm_term={keyword} | J5: https://luxhomme.store/products/kompaktnyj-moyushhij-pylesos-cleneo-pro?utm_source=yandex&utm_medium=cpc&utm_campaign=lux_epk_pylesosy_{campaign_id}&utm_content=cleneo-pro_{ad_id}_{source_type}&utm_term={keyword} | K5: https://luxhomme.store/products/kompaktnyj-moyushhij-pylesos-cleneo-pro?utm_source=yandex&utm_medium=cpc&utm_campaign=lux_feed_{campaign_id}&utm_content=cleneo-pro_{ad_id}_{source_type}&utm_term={keyword}
A6: 3 | B6: Вертикальный сухой пылесос Aerlyn | C6: Пылесосы | D6: VACCLDRY | E6: 15990 | F6: =ROUND(E6*(1-$B$1),0) | G6: 3 года | H6: https://luxhomme.store/products/vertikalnyj-suhoj-pylesos-aerlyn | I6: https://luxhomme.store/products/vertikalnyj-suhoj-pylesos-aerlyn?utm_source=yandex&utm_medium=cpc&utm_campaign=lux_search_pylesosy_{campaign_id}&utm_content=aerlyn_{ad_id}_{source_type}&utm_term={keyword} | J6: https://luxhomme.store/products/vertikalnyj-suhoj-pylesos-aerlyn?utm_source=yandex&utm_medium=cpc&utm_campaign=lux_epk_pylesosy_{campaign_id}&utm_content=aerlyn_{ad_id}_{source_type}&utm_term={keyword} | K6: https://luxhomme.store/products/vertikalnyj-suhoj-pylesos-aerlyn?utm_source=yandex&utm_medium=cpc&utm_campaign=lux_feed_{campaign_id}&utm_content=aerlyn_{ad_id}_{source_type}&utm_term={keyword}
A7: 4 | B7: Паровая швабра Luxhommè EcoSteam Pro | C7: Паровые швабры | D7: SHVPAREKCHB2 | E7: 5990 | F7: =ROUND(E7*(1-$B$1),0) | G7: 12 месяцев | H7: https://luxhomme.store/products/ecosteam-pro | I7: https://luxhomme.store/products/ecosteam-pro?utm_source=yandex&utm_medium=cpc&utm_campaign=lux_search_shvabry_{campaign_id}&utm_content=ecosteam-pro_{ad_id}_{source_type}&utm_term={keyword} | J7: https://luxhomme.store/products/ecosteam-pro?utm_source=yandex&utm_medium=cpc&utm_campaign=lux_epk_shvabry_{campaign_id}&utm_content=ecosteam-pro_{ad_id}_{source_type}&utm_term={keyword} | K7: https://luxhomme.store/products/ecosteam-pro?utm_source=yandex&utm_medium=cpc&utm_campaign=lux_feed_{campaign_id}&utm_content=ecosteam-pro_{ad_id}_{source_type}&utm_term={keyword}
A8: 5 | B8: Паровая швабра Luxhommè AirSteam Pro | C8: Паровые швабры | D8: SHVPAR3D | E8: 10990 | F8: =ROUND(E8*(1-$B$1),0) | G8: 3 года | H8: https://luxhomme.store/products/steamly-pro | I8: https://luxhomme.store/products/steamly-pro?utm_source=yandex&utm_medium=cpc&utm_campaign=lux_search_shvabry_{campaign_id}&utm_content=airsteam-pro_{ad_id}_{source_type}&utm_term={keyword} | J8: https://luxhomme.store/products/steamly-pro?utm_source=yandex&utm_medium=cpc&utm_campaign=lux_epk_shvabry_{campaign_id}&utm_content=airsteam-pro_{ad_id}_{source_type}&utm_term={keyword} | K8: https://luxhomme.store/products/steamly-pro?utm_source=yandex&utm_medium=cpc&utm_campaign=lux_feed_{campaign_id}&utm_content=airsteam-pro_{ad_id}_{source_type}&utm_term={keyword}
A9: 6 | B9: Паровая швабра Luxhommè SC-100 Max | C9: Паровые швабры | D9: SHVPAR7V1CH | E9: 7990 | F9: =ROUND(E9*(1-$B$1),0) | G9: 3 года | H9: https://luxhomme.store/products/sc-100 | I9: https://luxhomme.store/products/sc-100?utm_source=yandex&utm_medium=cpc&utm_campaign=lux_search_shvabry_{campaign_id}&utm_content=sc-100-max_{ad_id}_{source_type}&utm_term={keyword} | J9: https://luxhomme.store/products/sc-100?utm_source=yandex&utm_medium=cpc&utm_campaign=lux_epk_shvabry_{campaign_id}&utm_content=sc-100-max_{ad_id}_{source_type}&utm_term={keyword} | K9: https://luxhomme.store/products/sc-100?utm_source=yandex&utm_medium=cpc&utm_campaign=lux_feed_{campaign_id}&utm_content=sc-100-max_{ad_id}_{source_type}&utm_term={keyword}
A10: 7 | B10: Кофемашина Luxhommè CoffeeMaker Classic | C10: Кофемашины | D10: COFMASHCAP4V1 | E10: 9990 | F10: =ROUND(E10*(1-$B$1),0) | G10: 3 года | H10: https://luxhomme.store/products/coffee | I10: https://luxhomme.store/products/coffee?utm_source=yandex&utm_medium=cpc&utm_campaign=lux_search_kofe_{campaign_id}&utm_content=coffeemaker-classic_{ad_id}_{source_type}&utm_term={keyword} | J10: https://luxhomme.store/products/coffee?utm_source=yandex&utm_medium=cpc&utm_campaign=lux_epk_kofe_{campaign_id}&utm_content=coffeemaker-classic_{ad_id}_{source_type}&utm_term={keyword} | K10: https://luxhomme.store/products/coffee?utm_source=yandex&utm_medium=cpc&utm_campaign=lux_feed_{campaign_id}&utm_content=coffeemaker-classic_{ad_id}_{source_type}&utm_term={keyword}
A11: 8 | B11: Кофемашина рожковая Luxhommè Caffio Professional | C11: Кофемашины | D11: COFMASHROZH | E11: 17990 | F11: =ROUND(E11*(1-$B$1),0) | G11: 3 года | H11: https://luxhomme.store/products/caffio-professional | I11: https://luxhomme.store/products/caffio-professional?utm_source=yandex&utm_medium=cpc&utm_campaign=lux_search_kofe_{campaign_id}&utm_content=caffio-professional_{ad_id}_{source_type}&utm_term={keyword} | J11: https://luxhomme.store/products/caffio-professional?utm_source=yandex&utm_medium=cpc&utm_campaign=lux_epk_kofe_{campaign_id}&utm_content=caffio-professional_{ad_id}_{source_type}&utm_term={keyword} | K11: https://luxhomme.store/products/caffio-professional?utm_source=yandex&utm_medium=cpc&utm_campaign=lux_feed_{campaign_id}&utm_content=caffio-professional_{ad_id}_{source_type}&utm_term={keyword}
A12: 9 | B12: Кофемашина автоматическая зерновая с капучинатором и кофемолкой CremaX | C12: Кофемашины | D12: COFMASHPOMOL | E12: 47990 | F12: =ROUND(E12*(1-$B$1),0) | G12: 3 года | H12: https://luxhomme.store/products/cremax | I12: https://luxhomme.store/products/cremax?utm_source=yandex&utm_medium=cpc&utm_campaign=lux_search_kofe_{campaign_id}&utm_content=cremax_{ad_id}_{source_type}&utm_term={keyword} | J12: https://luxhomme.store/products/cremax?utm_source=yandex&utm_medium=cpc&utm_campaign=lux_epk_kofe_{campaign_id}&utm_content=cremax_{ad_id}_{source_type}&utm_term={keyword} | K12: https://luxhomme.store/products/cremax?utm_source=yandex&utm_medium=cpc&utm_campaign=lux_feed_{campaign_id}&utm_content=cremax_{ad_id}_{source_type}&utm_term={keyword}
A13: 10 | B13: Аэрогриль Luxhommè AirChef | C13: Аэрогрили | D13: AEROGRIL55L2 | E13: 5990 | F13: =ROUND(E13*(1-$B$1),0) | G13: 3 года | H13: https://luxhomme.store/products/airgrill | I13: https://luxhomme.store/products/airgrill?utm_source=yandex&utm_medium=cpc&utm_campaign=lux_search_aerogrili_{campaign_id}&utm_content=airchef_{ad_id}_{source_type}&utm_term={keyword} | J13: https://luxhomme.store/products/airgrill?utm_source=yandex&utm_medium=cpc&utm_campaign=lux_epk_aerogrili_{campaign_id}&utm_content=airchef_{ad_id}_{source_type}&utm_term={keyword} | K13: https://luxhomme.store/products/airgrill?utm_source=yandex&utm_medium=cpc&utm_campaign=lux_feed_{campaign_id}&utm_content=airchef_{ad_id}_{source_type}&utm_term={keyword}
A14: 11 | B14: Аэрогриль Luxhommè AirChef Dual Pro (2 чаши) | C14: Аэрогрили | D14: AEROGRIL2CHASHI | E14: 16990 | F14: =ROUND(E14*(1-$B$1),0) | G14: 3 года | H14: https://luxhomme.store/products/airgrill-dual-pro | I14: https://luxhomme.store/products/airgrill-dual-pro?utm_source=yandex&utm_medium=cpc&utm_campaign=lux_search_aerogrili_{campaign_id}&utm_content=airchef-dual-pro_{ad_id}_{source_type}&utm_term={keyword} | J14: https://luxhomme.store/products/airgrill-dual-pro?utm_source=yandex&utm_medium=cpc&utm_campaign=lux_epk_aerogrili_{campaign_id}&utm_content=airchef-dual-pro_{ad_id}_{source_type}&utm_term={keyword} | K14: https://luxhomme.store/products/airgrill-dual-pro?utm_source=yandex&utm_medium=cpc&utm_campaign=lux_feed_{campaign_id}&utm_content=airchef-dual-pro_{ad_id}_{source_type}&utm_term={keyword}
A15: 12 | B15: Виброплатформа uFit 2D Standard | C15: Виброплатформы | D15: VIPLATB | E15: 6190 | F15: =ROUND(E15*(1-$B$1),0) | G15: 2 года | H15: https://luxhomme.store/products/ufit-2d | I15: https://luxhomme.store/products/ufit-2d?utm_source=yandex&utm_medium=cpc&utm_campaign=lux_search_vibro_{campaign_id}&utm_content=ufit-2d_{ad_id}_{source_type}&utm_term={keyword} | J15: https://luxhomme.store/products/ufit-2d?utm_source=yandex&utm_medium=cpc&utm_campaign=lux_epk_vibro_{campaign_id}&utm_content=ufit-2d_{ad_id}_{source_type}&utm_term={keyword} | K15: https://luxhomme.store/products/ufit-2d?utm_source=yandex&utm_medium=cpc&utm_campaign=lux_feed_{campaign_id}&utm_content=ufit-2d_{ad_id}_{source_type}&utm_term={keyword}
... A18: 15 | B18: Робот мойщик Luxhommè uClean Max | C18: Роботы-мойщики окон | D18: ROBOTOKONKVADR | E18: 9990 | F18: =ROUND(E18*(1-$B$1),0) | G18: 3 года | H18: https://luxhomme.store/products/window | I18: https://luxhomme.store/products/window?utm_source=yandex&utm_medium=cpc&utm_campaign=lux_search_okna_{campaign_id}&utm_content=uclean-max_{ad_id}_{source_type}&utm_term={keyword} | J18: https://luxhomme.store/products/window?utm_source=yandex&utm_medium=cpc&utm_campaign=lux_epk_okna_{campaign_id}&utm_content=uclean-max_{ad_id}_{source_type}&utm_term={keyword} | K18: https://luxhomme.store/products/window?utm_source=yandex&utm_medium=cpc&utm_campaign=lux_feed_{campaign_id}&utm_content=uclean-max_{ad_id}_{source_type}&utm_term={keyword}

Sheet Aqvion Pro
A1: Вертикальный моющий пылесос Aqvion Pro
A2: Страница | B2: https://luxhomme.store/products/vertikalnyj-moyushhij-pylesos-aqvion-pro
A3: SKU | B3: VACCLWASH
A4: Цена, ₽ | B4: 19990
A5: С промокодом, ₽ | B5: =ROUND(B4*(1-Товары!$B$1),0)
A6: Промокод | B6: DIRECT20
A7: Категория | B7: Пылесосы
A9: УТП (факты из карточки)
A10: • | B10: Сухая и влажная уборка 2 в 1
A11: • | B11: Беспроводной, аккумулятор 5000 мАч
A12: • | B12: До 55–60 минут в эко-режиме, 28 минут на максимуме
A13: • | B13: Всасывание 15 000 Па
A14: • | B14: Самоочистка и сушка на базе
A15: • | B15: Электролиз воды
A16: • | B16: LED-подсветка, наклон 170°
A17: • | B17: Голосовые подсказки, IPX4
A18: • | B18: Баки 550 и 600 мл
A19: • | B19: Гарантия 3 года
A21: Семантика
A22: Группа | B22: Фраза | C22: Частотность
A23: Тип + покупка | B23: вертикальный моющий пылесос купить | C23: 10486
A24: Тип + покупка | B24: моющий вертикальный пылесос для дома купить | C24: 1724
A25: Тип + покупка | B25: вертикальный моющий пылесос цена | C25: 1567
A26: Тип + покупка | B26: недорогие вертикальные моющие пылесосы | C26: 1215
A27: Тип + покупка | B27: бюджетный вертикальный моющий пылесос | C27: 1000
A28: Тип + покупка | B28: моющие беспроводные вертикальные пылесосы цены | C28: 547
A29: Самоочистка и база | B29: вертикальные моющие пылесосы с сушкой | C29: 2192
A30: Самоочистка и база | B30: моющий пылесос вертикальный станция | C30: 2117
A31: Самоочистка и база | B31: моющий пылесос вертикальный со станцией | C31: 1104
A32: Беспроводной | B32: беспроводные моющие пылесосы для дома вертикальные | C32: 9882
A33: Назначение | B33: вертикальный моющий пылесос для дома | C33: 23105
A34: Назначение | B34: вертикальный моющий пылесос сухая | C34: 9907
... A47: Тип | B47: вертикальный моющий пылесос с подсветкой | C47: 548
A48: Модель | B48: aqvion pro
A49: Модель | B49: пылесос aqvion
A50: Модель | B50: aqvion pro купить
A52: Минус-слова товара (+ общие и конкуренты — лист «Минус-слова»)
A53: Товар | B53: робот, ручной, автомобильный, машины, щетка, валик, фильтр, аккумулятор, средство, сменные, запасные
A54: Конкуренты | B54: dyson, дайсон, dreame, дриме, дрими, дреаме, dream, roborock, роборок, tineco, тинеко, xiaomi, сяоми, ксиоми, karcher, керхер, tefal, тефаль, polaris, поларис, kitfort, китфорт, redmond, редмонд, philips, филипс, bosch, бош, samsung, самсунг, lg, vitek, витек, thomas, томас, deerma, jimmy, hwnd, atvel, атвел, puppyoo, viomi, midea, electrolux, haier, x clean, f16, ultimate, neatsvor, karingbee, chovery, ксиаоми, house up
A56: Объявления — Поиск
A57: № | B57: Заголовок 1 | C57: ≤56 | D57: Заголовок 2 | E57: ≤30 | F57: Текст | G57: ≤81 | H57: Отображаемая ссылка (≤20)
A58: 1 | B58: Вертикальный моющий пылесос Aqvion Pro со скидкой 20% | C58: =LEN(B58) | D58: Самоочистка и сушка | E58: =LEN(D58) | F58: Беспроводной, 15 000 Па, до 60 минут работы. Промокод DIRECT20 на сайте. | G58: =LEN(F58) | H58: Aqvion-Pro
A59: 2 | B59: Беспроводной моющий пылесос с самоочисткой | C59: =LEN(B59) | D59: Скидка 20% на сайте | E59: =LEN(D59) | F59: Aqvion Pro: сушка на базе, LED-подсветка, наклон 170°. Гарантия 3 года. | G59: =LEN(F59) | H59: Aqvion-Pro
A60: 3 | B60: Купить моющий пылесос Aqvion Pro за 15 992 ₽ | C60: =LEN(B60) | D60: Промокод DIRECT20 | E60: =LEN(D60) | F60: Баки 550 и 600 мл, аккумулятор 5000 мАч, голосовые подсказки, IPX4. | G60: =LEN(F60) | H60: Aqvion-Pro
A61: Ссылка (UTM) | B61: https://luxhomme.store/products/vertikalnyj-moyushhij-pylesos-aqvion-pro?utm_source=yandex&utm_medium=cpc&utm_campaign=lux_search_pylesosy_{campaign_id}&utm_content=aqvion-pro_{ad_id}_{source_type}&utm_term={keyword}
A63: Быстрые ссылки
A64: Название | B64: Описание | C64: ≤60 | D64: Ссылка (UTM) | H64: Название ≤30
A65: Каталог техники | B65: Пылесосы, швабры, кофемашины, аэрогрили | C65: =LEN(B65) | D65: https://luxhomme.store/catalog?utm_source=yandex&utm_medium=cpc&utm_campaign=lux_search_pylesosy_{campaign_id}&utm_content=aqvion-pro_sitelink_{ad_id}_{source_type}&utm_term={keyword} | H65: =LEN(A65)
A66: Доставка и оплата | B66: Пункты выдачи и курьер Ozon, срок после ввода адреса | C66: =LEN(B66) | D66: https://luxhomme.store/delivery?utm_source=yandex&utm_medium=cpc&utm_campaign=lux_search_pylesosy_{campaign_id}&utm_content=aqvion-pro_sitelink_{ad_id}_{source_type}&utm_term={keyword} | H66: =LEN(A66)
A67: Сервис и гарантия | B67: Бесплатный вывоз СДЭК при гарантийном случае | C67: =LEN(B67) | D67: https://luxhomme.store/service?utm_source=yandex&utm_medium=cpc&utm_campaign=lux_search_pylesosy_{campaign_id}&utm_content=aqvion-pro_sitelink_{ad_id}_{source_type}&utm_term={keyword} | H67: =LEN(A67)
A68: Моющий пылесос Cleneo Pro | B68: Пар и распыление: полы, ковры, мебель, авто | C68: =LEN(B68) | D68: https://luxhomme.store/products/kompaktnyj-moyushhij-pylesos-cleneo-pro?utm_source=yandex&utm_medium=cpc&utm_campaign=lux_search_pylesosy_{campaign_id}&utm_content=aqvion-pro_sitelink_{ad_id}_{source_type}&utm_term={keyword} | H68: =LEN(A68)
A70: Уточнения
A71: Уточнение | B71: ≤25
A72: Гарантия 3 года | B72: =LEN(A72)
A73: Скидка 20% по промокоду | B73: =LEN(A73)
A74: Доставка через Ozon | B74: =LEN(A74)
A75: Служба заботы 9–21 МСК | B75: =LEN(A75)
A76: Сервисный центр в РФ | B76: =LEN(A76)
A78: Объявления — Сети (РСЯ, ЕПК)
A79: № | B79: Заголовок | C79: ≤56 | D79: Текст | E79: ≤81 | F79: Бриф на картинку | H79: Фото с сайта
A80: 1 | B80: Моющий пылесос с самоочисткой и сушкой со скидкой 20% | C80: =LEN(B80) | D80: Aqvion Pro: беспроводной, 15 000 Па, до 60 минут. Промокод DIRECT20 на сайте. | E80: =LEN(D80) | F80: Пылесос на базе + след чистого пола с подсветкой; надпись «Самоочистка и сушка». Форматы: квадрат 1:1 и широкий 16:9; фото товара с карточки, светлый фон, плашка «−20% по промокоду» | H80: https://luxhomme.store/wp-content/uploads/2026/05/VMP-stranitsa-tovara-12.png
A81: 2 | B81: Вертикальный моющий пылесос Aqvion Pro | C81: =LEN(B81) | D81: Самоочистка на базе, LED-подсветка. С промокодом 15 992 ₽ вместо 19 990 ₽. | E81: =LEN(D81) | F81: Пылесос на базе + след чистого пола с подсветкой; надпись «Самоочистка и сушка». Форматы: квадрат 1:1 и широкий 16:9; фото товара с карточки, светлый фон, плашка «−20% по промокоду» | H81: https://luxhomme.store/wp-content/uploads/2026/05/VMP-stranitsa-tovara-12.png
A82: Ссылка (UTM) | B82: https://luxhomme.store/products/vertikalnyj-moyushhij-pylesos-aqvion-pro?utm_source=yandex&utm_medium=cpc&utm_campaign=lux_epk_pylesosy_{campaign_id}&utm_content=aqvion-pro_{ad_id}_{source_type}&utm_term={keyword}
A84: Ссылки с UTM
A85: Поиск | B85: https://luxhomme.store/products/vertikalnyj-moyushhij-pylesos-aqvion-pro?utm_source=yandex&utm_medium=cpc&utm_campaign=lux_search_pylesosy_{campaign_id}&utm_content=aqvion-pro_{ad_id}_{source_type}&utm_term={keyword}
A86: Сети | B86: https://luxhomme.store/products/vertikalnyj-moyushhij-pylesos-aqvion-pro?utm_source=yandex&utm_medium=cpc&utm_campaign=lux_epk_pylesosy_{campaign_id}&utm_content=aqvion-pro_{ad_id}_{source_type}&utm_term={keyword}
A87: Фид | B87: https://luxhomme.store/products/vertikalnyj-moyushhij-pylesos-aqvion-pro?utm_source=yandex&utm_medium=cpc&utm_campaign=lux_feed_{campaign_id}&utm_content=aqvion-pro_{ad_id}_{source_type}&utm_term={keyword}

Sheet Cleneo Pro
A1: Компактный моющий пылесос Cleneo Pro
A2: Страница | B2: https://luxhomme.store/products/kompaktnyj-moyushhij-pylesos-cleneo-pro
A3: SKU | B3: VACCLCOMPACT
A4: Цена, ₽ | B4: 16990
A5: С промокодом, ₽ | B5: =ROUND(B4*(1-Товары!$B$1),0)
A6: Промокод | B6: DIRECT20
A7: Категория | B7: Пылесосы
A9: УТП (факты из карточки)
A10: • | B10: Для дома и автомобиля: полы, ковры, мягкая мебель, салон
A11: • | B11: Пар 20–26 г/мин или распыление воды
A12: • | B12: Всасывание от 15 000 Па, 1400 Вт
A13: • | B13: Нагрев пара за 30 секунд
A14: • | B14: Баки: чистая вода 1,8 л, грязная 1,2 л
A15: • | B15: 11 насадок + 2 адаптера
A16: • | B16: Сухая и влажная уборка, 4 режима
A17: • | B17: Кабель 4,5 м, радиус 6,5 м
A18: • | B18: Гарантия 3 года
A20: Семантика
A21: Группа | B21: Фраза
A22: Тип + покупка | B22: моющий пылесос купить
A23: Тип + покупка | B23: моющий пылесос для дома купить
A24: Тип + покупка | B24: компактный моющий пылесос
A25: Тип + покупка | B25: моющий пылесос цена
A26: Химчистка мебели | B26: моющий пылесос для мебели
A27: Химчистка мебели | B27: моющий пылесос для химчистки мебели
A28: Химчистка мебели | B28: пылесос для химчистки дивана
A29: Химчистка мебели | B29: пылесос для химчистки мягкой мебели
A30: Химчистка мебели | B30: моющий пылесос для дивана
A31: Химчистка мебели | B31: пылесос для химчистки купить
A32: Авто | B32: моющий пылесос для автомобиля
... A42: Модель | B42: cleneo pro купить
A44: Минус-слова товара (+ общие и конкуренты — лист «Минус-слова»)
A45: Товар | B45: вертикальный, робот, беспроводной, аккумуляторный, ручной, средство, шампунь, сменные
A46: Конкуренты | B46: dyson, дайсон, dreame, дриме, дрими, дреаме, dream, roborock, роборок, tineco, тинеко, xiaomi, сяоми, ксиоми, karcher, керхер, tefal, тефаль, polaris, поларис, kitfort, китфорт, redmond, редмонд, philips, филипс, bosch, бош, samsung, самсунг, lg, vitek, витек, thomas, томас, deerma, jimmy, hwnd, atvel, атвел, puppyoo, viomi, midea, electrolux, haier, x clean, f16, ultimate, neatsvor, karingbee, chovery, ксиаоми, house up
A48: Объявления — Поиск
A49: № | B49: Заголовок 1 | C49: ≤56 | D49: Заголовок 2 | E49: ≤30 | F49: Текст | G49: ≤81 | H49: Отображаемая ссылка (≤20)
A50: 1 | B50: Моющий пылесос Cleneo Pro для дома и авто со скидкой 20% | C50: =LEN(B50) | D50: Пар и распыление | E50: =LEN(D50) | F50: Полы, ковры, мебель и салон авто. 11 насадок, баки 1,8 и 1,2 л. Промокод DIRECT20 | G50: =LEN(F50) | H50: Cleneo-Pro
A51: 2 | B51: Пылесос для химчистки мебели и ковров с паром | C51: =LEN(B51) | D51: Скидка 20% на сайте | E51: =LEN(D51) | F51: Cleneo Pro: всасывание от 15 000 Па, пар 20–26 г/мин, нагрев 30 секунд. | G51: =LEN(F51) | H51: Cleneo-Pro
A52: 3 | B52: Купить моющий пылесос Cleneo Pro за 13 592 ₽ | C52: =LEN(B52) | D52: Промокод DIRECT20 | E52: =LEN(D52) | F52: Сухая и влажная уборка, 4 режима, кабель 4,5 м. Гарантия 3 года. | G52: =LEN(F52) | H52: Cleneo-Pro
A53: Ссылка (UTM) | B53: https://luxhomme.store/products/kompaktnyj-moyushhij-pylesos-cleneo-pro?utm_source=yandex&utm_medium=cpc&utm_campaign=lux_search_pylesosy_{campaign_id}&utm_content=cleneo-pro_{ad_id}_{source_type}&utm_term={keyword}
A55: Быстрые ссылки
A56: Название | B56: Описание | C56: ≤60 | D56: Ссылка (UTM) | H56: Название ≤30
A57: Каталог техники | B57: Пылесосы, швабры, кофемашины, аэрогрили | C57: =LEN(B57) | D57: https://luxhomme.store/catalog?utm_source=yandex&utm_medium=cpc&utm_campaign=lux_search_pylesosy_{campaign_id}&utm_content=cleneo-pro_sitelink_{ad_id}_{source_type}&utm_term={keyword} | H57: =LEN(A57)
A58: Доставка и оплата | B58: Пункты выдачи и курьер Ozon, срок после ввода адреса | C58: =LEN(B58) | D58: https://luxhomme.store/delivery?utm_source=yandex&utm_medium=cpc&utm_campaign=lux_search_pylesosy_{campaign_id}&utm_content=cleneo-pro_sitelink_{ad_id}_{source_type}&utm_term={keyword} | H58: =LEN(A58)
A59: Сервис и гарантия | B59: Бесплатный вывоз СДЭК при гарантийном случае | C59: =LEN(B59) | D59: https://luxhomme.store/service?utm_source=yandex&utm_medium=cpc&utm_campaign=lux_search_pylesosy_{campaign_id}&utm_content=cleneo-pro_sitelink_{ad_id}_{source_type}&utm_term={keyword} | H59: =LEN(A59)
A60: Моющий пылесос Aqvion Pro | B60: Беспроводной, 15 000 Па, самоочистка и сушка | C60: =LEN(B60) | D60: https://luxhomme.store/products/vertikalnyj-moyushhij-pylesos-aqvion-pro?utm_source=yandex&utm_medium=cpc&utm_campaign=lux_search_pylesosy_{campaign_id}&utm_content=cleneo-pro_sitelink_{ad_id}_{source_type}&utm_term={keyword} | H60: =LEN(A60)
A62: Уточнения
A63: Уточнение | B63: ≤25
A64: Гарантия 3 года | B64: =LEN(A64)
A65: Скидка 20% по промокоду | B65: =LEN(A65)
A66: Доставка через Ozon | B66: =LEN(A66)
A67: Служба заботы 9–21 МСК | B67: =LEN(A67)
A68: Сервисный центр в РФ | B68: =LEN(A68)
A70: Объявления — Сети (РСЯ, ЕПК)
A71: № | B71: Заголовок | C71: ≤56 | D71: Текст | E71: ≤81 | F71: Бриф на картинку | H71: Фото с сайта
A72: 1 | B72: Химчистка дивана и салона авто дома со скидкой 20% | C72: =LEN(B72) | D72: Cleneo Pro: пар и распыление воды, 11 насадок. Промокод DIRECT20 на сайте. | E72: =LEN(D72) | F72: Чистка дивана (до/после полосой) + салон авто во второй картинке; надпись «Дом и авто». Форматы: квадрат 1:1 и широкий 16:9; фото товара с карточки, светлый фон, плашка «−20% по промокоду» | H72: https://luxhomme.store/wp-content/uploads/2026/05/VMP-stranitsa-tovara-1-2.png
A73: 2 | B73: Компактный моющий пылесос с паром | C73: =LEN(B73) | D73: Полы, ковры, мебель, авто. С промокодом 13 592 ₽ вместо 16 990 ₽. | E73: =LEN(D73) | F73: Чистка дивана (до/после полосой) + салон авто во второй картинке; надпись «Дом и авто». Форматы: квадрат 1:1 и широкий 16:9; фото товара с карточки, светлый фон, плашка «−20% по промокоду» | H73: https://luxhomme.store/wp-content/uploads/2026/05/VMP-stranitsa-tovara-1-2.png
A74: Ссылка (UTM) | B74: https://luxhomme.store/products/kompaktnyj-moyushhij-pylesos-cleneo-pro?utm_source=yandex&utm_medium=cpc&utm_campaign=lux_epk_pylesosy_{campaign_id}&utm_content=cleneo-pro_{ad_id}_{source_type}&utm_term={keyword}
A76: Ссылки с UTM
A77: Поиск | B77: https://luxhomme.store/products/kompaktnyj-moyushhij-pylesos-cleneo-pro?utm_source=yandex&utm_medium=cpc&utm_campaign=lux_search_pylesosy_{campaign_id}&utm_content=cleneo-pro_{ad_id}_{source_type}&utm_term={keyword}
A78: Сети | B78: https://luxhomme.store/products/kompaktnyj-moyushhij-pylesos-cleneo-pro?utm_source=yandex&utm_medium=cpc&utm_campaign=lux_epk_pylesosy_{campaign_id}&utm_content=cleneo-pro_{ad_id}_{source_type}&utm_term={keyword}
A79: Фид | B79: https://luxhomme.store/products/kompaktnyj-moyushhij-pylesos-cleneo-pro?utm_source=yandex&utm_medium=cpc&utm_campaign=lux_feed_{campaign_id}&utm_content=cleneo-pro_{ad_id}_{source_type}&utm_term={keyword}

Sheet Aerlyn
A1: Вертикальный сухой пылесос Aerlyn
A2: Страница | B2: https://luxhomme.store/products/vertikalnyj-suhoj-pylesos-aerlyn
A3: SKU | B3: VACCLDRY
A4: Цена, ₽ | B4: 15990
A5: С промокодом, ₽ | B5: =ROUND(B4*(1-Товары!$B$1),0)
A6: Промокод | B6: DIRECT20
A7: Категория | B7: Пылесосы
A9: УТП (факты из карточки)
A10: • | B10: 2 в 1: вертикальный и ручной
A11: • | B11: Всасывание до 35 кПа, 420 Вт
A12: • | B12: Аккумулятор 2200 мАч, до 60 минут
A13: • | B13: Режимы ECO / FLOOR / CARPET / TURBO + авто
A14: • | B14: Турбощётка, 8 насадок
A15: • | B15: HEPA-фильтр, бак 330 мл
A16: • | B16: Вес 2,35 кг, поворот 180°
A17: • | B17: Настенное крепление для зарядки
A18: • | B18: Гарантия 3 года
A20: Семантика
A21: Группа | B21: Фраза
A22: Тип + покупка | B22: вертикальный пылесос купить
A23: Тип + покупка | B23: беспроводной пылесос купить
A24: Тип + покупка | B24: беспроводной пылесос для дома купить
A25: Тип + покупка | B25: вертикальный пылесос цена
A26: Тип + покупка | B26: аккумуляторный пылесос вертикальный
A27: Назначение | B27: вертикальный пылесос для дома
A28: Назначение | B28: беспроводной вертикальный пылесос
A29: Назначение | B29: вертикальный пылесос для ковров
A30: Назначение | B30: беспроводной пылесос для квартиры
A31: Характеристики | B31: вертикальный пылесос 2 в 1
A32: Характеристики | B32: пылесос вертикальный ручной 2 в 1
... A39: Модель | B39: aerlyn купить
A41: Минус-слова товара (+ общие и конкуренты — лист «Минус-слова»)
A42: Товар | B42: моющий, моет, влажной, влажная, робот, автомобильный, машины, строительный, садовый, щетка, сменные
A43: Конкуренты | B43: dyson, дайсон, dreame, дриме, дрими, дреаме, dream, roborock, роборок, tineco, тинеко, xiaomi, сяоми, ксиоми, karcher, керхер, tefal, тефаль, polaris, поларис, kitfort, китфорт, redmond, редмонд, philips, филипс, bosch, бош, samsung, самсунг, lg, vitek, витек, thomas, томас, deerma, jimmy, hwnd, atvel, атвел, puppyoo, viomi, midea, electrolux, haier, x clean, f16, ultimate, neatsvor, karingbee, chovery, ксиаоми, house up
A45: Объявления — Поиск
A46: № | B46: Заголовок 1 | C46: ≤56 | D46: Заголовок 2 | E46: ≤30 | F46: Текст | G46: ≤81 | H46: Отображаемая ссылка (≤20)
A47: 1 | B47: Беспроводной пылесос Aerlyn 2 в 1 — до 35 кПа | C47: =LEN(B47) | D47: Скидка 20% на сайте | E47: =LEN(D47) | F47: До 60 минут работы, HEPA-фильтр, турбощётка, 8 насадок. Промокод DIRECT20. | G47: =LEN(F47) | H47: Aerlyn
A48: 2 | B48: Вертикальный беспроводной пылесос с HEPA-фильтром | C48: =LEN(B48) | D48: Скидка 20% по промокоду | E48: =LEN(D48) | F48: Aerlyn: режимы ECO, FLOOR, CARPET, TURBO и авто. Гарантия 3 года. | G48: =LEN(F48) | H48: Aerlyn
A49: 3 | B49: Купить вертикальный пылесос Aerlyn за 12 792 ₽ | C49: =LEN(B49) | D49: Промокод DIRECT20 | E49: =LEN(D49) | F49: 420 Вт, бак 330 мл, вес 2,35 кг, настенное крепление для зарядки. | G49: =LEN(F49) | H49: Aerlyn
A50: Ссылка (UTM) | B50: https://luxhomme.store/products/vertikalnyj-suhoj-pylesos-aerlyn?utm_source=yandex&utm_medium=cpc&utm_campaign=lux_search_pylesosy_{campaign_id}&utm_content=aerlyn_{ad_id}_{source_type}&utm_term={keyword}
A52: Быстрые ссылки
A53: Название | B53: Описание | C53: ≤60 | D53: Ссылка (UTM) | H53: Название ≤30
A54: Каталог техники | B54: Пылесосы, швабры, кофемашины, аэрогрили | C54: =LEN(B54) | D54: https://luxhomme.store/catalog?utm_source=yandex&utm_medium=cpc&utm_campaign=lux_search_pylesosy_{campaign_id}&utm_content=aerlyn_sitelink_{ad_id}_{source_type}&utm_term={keyword} | H54: =LEN(A54)
A55: Доставка и оплата | B55: Пункты выдачи и курьер Ozon, срок после ввода адреса | C55: =LEN(B55) | D55: https://luxhomme.store/delivery?utm_source=yandex&utm_medium=cpc&utm_campaign=lux_search_pylesosy_{campaign_id}&utm_content=aerlyn_sitelink_{ad_id}_{source_type}&utm_term={keyword} | H55: =LEN(A55)
A56: Сервис и гарантия | B56: Бесплатный вывоз СДЭК при гарантийном случае | C56: =LEN(B56) | D56: https://luxhomme.store/service?utm_source=yandex&utm_medium=cpc&utm_campaign=lux_search_pylesosy_{campaign_id}&utm_content=aerlyn_sitelink_{ad_id}_{source_type}&utm_term={keyword} | H56: =LEN(A56)
A57: Моющий пылесос Aqvion Pro | B57: Беспроводной, 15 000 Па, самоочистка и сушка | C57: =LEN(B57) | D57: https://luxhomme.store/products/vertikalnyj-moyushhij-pylesos-aqvion-pro?utm_source=yandex&utm_medium=cpc&utm_campaign=lux_search_pylesosy_{campaign_id}&utm_content=aerlyn_sitelink_{ad_id}_{source_type}&utm_term={keyword} | H57: =LEN(A57)
A59: Уточнения
A60: Уточнение | B60: ≤25
A61: Гарантия 3 года | B61: =LEN(A61)
A62: Скидка 20% по промокоду | B62: =LEN(A62)
A63: Доставка через Ozon | B63: =LEN(A63)
A64: Служба заботы 9–21 МСК | B64: =LEN(A64)
A65: Сервисный центр в РФ | B65: =LEN(A65)
A67: Объявления — Сети (РСЯ, ЕПК)
A68: № | B68: Заголовок | C68: ≤56 | D68: Текст | E68: ≤81 | F68: Бриф на картинку | H68: Фото с сайта
A69: 1 | B69: Беспроводной пылесос 2 в 1 со скидкой 20% | C69: =LEN(B69) | D69: Aerlyn: до 35 кПа, до 60 минут, HEPA-фильтр. Промокод DIRECT20 на сайте. | E69: =LEN(D69) | F69: Пылесос в интерьере + ручной режим на диване; надпись «2 в 1 · до 60 минут». Форматы: квадрат 1:1 и широкий 16:9; фото товара с карточки, светлый фон, плашка «−20% по промокоду» | H69: https://luxhomme.store/wp-content/uploads/2026/06/VMP-stranitsa-tovara-98.png
A70: 2 | B70: Вертикальный пылесос Aerlyn с турбощёткой | C70: =LEN(B70) | D70: 4 режима и авто, 8 насадок. С промокодом 12 792 ₽ вместо 15 990 ₽. | E70: =LEN(D70) | F70: Пылесос в интерьере + ручной режим на диване; надпись «2 в 1 · до 60 минут». Форматы: квадрат 1:1 и широкий 16:9; фото товара с карточки, светлый фон, плашка «−20% по промокоду» | H70: https://luxhomme.store/wp-content/uploads/2026/06/VMP-stranitsa-tovara-98.png
A71: Ссылка (UTM) | B71: https://luxhomme.store/products/vertikalnyj-suhoj-pylesos-aerlyn?utm_source=yandex&utm_medium=cpc&utm_campaign=lux_epk_pylesosy_{campaign_id}&utm_content=aerlyn_{ad_id}_{source_type}&utm_term={keyword}
A73: Ссылки с UTM
A74: Поиск | B74: https://luxhomme.store/products/vertikalnyj-suhoj-pylesos-aerlyn?utm_source=yandex&utm_medium=cpc&utm_campaign=lux_search_pylesosy_{campaign_id}&utm_content=aerlyn_{ad_id}_{source_type}&utm_term={keyword}
A75: Сети | B75: https://luxhomme.store/products/vertikalnyj-suhoj-pylesos-aerlyn?utm_source=yandex&utm_medium=cpc&utm_campaign=lux_epk_pylesosy_{campaign_id}&utm_content=aerlyn_{ad_id}_{source_type}&utm_term={keyword}
A76: Фид | B76: https://luxhomme.store/products/vertikalnyj-suhoj-pylesos-aerlyn?utm_source=yandex&utm_medium=cpc&utm_campaign=lux_feed_{campaign_id}&utm_content=aerlyn_{ad_id}_{source_type}&utm_term={keyword}

Sheet EcoSteam Pro
A1: Паровая швабра Luxhommè EcoSteam Pro
A2: Страница | B2: https://luxhomme.store/products/ecosteam-pro
A3: SKU | B3: SHVPAREKCHB2
A4: Цена, ₽ | B4: 5990
A5: С промокодом, ₽ | B5: =ROUND(B4*(1-Товары!$B$1),0)
A6: Промокод | B6: DIRECT20
A7: Категория | B7: Паровые швабры
A9: УТП (факты из карточки)
A10: • | B10: Нагрев за 30 секунд
A11: • | B11: 1400 Вт, пар до 120 °C, подача 18–20 / 25–30 г/мин
A12: • | B12: 22 насадки в комплекте: окна, швы, металл, углы
A13: • | B13: Освежает полы и разглаживает одежду
A14: • | B14: Поворот головки 270°, вес 1,83 кг
A15: • | B15: Бак 400 мл, шнур 5 м, 25 минут непрерывной работы
A16: • | B16: Гарантия 12 месяцев
A18: Семантика
A19: Группа | B19: Фраза
A20: Тип + покупка | B20: паровая швабра купить
A21: Тип + покупка | B21: купить паровую швабру для дома
A22: Тип + покупка | B22: паровая швабра цена
A23: Тип + покупка | B23: паровая швабра недорого
A24: Тип + покупка | B24: паровая швабра интернет магазин
A25: Тип + покупка | B25: швабра с паром купить
A26: Назначение | B26: паровая швабра для дома
A27: Назначение | B27: паровая швабра для пола
A28: Назначение | B28: паровая швабра для плитки
A29: Назначение | B29: паровая швабра для уборки квартиры
A30: Назначение | B30: швабра с паром для пола
... A39: Модель | B39: швабра ecosteam pro купить
A41: Минус-слова товара (+ общие и конкуренты — лист «Минус-слова»)
A42: Товар | B42: ручная, отжим, отжимом, тряпка, веревочная, spin, сменные, запасные, салфетки, щетка
A43: Конкуренты | B43: karcher, керхер, tefal, тефаль, kitfort, китфорт, polaris, поларис, bissell, биссел, black decker, vileda, виледа, leifheit, vax, endever, clatronic, kelli, bort, redmond, редмонд, philips, филипс
A45: Объявления — Поиск
A46: № | B46: Заголовок 1 | C46: ≤56 | D46: Заголовок 2 | E46: ≤30 | F46: Текст | G46: ≤81 | H46: Отображаемая ссылка (≤20)
A47: 1 | B47: Паровая швабра EcoSteam Pro — 22 насадки | C47: =LEN(B47) | D47: Скидка 20% по промокоду | E47: =LEN(D47) | F47: Нагрев за 30 секунд, пар до 120 °C, бак 400 мл, шнур 5 м. Промокод DIRECT20. | G47: =LEN(F47) | H47: EcoSteam-Pro
A48: 2 | B48: Паровая швабра для дома — нагрев за 30 секунд | C48: =LEN(B48) | D48: Скидка 20% на сайте | E48: =LEN(D48) | F48: EcoSteam Pro: 1400 Вт, 22 насадки, поворот 270°. С промокодом — 4 792 ₽. | G48: =LEN(F48) | H48: EcoSteam-Pro
A49: 3 | B49: Купить паровую швабру EcoSteam Pro за 4 792 ₽ | C49: =LEN(B49) | D49: Промокод DIRECT20 | E49: =LEN(D49) | F49: Пар до 120 °C, 22 насадки, вес 1,83 кг. Гарантия 12 месяцев. | G49: =LEN(F49) | H49: EcoSteam-Pro
A50: Ссылка (UTM) | B50: https://luxhomme.store/products/ecosteam-pro?utm_source=yandex&utm_medium=cpc&utm_campaign=lux_search_shvabry_{campaign_id}&utm_content=ecosteam-pro_{ad_id}_{source_type}&utm_term={keyword}
A52: Быстрые ссылки
A53: Название | B53: Описание | C53: ≤60 | D53: Ссылка (UTM) | H53: Название ≤30
A54: Каталог техники | B54: Пылесосы, швабры, кофемашины, аэрогрили | C54: =LEN(B54) | D54: https://luxhomme.store/catalog?utm_source=yandex&utm_medium=cpc&utm_campaign=lux_search_shvabry_{campaign_id}&utm_content=ecosteam-pro_sitelink_{ad_id}_{source_type}&utm_term={keyword} | H54: =LEN(A54)
A55: Доставка и оплата | B55: Пункты выдачи и курьер Ozon, срок после ввода адреса | C55: =LEN(B55) | D55: https://luxhomme.store/delivery?utm_source=yandex&utm_medium=cpc&utm_campaign=lux_search_shvabry_{campaign_id}&utm_content=ecosteam-pro_sitelink_{ad_id}_{source_type}&utm_term={keyword} | H55: =LEN(A55)
A56: Сервис и гарантия | B56: Бесплатный вывоз СДЭК при гарантийном случае | C56: =LEN(B56) | D56: https://luxhomme.store/service?utm_source=yandex&utm_medium=cpc&utm_campaign=lux_search_shvabry_{campaign_id}&utm_content=ecosteam-pro_sitelink_{ad_id}_{source_type}&utm_term={keyword} | H56: =LEN(A56)
A57: Паровая швабра AirSteam Pro | B57: 1800 Вт, пар до 150 °C, отпаривание одежды | C57: =LEN(B57) | D57: https://luxhomme.store/products/steamly-pro?utm_source=yandex&utm_medium=cpc&utm_campaign=lux_search_shvabry_{campaign_id}&utm_content=ecosteam-pro_sitelink_{ad_id}_{source_type}&utm_term={keyword} | H57: =LEN(A57)
A59: Уточнения
A60: Уточнение | B60: ≤25
A61: Гарантия 12 месяцев | B61: =LEN(A61)
A62: Скидка 20% по промокоду | B62: =LEN(A62)
A63: Доставка через Ozon | B63: =LEN(A63)
A64: Служба заботы 9–21 МСК | B64: =LEN(A64)
A65: Сервисный центр в РФ | B65: =LEN(A65)
A67: Объявления — Сети (РСЯ, ЕПК)
A68: № | B68: Заголовок | C68: ≤56 | D68: Текст | E68: ≤81 | F68: Бриф на картинку | H68: Фото с сайта
A69: 1 | B69: Паровая швабра EcoSteam Pro со скидкой 20% | C69: =LEN(B69) | D69: 22 насадки, пар до 120 °C, нагрев за 30 секунд. Промокод DIRECT20 на сайте. | E69: =LEN(D69) | F69: Швабра на чистом полу с облаком пара + веер насадок; надпись «22 насадки». Форматы: квадрат 1:1 и широкий 16:9; фото товара с карточки, светлый фон, плашка «−20% по промокоду» | H69: https://luxhomme.store/wp-content/uploads/2017/10/SHvabra-EcoSteam-Pro-1a.jpg
A70: 2 | B70: Уборка паром: нагрев швабры за 30 секунд | C70: =LEN(B70) | D70: EcoSteam Pro — 1400 Вт, бак 400 мл. С промокодом 4 792 ₽ вместо 5 990 ₽. | E70: =LEN(D70) | F70: Швабра на чистом полу с облаком пара + веер насадок; надпись «22 насадки». Форматы: квадрат 1:1 и широкий 16:9; фото товара с карточки, светлый фон, плашка «−20% по промокоду» | H70: https://luxhomme.store/wp-content/uploads/2017/10/SHvabra-EcoSteam-Pro-1a.jpg
A71: Ссылка (UTM) | B71: https://luxhomme.store/products/ecosteam-pro?utm_source=yandex&utm_medium=cpc&utm_campaign=lux_epk_shvabry_{campaign_id}&utm_content=ecosteam-pro_{ad_id}_{source_type}&utm_term={keyword}
A73: Ссылки с UTM
A74: Поиск | B74: https://luxhomme.store/products/ecosteam-pro?utm_source=yandex&utm_medium=cpc&utm_campaign=lux_search_shvabry_{campaign_id}&utm_content=ecosteam-pro_{ad_id}_{source_type}&utm_term={keyword}
A75: Сети | B75: https://luxhomme.store/products/ecosteam-pro?utm_source=yandex&utm_medium=cpc&utm_campaign=lux_epk_shvabry_{campaign_id}&utm_content=ecosteam-pro_{ad_id}_{source_type}&utm_term={keyword}
A76: Фид | B76: https://luxhomme.store/products/ecosteam-pro?utm_source=yandex&utm_medium=cpc&utm_campaign=lux_feed_{campaign_id}&utm_content=ecosteam-pro_{ad_id}_{source_type}&utm_term={keyword}

Sheet AirSteam Pro
A1: Паровая швабра Luxhommè AirSteam Pro
A2: Страница | B2: https://luxhomme.store/products/steamly-pro
A3: SKU | B3: SHVPAR3D
A4: Цена, ₽ | B4: 10990
A5: С промокодом, ₽ | B5: =ROUND(B4*(1-Товары!$B$1),0)
A6: Промокод | B6: DIRECT20
A7: Категория | B7: Паровые швабры
A9: УТП (факты из карточки)
A10: • | B10: 1800 Вт, пар до 150 °C
A11: • | B11: 3 режима пара, 15–48 г/мин
A12: • | B12: Нагрев 25–30 секунд
A13: • | B13: 25 насадок в комплекте
A14: • | B14: Отпаривание одежды
A15: • | B15: Аромакапсулы, автоотключение
A16: • | B16: Бак 450 мл
A17: • | B17: Гарантия 3 года
A19: Семантика
A20: Группа | B20: Фраза
A21: Тип + покупка | B21: паровая швабра купить
A22: Тип + покупка | B22: купить паровую швабру
A23: Тип + покупка | B23: паровая швабра цена
A24: Тип + покупка | B24: паровая швабра для дома купить
A25: С отпаривателем | B25: паровая швабра с отпаривателем
A26: С отпаривателем | B26: паровая швабра отпариватель для одежды
A27: С отпаривателем | B27: швабра отпариватель
A28: С отпаривателем | B28: паровая швабра и отпариватель
A29: Характеристики | B29: мощная паровая швабра
A30: Характеристики | B30: паровая швабра 1800 вт
A31: Характеристики | B31: паровая швабра с регулировкой пара
... A40: Модель | B40: швабра airsteam pro купить
A42: Минус-слова товара (+ общие и конкуренты — лист «Минус-слова»)
A43: Товар | B43: ручная, отжим, отжимом, тряпка, веревочная, spin, сменные, запасные, салфетки, щетка, вертикальный
A44: Конкуренты | B44: karcher, керхер, tefal, тефаль, kitfort, китфорт, polaris, поларис, bissell, биссел, black decker, vileda, виледа, leifheit, vax, endever, clatronic, kelli, bort, redmond, редмонд, philips, филипс
A46: Объявления — Поиск
A47: № | B47: Заголовок 1 | C47: ≤56 | D47: Заголовок 2 | E47: ≤30 | F47: Текст | G47: ≤81 | H47: Отображаемая ссылка (≤20)
A48: 1 | B48: Паровая швабра AirSteam Pro — пар до 150 °C | C48: =LEN(B48) | D48: Скидка 20% на сайте | E48: =LEN(D48) | F48: 1800 Вт, 3 режима пара, 25 насадок, отпаривание одежды. Промокод DIRECT20. | G48: =LEN(F48) | H48: AirSteam-Pro
A49: 2 | B49: Паровая швабра с отпариванием одежды | C49: =LEN(B49) | D49: Скидка 20% по промокоду | E49: =LEN(D49) | F49: AirSteam Pro: нагрев 25–30 с, бак 450 мл, автоотключение. Гарантия 3 года. | G49: =LEN(F49) | H49: AirSteam-Pro
A50: 3 | B50: Купить паровую швабру AirSteam Pro за 8 792 ₽ | C50: =LEN(B50) | D50: Промокод DIRECT20 | E50: =LEN(D50) | F50: До 48 г/мин пара, 3 режима, поддержка аромакапсул. Гарантия 3 года. | G50: =LEN(F50) | H50: AirSteam-Pro
A51: Ссылка (UTM) | B51: https://luxhomme.store/products/steamly-pro?utm_source=yandex&utm_medium=cpc&utm_campaign=lux_search_shvabry_{campaign_id}&utm_content=airsteam-pro_{ad_id}_{source_type}&utm_term={keyword}
A53: Быстрые ссылки
A54: Название | B54: Описание | C54: ≤60 | D54: Ссылка (UTM) | H54: Название ≤30
A55: Каталог техники | B55: Пылесосы, швабры, кофемашины, аэрогрили | C55: =LEN(B55) | D55: https://luxhomme.store/catalog?utm_source=yandex&utm_medium=cpc&utm_campaign=lux_search_shvabry_{campaign_id}&utm_content=airsteam-pro_sitelink_{ad_id}_{source_type}&utm_term={keyword} | H55: =LEN(A55)
A56: Доставка и оплата | B56: Пункты выдачи и курьер Ozon, срок после ввода адреса | C56: =LEN(B56) | D56: https://luxhomme.store/delivery?utm_source=yandex&utm_medium=cpc&utm_campaign=lux_search_shvabry_{campaign_id}&utm_content=airsteam-pro_sitelink_{ad_id}_{source_type}&utm_term={keyword} | H56: =LEN(A56)
A57: Сервис и гарантия | B57: Бесплатный вывоз СДЭК при гарантийном случае | C57: =LEN(B57) | D57: https://luxhomme.store/service?utm_source=yandex&utm_medium=cpc&utm_campaign=lux_search_shvabry_{campaign_id}&utm_content=airsteam-pro_sitelink_{ad_id}_{source_type}&utm_term={keyword} | H57: =LEN(A57)
A58: Паровая швабра SC-100 Max | B58: 1500 Вт, давление 4,5 бар, 9 насадок | C58: =LEN(B58) | D58: https://luxhomme.store/products/sc-100?utm_source=yandex&utm_medium=cpc&utm_campaign=lux_search_shvabry_{campaign_id}&utm_content=airsteam-pro_sitelink_{ad_id}_{source_type}&utm_term={keyword} | H58: =LEN(A58)
A60: Уточнения
A61: Уточнение | B61: ≤25
A62: Гарантия 3 года | B62: =LEN(A62)
A63: Скидка 20% по промокоду | B63: =LEN(A63)
A64: Доставка через Ozon | B64: =LEN(A64)
A65: Служба заботы 9–21 МСК | B65: =LEN(A65)
A66: Сервисный центр в РФ | B66: =LEN(A66)
A68: Объявления — Сети (РСЯ, ЕПК)
A69: № | B69: Заголовок | C69: ≤56 | D69: Текст | E69: ≤81 | F69: Бриф на картинку | H69: Фото с сайта
A70: 1 | B70: Паровая швабра и отпариватель — скидка 20% | C70: =LEN(B70) | D70: AirSteam Pro: 1800 Вт, до 150 °C, 25 насадок. Промокод DIRECT20 на сайте. | E70: =LEN(D70) | F70: Швабра на полу + отпаривание рубашки на вешалке; надпись «Полы и одежда». Форматы: квадрат 1:1 и широкий 16:9; фото товара с карточки, светлый фон, плашка «−20% по промокоду» | H70: https://luxhomme.store/wp-content/uploads/2026/04/VMP-stranitsa-tovara-33.png
A71: 2 | B71: Пар до 150 °C для полов и одежды | C71: =LEN(B71) | D71: 3 режима пара, бак 450 мл. С промокодом 8 792 ₽ вместо 10 990 ₽. | E71: =LEN(D71) | F71: Швабра на полу + отпаривание рубашки на вешалке; надпись «Полы и одежда». Форматы: квадрат 1:1 и широкий 16:9; фото товара с карточки, светлый фон, плашка «−20% по промокоду» | H71: https://luxhomme.store/wp-content/uploads/2026/04/VMP-stranitsa-tovara-33.png
A72: Ссылка (UTM) | B72: https://luxhomme.store/products/steamly-pro?utm_source=yandex&utm_medium=cpc&utm_campaign=lux_epk_shvabry_{campaign_id}&utm_content=airsteam-pro_{ad_id}_{source_type}&utm_term={keyword}
A74: Ссылки с UTM
A75: Поиск | B75: https://luxhomme.store/products/steamly-pro?utm_source=yandex&utm_medium=cpc&utm_campaign=lux_search_shvabry_{campaign_id}&utm_content=airsteam-pro_{ad_id}_{source_type}&utm_term={keyword}
A76: Сети | B76: https://luxhomme.store/products/steamly-pro?utm_source=yandex&utm_medium=cpc&utm_campaign=lux_epk_shvabry_{campaign_id}&utm_content=airsteam-pro_{ad_id}_{source_type}&utm_term={keyword}
A77: Фид | B77: https://luxhomme.store/products/steamly-pro?utm_source=yandex&utm_medium=cpc&utm_campaign=lux_feed_{campaign_id}&utm_content=airsteam-pro_{ad_id}_{source_type}&utm_term={keyword}

Sheet SC-100 Max
A1: Паровая швабра Luxhommè SC-100 Max
A2: Страница | B2: https://luxhomme.store/products/sc-100
A3: SKU | B3: SHVPAR7V1CH
A4: Цена, ₽ | B4: 7990
A5: С промокодом, ₽ | B5: =ROUND(B4*(1-Товары!$B$1),0)
A6: Промокод | B6: DIRECT20
A7: Категория | B7: Паровые швабры
A9: УТП (факты из карточки)
A10: • | B10: 1500 Вт, пар до 150 °C
A11: • | B11: Давление 4,5 бар
A12: • | B12: 2 режима подачи пара: 12–16 / 25–32 г/мин
A13: • | B13: Нагрев 30 секунд
A14: • | B14: 9 насадок + 3 микрофибры
A15: • | B15: Бак 360 мл, шнур 5 м
A16: • | B16: Гарантия 3 года
A18: Семантика
A19: Группа | B19: Фраза
A20: Тип + покупка | B20: паровая швабра купить
A21: Тип + покупка | B21: купить паровую швабру для пола
A22: Тип + покупка | B22: паровая швабра цена
A23: Тип + покупка | B23: швабра с паром купить
A24: Назначение | B24: паровая швабра для дома
A25: Назначение | B25: паровая швабра для пола
A26: Назначение | B26: швабра с паром для пола
A27: Назначение | B27: паровой очиститель для пола
A28: Характеристики | B28: паровая швабра с давлением
A29: Характеристики | B29: паровая швабра 1500 вт
A30: Характеристики | B30: паровая швабра с микрофиброй
... A36: Модель | B36: швабра sc100
A38: Минус-слова товара (+ общие и конкуренты — лист «Минус-слова»)
A39: Товар | B39: ручная, отжим, отжимом, тряпка, веревочная, spin, сменные, запасные, салфетки, щетка
A40: Конкуренты | B40: karcher, керхер, tefal, тефаль, kitfort, китфорт, polaris, поларис, bissell, биссел, black decker, vileda, виледа, leifheit, vax, endever, clatronic, kelli, bort, redmond, редмонд, philips, филипс
A42: Объявления — Поиск
A43: № | B43: Заголовок 1 | C43: ≤56 | D43: Заголовок 2 | E43: ≤30 | F43: Текст | G43: ≤81 | H43: Отображаемая ссылка (≤20)
A44: 1 | B44: Паровая швабра SC-100 Max — давление 4,5 бар | C44: =LEN(B44) | D44: Скидка 20% на сайте | E44: =LEN(D44) | F44: 1500 Вт, пар до 150 °C, 2 режима подачи пара, 9 насадок. Промокод DIRECT20. | G44: =LEN(F44) | H44: SC-100-Max
A45: 2 | B45: Паровая швабра с 9 насадками и микрофиброй | C45: =LEN(B45) | D45: Скидка 20% по промокоду | E45: =LEN(D45) | F45: SC-100 Max: нагрев 30 секунд, бак 360 мл, шнур 5 м. Гарантия 3 года. | G45: =LEN(F45) | H45: SC-100-Max
A46: 3 | B46: Купить паровую швабру SC-100 Max за 6 392 ₽ | C46: =LEN(B46) | D46: Промокод DIRECT20 | E46: =LEN(D46) | F46: До 32 г/мин пара и до 150 °C. 9 насадок и 3 микрофибры в комплекте. | G46: =LEN(F46) | H46: SC-100-Max
A47: Ссылка (UTM) | B47: https://luxhomme.store/products/sc-100?utm_source=yandex&utm_medium=cpc&utm_campaign=lux_search_shvabry_{campaign_id}&utm_content=sc-100-max_{ad_id}_{source_type}&utm_term={keyword}
A49: Быстрые ссылки
A50: Название | B50: Описание | C50: ≤60 | D50: Ссылка (UTM) | H50: Название ≤30
A51: Каталог техники | B51: Пылесосы, швабры, кофемашины, аэрогрили | C51: =LEN(B51) | D51: https://luxhomme.store/catalog?utm_source=yandex&utm_medium=cpc&utm_campaign=lux_search_shvabry_{campaign_id}&utm_content=sc-100-max_sitelink_{ad_id}_{source_type}&utm_term={keyword} | H51: =LEN(A51)
A52: Доставка и оплата | B52: Пункты выдачи и курьер Ozon, срок после ввода адреса | C52: =LEN(B52) | D52: https://luxhomme.store/delivery?utm_source=yandex&utm_medium=cpc&utm_campaign=lux_search_shvabry_{campaign_id}&utm_content=sc-100-max_sitelink_{ad_id}_{source_type}&utm_term={keyword} | H52: =LEN(A52)
A53: Сервис и гарантия | B53: Бесплатный вывоз СДЭК при гарантийном случае | C53: =LEN(B53) | D53: https://luxhomme.store/service?utm_source=yandex&utm_medium=cpc&utm_campaign=lux_search_shvabry_{campaign_id}&utm_content=sc-100-max_sitelink_{ad_id}_{source_type}&utm_term={keyword} | H53: =LEN(A53)
A54: Паровая швабра EcoSteam Pro | B54: 1400 Вт, 22 насадки, нагрев за 30 секунд | C54: =LEN(B54) | D54: https://luxhomme.store/products/ecosteam-pro?utm_source=yandex&utm_medium=cpc&utm_campaign=lux_search_shvabry_{campaign_id}&utm_content=sc-100-max_sitelink_{ad_id}_{source_type}&utm_term={keyword} | H54: =LEN(A54)
A56: Уточнения
A57: Уточнение | B57: ≤25
A58: Гарантия 3 года | B58: =LEN(A58)
A59: Скидка 20% по промокоду | B59: =LEN(A59)
A60: Доставка через Ozon | B60: =LEN(A60)
A61: Служба заботы 9–21 МСК | B61: =LEN(A61)
A62: Сервисный центр в РФ | B62: =LEN(A62)
A64: Объявления — Сети (РСЯ, ЕПК)
A65: № | B65: Заголовок | C65: ≤56 | D65: Текст | E65: ≤81 | F65: Бриф на картинку | H65: Фото с сайта
A66: 1 | B66: Паровая швабра SC-100 Max со скидкой 20% | C66: =LEN(B66) | D66: Пар до 150 °C, давление 4,5 бар, 9 насадок. Промокод DIRECT20 на сайте. | E66: =LEN(D66) | F66: Швабра крупным планом, пар над плиткой; надпись «4,5 бар · 150 °C». Форматы: квадрат 1:1 и широкий 16:9; фото товара с карточки, светлый фон, плашка «−20% по промокоду» | H66: https://luxhomme.store/wp-content/uploads/2025/09/VMP-stranitsa-tovara-29.png
A67: 2 | B67: Нагрев за 30 секунд и пар до 150 °C | C67: =LEN(B67) | D67: SC-100 Max: 1500 Вт, бак 360 мл. С промокодом 6 392 ₽ вместо 7 990 ₽. | E67: =LEN(D67) | F67: Швабра крупным планом, пар над плиткой; надпись «4,5 бар · 150 °C». Форматы: квадрат 1:1 и широкий 16:9; фото товара с карточки, светлый фон, плашка «−20% по промокоду» | H67: https://luxhomme.store/wp-content/uploads/2025/09/VMP-stranitsa-tovara-29.png
A68: Ссылка (UTM) | B68: https://luxhomme.store/products/sc-100?utm_source=yandex&utm_medium=cpc&utm_campaign=lux_epk_shvabry_{campaign_id}&utm_content=sc-100-max_{ad_id}_{source_type}&utm_term={keyword}
A70: Ссылки с UTM
A71: Поиск | B71: https://luxhomme.store/products/sc-100?utm_source=yandex&utm_medium=cpc&utm_campaign=lux_search_shvabry_{campaign_id}&utm_content=sc-100-max_{ad_id}_{source_type}&utm_term={keyword}
A72: Сети | B72: https://luxhomme.store/products/sc-100?utm_source=yandex&utm_medium=cpc&utm_campaign=lux_epk_shvabry_{campaign_id}&utm_content=sc-100-max_{ad_id}_{source_type}&utm_term={keyword}
A73: Фид | B73: https://luxhomme.store/products/sc-100?utm_source=yandex&utm_medium=cpc&utm_campaign=lux_feed_{campaign_id}&utm_content=sc-100-max_{ad_id}_{source_type}&utm_term={keyword}

Sheet CoffeeMaker Classic
A1: Кофемашина Luxhommè CoffeeMaker Classic
A2: Страница | B2: https://luxhomme.store/products/coffee
A3: SKU | B3: COFMASHCAP4V1
A4: Цена, ₽ | B4: 9990
A5: С промокодом, ₽ | B5: =ROUND(B4*(1-Товары!$B$1),0)
A6: Промокод | B6: DIRECT20
A7: Категория | B7: Кофемашины
A9: УТП (факты из карточки)
A10: • | B10: Капсулы формата Nespresso, чалды и молотый кофе
A11: • | B11: Помпа 19 бар, 1450 Вт
A12: • | B12: Капучинатор: латте, капучино, эспрессо
A13: • | B13: Горячие и холодные напитки
A14: • | B14: Тёплый кофе через 20 секунд, шум 60–65 дБ
A15: • | B15: Компактная: ширина 11,7 см
A16: • | B16: Бак 0,6 л
A17: • | B17: Гарантия 3 года
A19: Семантика
A20: Группа | B20: Фраза
A21: Тип + покупка | B21: капсульная кофемашина купить
A22: Тип + покупка | B22: кофемашина капсульная для дома
A23: Тип + покупка | B23: кофемашина для дома купить
A24: Тип + покупка | B24: кофеварка капсульная
A25: Тип + покупка | B25: кофемашина недорого
A26: Форматы кофе | B26: кофемашина для капсул nespresso
A27: Форматы кофе | B27: кофемашина под капсулы неспрессо
A28: Форматы кофе | B28: кофемашина для чалд
A29: Форматы кофе | B29: кофемашина для молотого кофе и капсул
A30: Форматы кофе | B30: кофемашина капсулы и молотый
A31: Характеристики | B31: компактная кофемашина для дома
... A37: Модель | B37: кофемашина coffeemaker
A39: Минус-слова товара (+ общие и конкуренты — лист «Минус-слова»)
A40: Товар | B40: зерновая, зерно, кофемолка, рожковая, капельная, турка, гейзерная, декальцинация, чистка, таблетки, многоразовые
A41: Конкуренты | B41: delonghi, делонги, philips, филипс, saeco, krups, крупс, jura, nivona, melitta, bosch, siemens, polaris, поларис, kitfort, китфорт, redmond, редмонд, garlyn, гарлин, vitek, xiaomi, smeg, gaggia, sage, breville, oursson, starwind, dauken
A43: Объявления — Поиск
A44: № | B44: Заголовок 1 | C44: ≤56 | D44: Заголовок 2 | E44: ≤30 | F44: Текст | G44: ≤81 | H44: Отображаемая ссылка (≤20)
A45: 1 | B45: Кофемашина: капсулы Nespresso, чалды и молотый | C45: =LEN(B45) | D45: Скидка 20% на сайте | E45: =LEN(D45) | F45: CoffeeMaker Classic: 19 бар, капучинатор, горячий и холодный кофе. Код DIRECT20 | G45: =LEN(F45) | H45: CoffeeMaker-Classic
A46: 2 | B46: Компактная капсульная кофемашина — ширина 11,7 см | C46: =LEN(B46) | D46: Скидка 20% по промокоду | E46: =LEN(D46) | F46: Кофе через 20 секунд, тихая работа 60–65 дБ, помпа 19 бар. Гарантия 3 года. | G46: =LEN(F46) | H46: CoffeeMaker-Classic
A47: 3 | B47: Купить кофемашину CoffeeMaker Classic за 7 992 ₽ | C47: =LEN(B47) | D47: Промокод DIRECT20 | E47: =LEN(D47) | F47: Эспрессо, латте и капучино дома. Капсулы формата Nespresso, чалды, молотый. | G47: =LEN(F47) | H47: CoffeeMaker-Classic
A48: Ссылка (UTM) | B48: https://luxhomme.store/products/coffee?utm_source=yandex&utm_medium=cpc&utm_campaign=lux_search_kofe_{campaign_id}&utm_content=coffeemaker-classic_{ad_id}_{source_type}&utm_term={keyword}
A50: Быстрые ссылки
A51: Название | B51: Описание | C51: ≤60 | D51: Ссылка (UTM) | H51: Название ≤30
A52: Каталог техники | B52: Пылесосы, швабры, кофемашины, аэрогрили | C52: =LEN(B52) | D52: https://luxhomme.store/catalog?utm_source=yandex&utm_medium=cpc&utm_campaign=lux_search_kofe_{campaign_id}&utm_content=coffeemaker-classic_sitelink_{ad_id}_{source_type}&utm_term={keyword} | H52: =LEN(A52)
A53: Доставка и оплата | B53: Пункты выдачи и курьер Ozon, срок после ввода адреса | C53: =LEN(B53) | D53: https://luxhomme.store/delivery?utm_source=yandex&utm_medium=cpc&utm_campaign=lux_search_kofe_{campaign_id}&utm_content=coffeemaker-classic_sitelink_{ad_id}_{source_type}&utm_term={keyword} | H53: =LEN(A53)
A54: Сервис и гарантия | B54: Бесплатный вывоз СДЭК при гарантийном случае | C54: =LEN(B54) | D54: https://luxhomme.store/service?utm_source=yandex&utm_medium=cpc&utm_campaign=lux_search_kofe_{campaign_id}&utm_content=coffeemaker-classic_sitelink_{ad_id}_{source_type}&utm_term={keyword} | H54: =LEN(A54)
A55: Кофемашина Caffio Professional | B55: Рожковая, ULKA 20 бар, автокапучинатор | C55: =LEN(B55) | D55: https://luxhomme.store/products/caffio-professional?utm_source=yandex&utm_medium=cpc&utm_campaign=lux_search_kofe_{campaign_id}&utm_content=coffeemaker-classic_sitelink_{ad_id}_{source_type}&utm_term={keyword} | H55: =LEN(A55)
A57: Уточнения
A58: Уточнение | B58: ≤25
A59: Гарантия 3 года | B59: =LEN(A59)
A60: Скидка 20% по промокоду | B60: =LEN(A60)
A61: Доставка через Ozon | B61: =LEN(A61)
A62: Служба заботы 9–21 МСК | B62: =LEN(A62)
A63: Сервисный центр в РФ | B63: =LEN(A63)
A65: Объявления — Сети (РСЯ, ЕПК)
A66: № | B66: Заголовок | C66: ≤56 | D66: Текст | E66: ≤81 | F66: Бриф на картинку | H66: Фото с сайта
A67: 1 | B67: Капсульная кофемашина 3 формата кофе со скидкой 20% | C67: =LEN(B67) | D67: CoffeeMaker Classic: 19 бар, капучинатор. Промокод DIRECT20 на сайте. | E67: =LEN(D67) | F67: Кофемашина на кухонной столешнице + капсула, чалда и молотый кофе рядом; надпись «3 формата кофе». Форматы: квадрат 1:1 и широкий 16:9; фото товара с карточки, светлый фон, плашка «−20% по промокоду» | H67: https://luxhomme.store/wp-content/uploads/2017/10/VMP-stranitsa-tovara-19.png
A68: 2 | B68: Кофе через 20 секунд: компактная кофемашина | C68: =LEN(B68) | D68: Ширина 11,7 см, горячий и холодный кофе. 7 992 ₽ с промокодом. | E68: =LEN(D68) | F68: Кофемашина на кухонной столешнице + капсула, чалда и молотый кофе рядом; надпись «3 формата кофе». Форматы: квадрат 1:1 и широкий 16:9; фото товара с карточки, светлый фон, плашка «−20% по промокоду» | H68: https://luxhomme.store/wp-content/uploads/2017/10/VMP-stranitsa-tovara-19.png
A69: Ссылка (UTM) | B69: https://luxhomme.store/products/coffee?utm_source=yandex&utm_medium=cpc&utm_campaign=lux_epk_kofe_{campaign_id}&utm_content=coffeemaker-classic_{ad_id}_{source_type}&utm_term={keyword}
A71: Ссылки с UTM
A72: Поиск | B72: https://luxhomme.store/products/coffee?utm_source=yandex&utm_medium=cpc&utm_campaign=lux_search_kofe_{campaign_id}&utm_content=coffeemaker-classic_{ad_id}_{source_type}&utm_term={keyword}
A73: Сети | B73: https://luxhomme.store/products/coffee?utm_source=yandex&utm_medium=cpc&utm_campaign=lux_epk_kofe_{campaign_id}&utm_content=coffeemaker-classic_{ad_id}_{source_type}&utm_term={keyword}
A74: Фид | B74: https://luxhomme.store/products/coffee?utm_source=yandex&utm_medium=cpc&utm_campaign=lux_feed_{campaign_id}&utm_content=coffeemaker-classic_{ad_id}_{source_type}&utm_term={keyword}

Sheet Caffio Professional
A1: Кофемашина рожковая Luxhommè Caffio Professional
A2: Страница | B2: https://luxhomme.store/products/caffio-professional
A3: SKU | B3: COFMASHROZH
A4: Цена, ₽ | B4: 17990
A5: С промокодом, ₽ | B5: =ROUND(B4*(1-Товары!$B$1),0)
A6: Промокод | B6: DIRECT20
A7: Категория | B7: Кофемашины
A9: УТП (факты из карточки)
A10: • | B10: Рожковая 4 в 1: молотый, капсулы Nespresso и Dolce Gusto, чалды ESE
A11: • | B11: Итальянская помпа ULKA 20 бар
A12: • | B12: Thermoblock — нагрев от 10 секунд
A13: • | B13: Автоматический капучинатор с регулировкой пены
A14: • | B14: Горячий и холодный кофе
A15: • | B15: Бак 1,5 л, молочник 500 мл
A16: • | B16: Гарантия 3 года
A18: Семантика
A19: Группа | B19: Фраза
A20: Тип + покупка | B20: рожковая кофемашина купить
A21: Тип + покупка | B21: рожковая кофемашина для дома
A22: Тип + покупка | B22: кофемашина рожкового типа
A23: Тип + покупка | B23: кофемашина для дома с капучинатором
A24: Характеристики | B24: рожковая кофемашина с капучинатором
A25: Характеристики | B25: кофемашина с автоматическим капучинатором
A26: Характеристики | B26: кофеварка рожковая с капучинатором
A27: Характеристики | B27: кофемашина 20 бар
A28: Характеристики | B28: кофемашина с молочником
A29: Характеристики | B29: кофемашина для холодного кофе
A30: Характеристики | B30: кофемашина 4 в 1
... A35: Модель | B35: кофемашина caffio
A37: Минус-слова товара (+ общие и конкуренты — лист «Минус-слова»)
A38: Товар | B38: зерновая, зерно, кофемолка, капельная, турка, гейзерная, декальцинация, чистка, таблетки, многоразовые
A39: Конкуренты | B39: delonghi, делонги, philips, филипс, saeco, krups, крупс, jura, nivona, melitta, bosch, siemens, polaris, поларис, kitfort, китфорт, redmond, редмонд, garlyn, гарлин, vitek, xiaomi, smeg, gaggia, sage, breville, oursson, starwind, dauken
A41: Объявления — Поиск
A42: № | B42: Заголовок 1 | C42: ≤56 | D42: Заголовок 2 | E42: ≤30 | F42: Текст | G42: ≤81 | H42: Отображаемая ссылка (≤20)
A43: 1 | B43: Рожковая кофемашина Caffio Professional со скидкой 20% | C43: =LEN(B43) | D43: Автокапучинатор | E43: =LEN(D43) | F43: Помпа ULKA 20 бар, Thermoblock, 4 формата кофе. Промокод DIRECT20 на сайте. | G43: =LEN(F43) | H43: Caffio-Professional
A44: 2 | B44: Кофемашина 4 в 1: молотый, капсулы и чалды ESE | C44: =LEN(B44) | D44: Скидка 20% на сайте | E44: =LEN(D44) | F44: Caffio Professional: регулировка пены, горячий и холодный кофе. Гарантия 3 года. | G44: =LEN(F44) | H44: Caffio-Professional
A45: 3 | B45: Купить рожковую кофемашину Caffio за 14 392 ₽ | C45: =LEN(B45) | D45: Промокод DIRECT20 | E45: =LEN(D45) | F45: Бак 1,5 л и молочник 500 мл, нагрев Thermoblock от 10 секунд. | G45: =LEN(F45) | H45: Caffio-Professional
A46: Ссылка (UTM) | B46: https://luxhomme.store/products/caffio-professional?utm_source=yandex&utm_medium=cpc&utm_campaign=lux_search_kofe_{campaign_id}&utm_content=caffio-professional_{ad_id}_{source_type}&utm_term={keyword}
A48: Быстрые ссылки
A49: Название | B49: Описание | C49: ≤60 | D49: Ссылка (UTM) | H49: Название ≤30
A50: Каталог техники | B50: Пылесосы, швабры, кофемашины, аэрогрили | C50: =LEN(B50) | D50: https://luxhomme.store/catalog?utm_source=yandex&utm_medium=cpc&utm_campaign=lux_search_kofe_{campaign_id}&utm_content=caffio-professional_sitelink_{ad_id}_{source_type}&utm_term={keyword} | H50: =LEN(A50)
A51: Доставка и оплата | B51: Пункты выдачи и курьер Ozon, срок после ввода адреса | C51: =LEN(B51) | D51: https://luxhomme.store/delivery?utm_source=yandex&utm_medium=cpc&utm_campaign=lux_search_kofe_{campaign_id}&utm_content=caffio-professional_sitelink_{ad_id}_{source_type}&utm_term={keyword} | H51: =LEN(A51)
A52: Сервис и гарантия | B52: Бесплатный вывоз СДЭК при гарантийном случае | C52: =LEN(B52) | D52: https://luxhomme.store/service?utm_source=yandex&utm_medium=cpc&utm_campaign=lux_search_kofe_{campaign_id}&utm_content=caffio-professional_sitelink_{ad_id}_{source_type}&utm_term={keyword} | H52: =LEN(A52)
A53: Кофемашина CremaX | B53: Встроенная кофемолка, 20 степеней помола | C53: =LEN(B53) | D53: https://luxhomme.store/products/cremax?utm_source=yandex&utm_medium=cpc&utm_campaign=lux_search_kofe_{campaign_id}&utm_content=caffio-professional_sitelink_{ad_id}_{source_type}&utm_term={keyword} | H53: =LEN(A53)
A55: Уточнения
A56: Уточнение | B56: ≤25
A57: Гарантия 3 года | B57: =LEN(A57)
A58: Скидка 20% по промокоду | B58: =LEN(A58)
A59: Доставка через Ozon | B59: =LEN(A59)
A60: Служба заботы 9–21 МСК | B60: =LEN(A60)
A61: Сервисный центр в РФ | B61: =LEN(A61)
A63: Объявления — Сети (РСЯ, ЕПК)
A64: № | B64: Заголовок | C64: ≤56 | D64: Текст | E64: ≤81 | F64: Бриф на картинку | H64: Фото с сайта
A65: 1 | B65: Рожковая кофемашина с автокапучинатором со скидкой 20% | C65: =LEN(B65) | D65: Caffio Professional: 20 бар, 4 формата кофе. Промокод DIRECT20 на сайте. | E65: =LEN(D65) | F65: Кофемашина + чашка капучино с пенкой; надпись «Автокапучинатор · 20 бар». Форматы: квадрат 1:1 и широкий 16:9; фото товара с карточки, светлый фон, плашка «−20% по промокоду» | H65: https://luxhomme.store/wp-content/uploads/2026/09/Caffio-Professional-1.7.png
A66: 2 | B66: Капучино и латте дома с автокапучинатором | C66: =LEN(B66) | D66: Горячий и холодный кофе. С промокодом 14 392 ₽ вместо 17 990 ₽. | E66: =LEN(D66) | F66: Кофемашина + чашка капучино с пенкой; надпись «Автокапучинатор · 20 бар». Форматы: квадрат 1:1 и широкий 16:9; фото товара с карточки, светлый фон, плашка «−20% по промокоду» | H66: https://luxhomme.store/wp-content/uploads/2026/09/Caffio-Professional-1.7.png
A67: Ссылка (UTM) | B67: https://luxhomme.store/products/caffio-professional?utm_source=yandex&utm_medium=cpc&utm_campaign=lux_epk_kofe_{campaign_id}&utm_content=caffio-professional_{ad_id}_{source_type}&utm_term={keyword}
A69: Ссылки с UTM
A70: Поиск | B70: https://luxhomme.store/products/caffio-professional?utm_source=yandex&utm_medium=cpc&utm_campaign=lux_search_kofe_{campaign_id}&utm_content=caffio-professional_{ad_id}_{source_type}&utm_term={keyword}
A71: Сети | B71: https://luxhomme.store/products/caffio-professional?utm_source=yandex&utm_medium=cpc&utm_campaign=lux_epk_kofe_{campaign_id}&utm_content=caffio-professional_{ad_id}_{source_type}&utm_term={keyword}
A72: Фид | B72: https://luxhomme.store/products/caffio-professional?utm_source=yandex&utm_medium=cpc&utm_campaign=lux_feed_{campaign_id}&utm_content=caffio-professional_{ad_id}_{source_type}&utm_term={keyword}

Sheet CremaX
A1: Кофемашина автоматическая зерновая с капучинатором и кофемолкой CremaX
A2: Страница | B2: https://luxhomme.store/products/cremax
A3: SKU | B3: COFMASHPOMOL
A4: Цена, ₽ | B4: 47990
A5: С промокодом, ₽ | B5: =ROUND(B4*(1-Товары!$B$1),0)
A6: Промокод | B6: DIRECT20
A7: Категория | B7: Кофемашины
A9: УТП (факты из карточки)
A10: • | B10: 5 в 1: зерно, молотый, Nespresso, Dolce Gusto, чалды ESE
A11: • | B11: Встроенная кофемолка, 20 степеней помола, бункер 120 г
A12: • | B12: Помпа ULKA 20 бар, Thermoblock, нагрев от 25 секунд
A13: • | B13: Предсмачивание
A14: • | B14: 10 программ, горячий и холодный кофе
A15: • | B15: Автоматический съёмный капучинатор, регулировка пены
A16: • | B16: Бак 2 л, шум 50 дБ
A17: • | B17: Гарантия 3 года
A19: Семантика
A20: Группа | B20: Фраза
A21: Тип + покупка | B21: кофемашина с кофемолкой купить
A22: Тип + покупка | B22: кофемашина с кофемолкой для дома
A23: Тип + покупка | B23: кофемашина зерновая для дома купить
A24: Тип + покупка | B24: автоматическая кофемашина с капучинатором для дома
A25: Характеристики | B25: кофемашина со встроенной кофемолкой
A26: Характеристики | B26: рожковая кофемашина с кофемолкой
A27: Характеристики | B27: кофемашина зерновая с капучинатором
A28: Характеристики | B28: кофемашина 20 бар с кофемолкой
A29: Характеристики | B29: кофемашина с предсмачиванием
A30: Характеристики | B30: кофемашина для холодного кофе с кофемолкой
A31: Форматы кофе | B31: кофемашина для зерна и капсул
... A36: Модель | B36: crema x кофемашина
A38: Минус-слова товара (+ общие и конкуренты — лист «Минус-слова»)
A39: Товар | B39: капельная, турка, гейзерная, ручная, декальцинация, чистка, таблетки, многоразовые
A40: Конкуренты | B40: delonghi, делонги, philips, филипс, saeco, krups, крупс, jura, nivona, melitta, bosch, siemens, polaris, поларис, kitfort, китфорт, redmond, редмонд, garlyn, гарлин, vitek, xiaomi, smeg, gaggia, sage, breville, oursson, starwind, dauken
A42: Объявления — Поиск
A43: № | B43: Заголовок 1 | C43: ≤56 | D43: Заголовок 2 | E43: ≤30 | F43: Текст | G43: ≤81 | H43: Отображаемая ссылка (≤20)
A44: 1 | B44: Кофемашина с кофемолкой CremaX — скидка 20% | C44: =LEN(B44) | D44: Промокод DIRECT20 | E44: =LEN(D44) | F44: 20 степеней помола, помпа ULKA 20 бар, автокапучинатор, 10 программ. | G44: =LEN(F44) | H44: CremaX
A45: 2 | B45: Кофемашина 5 в 1: зерно, молотый, капсулы, ESE | C45: =LEN(B45) | D45: Скидка 20% на сайте | E45: =LEN(D45) | F45: CremaX: предсмачивание, холодный кофе, бак 2 л, нагрев от 25 с. Гарантия 3 года. | G45: =LEN(F45) | H45: CremaX
A46: 3 | B46: Купить кофемашину CremaX за 38 392 ₽ | C46: =LEN(B46) | D46: Промокод DIRECT20 | E46: =LEN(D46) | F46: Встроенная кофемолка, бункер 120 г. Горячий и холодный кофе, шум 50 дБ. | G46: =LEN(F46) | H46: CremaX
A47: Ссылка (UTM) | B47: https://luxhomme.store/products/cremax?utm_source=yandex&utm_medium=cpc&utm_campaign=lux_search_kofe_{campaign_id}&utm_content=cremax_{ad_id}_{source_type}&utm_term={keyword}
A49: Быстрые ссылки
A50: Название | B50: Описание | C50: ≤60 | D50: Ссылка (UTM) | H50: Название ≤30
A51: Каталог техники | B51: Пылесосы, швабры, кофемашины, аэрогрили | C51: =LEN(B51) | D51: https://luxhomme.store/catalog?utm_source=yandex&utm_medium=cpc&utm_campaign=lux_search_kofe_{campaign_id}&utm_content=cremax_sitelink_{ad_id}_{source_type}&utm_term={keyword} | H51: =LEN(A51)
A52: Доставка и оплата | B52: Пункты выдачи и курьер Ozon, срок после ввода адреса | C52: =LEN(B52) | D52: https://luxhomme.store/delivery?utm_source=yandex&utm_medium=cpc&utm_campaign=lux_search_kofe_{campaign_id}&utm_content=cremax_sitelink_{ad_id}_{source_type}&utm_term={keyword} | H52: =LEN(A52)
A53: Сервис и гарантия | B53: Бесплатный вывоз СДЭК при гарантийном случае | C53: =LEN(B53) | D53: https://luxhomme.store/service?utm_source=yandex&utm_medium=cpc&utm_campaign=lux_search_kofe_{campaign_id}&utm_content=cremax_sitelink_{ad_id}_{source_type}&utm_term={keyword} | H53: =LEN(A53)
A54: Кофемашина Caffio Professional | B54: Рожковая, ULKA 20 бар, автокапучинатор | C54: =LEN(B54) | D54: https://luxhomme.store/products/caffio-professional?utm_source=yandex&utm_medium=cpc&utm_campaign=lux_search_kofe_{campaign_id}&utm_content=cremax_sitelink_{ad_id}_{source_type}&utm_term={keyword} | H54: =LEN(A54)
A56: Уточнения
A57: Уточнение | B57: ≤25
A58: Гарантия 3 года | B58: =LEN(A58)
A59: Скидка 20% по промокоду | B59: =LEN(A59)
A60: Доставка через Ozon | B60: =LEN(A60)
A61: Служба заботы 9–21 МСК | B61: =LEN(A61)
A62: Сервисный центр в РФ | B62: =LEN(A62)
A64: Объявления — Сети (РСЯ, ЕПК)
A65: № | B65: Заголовок | C65: ≤56 | D65: Текст | E65: ≤81 | F65: Бриф на картинку | H65: Фото с сайта
A66: 1 | B66: Кофемашина со встроенной кофемолкой со скидкой 20% | C66: =LEN(B66) | D66: CremaX: 20 степеней помола, автокапучинатор. Промокод DIRECT20 на сайте. | E66: =LEN(D66) | F66: Кофемашина + зёрна в бункере и чашка эспрессо; надпись «Кофемолка внутри». Форматы: квадрат 1:1 и широкий 16:9; фото товара с карточки, светлый фон, плашка «−20% по промокоду» | H66: https://luxhomme.store/wp-content/uploads/2026/10/CremaX-1.1.jpg
A67: 2 | B67: Кофе из зёрен дома: CremaX 5 в 1 | C67: =LEN(B67) | D67: 10 программ, холодный кофе, бак 2 л. С промокодом 38 392 ₽ вместо 47 990 ₽. | E67: =LEN(D67) | F67: Кофемашина + зёрна в бункере и чашка эспрессо; надпись «Кофемолка внутри». Форматы: квадрат 1:1 и широкий 16:9; фото товара с карточки, светлый фон, плашка «−20% по промокоду» | H67: https://luxhomme.store/wp-content/uploads/2026/10/CremaX-1.1.jpg
A68: Ссылка (UTM) | B68: https://luxhomme.store/products/cremax?utm_source=yandex&utm_medium=cpc&utm_campaign=lux_epk_kofe_{campaign_id}&utm_content=cremax_{ad_id}_{source_type}&utm_term={keyword}
A70: Ссылки с UTM
A71: Поиск | B71: https://luxhomme.store/products/cremax?utm_source=yandex&utm_medium=cpc&utm_campaign=lux_search_kofe_{campaign_id}&utm_content=cremax_{ad_id}_{source_type}&utm_term={keyword}
A72: Сети | B72: https://luxhomme.store/products/cremax?utm_source=yandex&utm_medium=cpc&utm_campaign=lux_epk_kofe_{campaign_id}&utm_content=cremax_{ad_id}_{source_type}&utm_term={keyword}
A73: Фид | B73: https://luxhomme.store/products/cremax?utm_source=yandex&utm_medium=cpc&utm_campaign=lux_feed_{campaign_id}&utm_content=cremax_{ad_id}_{source_type}&utm_term={keyword}

Sheet AirChef
A1: Аэрогриль Luxhommè AirChef
A2: Страница | B2: https://luxhomme.store/products/airgrill
A3: SKU | B3: AEROGRIL55L2
A4: Цена, ₽ | B4: 5990
A5: С промокодом, ₽ | B5: =ROUND(B4*(1-Товары!$B$1),0)
A6: Промокод | B6: DIRECT20
A7: Категория | B7: Аэрогрили
A9: УТП (факты из карточки)
A10: • | B10: Чаша 5,5 л — на 2–4 человека
A11: • | B11: 1500 Вт, 35–200 °C
A12: • | B12: 12 программ
A13: • | B13: Смотровое окно с подсветкой
A14: • | B14: Режим сушки
A15: • | B15: Гарантия 3 года
A17: Семантика
A18: Группа | B18: Фраза
A19: Тип + покупка | B19: аэрогриль купить
A20: Тип + покупка | B20: аэрогриль для дома купить
A21: Тип + покупка | B21: аэрогриль цена
A22: Тип + покупка | B22: аэрогриль недорого
A23: Тип + покупка | B23: купить аэрогриль с окном
A24: Характеристики | B24: аэрогриль с окошком
A25: Характеристики | B25: аэрогриль со смотровым окном
A26: Характеристики | B26: аэрогриль 5 литров
A27: Характеристики | B27: аэрогриль 5.5 л
A28: Характеристики | B28: аэрогриль с функцией сушки
A29: Характеристики | B29: аэрогриль 1500 вт
... A35: Модель | B35: аэрогриль airchef
A37: Минус-слова товара (+ общие и конкуренты — лист «Минус-слова»)
A38: Товар | B38: рецепт, рецепты, рецептами, приготовить, готовить, сколько, минут, книга, пергамент, бумага, форма, решетка, подставка, две, двумя, двойной, двухкамерный, dual
A39: Конкуренты | B39: tefal, тефаль, philips, филипс, ninja, ниндзя, cosori, косори, xiaomi, redmond, редмонд, polaris, поларис, kitfort, китфорт, moulinex, мулинекс, instant, hotter, gfgril, oberhof, garlyn, гарлин, proficook, vitek, dexp, dauken
A41: Объявления — Поиск
A42: № | B42: Заголовок 1 | C42: ≤56 | D42: Заголовок 2 | E42: ≤30 | F42: Текст | G42: ≤81 | H42: Отображаемая ссылка (≤20)
A43: 1 | B43: Аэрогриль AirChef 5,5 л с окном — скидка 20% | C43: =LEN(B43) | D43: Промокод DIRECT20 | E43: =LEN(D43) | F43: 12 программ, 35–200 °C, подсветка камеры, режим сушки. Для 2–4 человек. | G43: =LEN(F43) | H43: AirChef
A44: 2 | B44: Аэрогриль для дома: 12 программ и сушка | C44: =LEN(B44) | D44: Скидка 20% на сайте | E44: =LEN(D44) | F44: AirChef: 1500 Вт, чаша 5,5 л, смотровое окно. Гарантия 3 года. | G44: =LEN(F44) | H44: AirChef
A45: 3 | B45: Купить аэрогриль AirChef за 4 792 ₽ | C45: =LEN(B45) | D45: Скидка 20% по промокоду | E45: =LEN(D45) | F45: Чаша 5,5 литра, окно с подсветкой, температура от 35 до 200 °C. | G45: =LEN(F45) | H45: AirChef
A46: Ссылка (UTM) | B46: https://luxhomme.store/products/airgrill?utm_source=yandex&utm_medium=cpc&utm_campaign=lux_search_aerogrili_{campaign_id}&utm_content=airchef_{ad_id}_{source_type}&utm_term={keyword}
A48: Быстрые ссылки
A49: Название | B49: Описание | C49: ≤60 | D49: Ссылка (UTM) | H49: Название ≤30
A50: Каталог техники | B50: Пылесосы, швабры, кофемашины, аэрогрили | C50: =LEN(B50) | D50: https://luxhomme.store/catalog?utm_source=yandex&utm_medium=cpc&utm_campaign=lux_search_aerogrili_{campaign_id}&utm_content=airchef_sitelink_{ad_id}_{source_type}&utm_term={keyword} | H50: =LEN(A50)
A51: Доставка и оплата | B51: Пункты выдачи и курьер Ozon, срок после ввода адреса | C51: =LEN(B51) | D51: https://luxhomme.store/delivery?utm_source=yandex&utm_medium=cpc&utm_campaign=lux_search_aerogrili_{campaign_id}&utm_content=airchef_sitelink_{ad_id}_{source_type}&utm_term={keyword} | H51: =LEN(A51)
A52: Сервис и гарантия | B52: Бесплатный вывоз СДЭК при гарантийном случае | C52: =LEN(B52) | D52: https://luxhomme.store/service?utm_source=yandex&utm_medium=cpc&utm_campaign=lux_search_aerogrili_{campaign_id}&utm_content=airchef_sitelink_{ad_id}_{source_type}&utm_term={keyword} | H52: =LEN(A52)
A53: Аэрогриль AirChef Dual Pro | B53: Две чаши 7 + 5 л, 18 программ, 3200 Вт | C53: =LEN(B53) | D53: https://luxhomme.store/products/airgrill-dual-pro?utm_source=yandex&utm_medium=cpc&utm_campaign=lux_search_aerogrili_{campaign_id}&utm_content=airchef_sitelink_{ad_id}_{source_type}&utm_term={keyword} | H53: =LEN(A53)
A55: Уточнения
A56: Уточнение | B56: ≤25
A57: Гарантия 3 года | B57: =LEN(A57)
A58: Скидка 20% по промокоду | B58: =LEN(A58)
A59: Доставка через Ozon | B59: =LEN(A59)
A60: Служба заботы 9–21 МСК | B60: =LEN(A60)
A61: Сервисный центр в РФ | B61: =LEN(A61)
A63: Объявления — Сети (РСЯ, ЕПК)
A64: № | B64: Заголовок | C64: ≤56 | D64: Текст | E64: ≤81 | F64: Бриф на картинку | H64: Фото с сайта
A65: 1 | B65: Аэрогриль AirChef с окном — скидка 20% | C65: =LEN(B65) | D65: Чаша 5,5 л, 12 программ, режим сушки. Промокод DIRECT20 на сайте. | E65: =LEN(D65) | F65: Аэрогриль с подсвеченным окном, внутри золотистый картофель; надпись «Окно с подсветкой». Форматы: квадрат 1:1 и широкий 16:9; фото товара с карточки, светлый фон, плашка «−20% по промокоду» | H65: https://luxhomme.store/wp-content/uploads/2017/10/VMP-stranitsa-tovara-62.png
A66: 2 | B66: Видно, как готовится: аэрогриль с окном | C66: =LEN(B66) | D66: AirChef: 1500 Вт, 35–200 °C. С промокодом 4 792 ₽ вместо 5 990 ₽. | E66: =LEN(D66) | F66: Аэрогриль с подсвеченным окном, внутри золотистый картофель; надпись «Окно с подсветкой». Форматы: квадрат 1:1 и широкий 16:9; фото товара с карточки, светлый фон, плашка «−20% по промокоду» | H66: https://luxhomme.store/wp-content/uploads/2017/10/VMP-stranitsa-tovara-62.png
A67: Ссылка (UTM) | B67: https://luxhomme.store/products/airgrill?utm_source=yandex&utm_medium=cpc&utm_campaign=lux_epk_aerogrili_{campaign_id}&utm_content=airchef_{ad_id}_{source_type}&utm_term={keyword}
A69: Ссылки с UTM
A70: Поиск | B70: https://luxhomme.store/products/airgrill?utm_source=yandex&utm_medium=cpc&utm_campaign=lux_search_aerogrili_{campaign_id}&utm_content=airchef_{ad_id}_{source_type}&utm_term={keyword}
A71: Сети | B71: https://luxhomme.store/products/airgrill?utm_source=yandex&utm_medium=cpc&utm_campaign=lux_epk_aerogrili_{campaign_id}&utm_content=airchef_{ad_id}_{source_type}&utm_term={keyword}
A72: Фид | B72: https://luxhomme.store/products/airgrill?utm_source=yandex&utm_medium=cpc&utm_campaign=lux_feed_{campaign_id}&utm_content=airchef_{ad_id}_{source_type}&utm_term={keyword}

Sheet AirChef Dual Pro
A1: Аэрогриль Luxhommè AirChef Dual Pro (2 чаши)
A2: Страница | B2: https://luxhomme.store/products/airgrill-dual-pro
A3: SKU | B3: AEROGRIL2CHASHI
A4: Цена, ₽ | B4: 16990
A5: С промокодом, ₽ | B5: =ROUND(B4*(1-Товары!$B$1),0)
A6: Промокод | B6: DIRECT20
A7: Категория | B7: Аэрогрили
A9: УТП (факты из карточки)
A10: • | B10: Две независимые чаши: 7 л сверху и 5 л снизу
A11: • | B11: Горячее и гарнир одновременно, запахи не смешиваются
A12: • | B12: 3200 Вт, 30–220 °C
A13: • | B13: 18 программ, таймер до 8 часов
A14: • | B14: Синхронизация чаш
A15: • | B15: 2 смотровых окна
A16: • | B16: Можно мыть в посудомоечной машине
A17: • | B17: Гарантия 3 года
A19: Семантика
A20: Группа | B20: Фраза
A21: Тип + покупка | B21: аэрогриль с двумя чашами купить
A22: Тип + покупка | B22: аэрогриль 2 чаши купить
A23: Тип + покупка | B23: аэрогриль двойной
A24: Тип + покупка | B24: аэрогриль с двумя корзинами
A25: Характеристики | B25: аэрогриль с двумя чашами
A26: Характеристики | B26: аэрогриль большой объем
A27: Характеристики | B27: аэрогриль 7 литров
A28: Характеристики | B28: аэрогриль с синхронизацией
A29: Характеристики | B29: аэрогриль с двумя окнами
A30: Характеристики | B30: мощный аэрогриль
A31: Характеристики | B31: аэрогриль 3200 вт
... A36: Модель | B36: аэрогриль airchef dual
A38: Минус-слова товара (+ общие и конкуренты — лист «Минус-слова»)
A39: Товар | B39: рецепт, рецепты, рецептами, приготовить, готовить, сколько, минут, книга, пергамент, бумага, форма, решетка, подставка
A40: Конкуренты | B40: tefal, тефаль, philips, филипс, ninja, ниндзя, cosori, косори, xiaomi, redmond, редмонд, polaris, поларис, kitfort, китфорт, moulinex, мулинекс, instant, hotter, gfgril, oberhof, garlyn, гарлин, proficook, vitek, dexp, dauken
A42: Объявления — Поиск
A43: № | B43: Заголовок 1 | C43: ≤56 | D43: Заголовок 2 | E43: ≤30 | F43: Текст | G43: ≤81 | H43: Отображаемая ссылка (≤20)
A44: 1 | B44: Аэрогриль с двумя чашами 7 + 5 л — скидка 20% | C44: =LEN(B44) | D44: Промокод DIRECT20 | E44: =LEN(D44) | F44: AirChef Dual Pro: 3200 Вт, 18 программ, синхронизация чаш, 2 окна. | G44: =LEN(F44) | H44: AirChef-Dual-Pro
A45: 2 | B45: Аэрогриль AirChef Dual Pro: два блюда сразу | C45: =LEN(B45) | D45: Скидка 20% на сайте | E45: =LEN(D45) | F45: Чаши 7 и 5 л, 30–220 °C, таймер до 8 часов. Гарантия 3 года. | G45: =LEN(F45) | H45: AirChef-Dual-Pro
A46: 3 | B46: Купить аэрогриль на 2 чаши за 13 592 ₽ | C46: =LEN(B46) | D46: Промокод DIRECT20 | E46: =LEN(D46) | F46: Горячее и гарнир одновременно, запахи не смешиваются. 3200 Вт, 18 программ. | G46: =LEN(F46) | H46: AirChef-Dual-Pro
A47: Ссылка (UTM) | B47: https://luxhomme.store/products/airgrill-dual-pro?utm_source=yandex&utm_medium=cpc&utm_campaign=lux_search_aerogrili_{campaign_id}&utm_content=airchef-dual-pro_{ad_id}_{source_type}&utm_term={keyword}
A49: Быстрые ссылки
A50: Название | B50: Описание | C50: ≤60 | D50: Ссылка (UTM) | H50: Название ≤30
A51: Каталог техники | B51: Пылесосы, швабры, кофемашины, аэрогрили | C51: =LEN(B51) | D51: https://luxhomme.store/catalog?utm_source=yandex&utm_medium=cpc&utm_campaign=lux_search_aerogrili_{campaign_id}&utm_content=airchef-dual-pro_sitelink_{ad_id}_{source_type}&utm_term={keyword} | H51: =LEN(A51)
A52: Доставка и оплата | B52: Пункты выдачи и курьер Ozon, срок после ввода адреса | C52: =LEN(B52) | D52: https://luxhomme.store/delivery?utm_source=yandex&utm_medium=cpc&utm_campaign=lux_search_aerogrili_{campaign_id}&utm_content=airchef-dual-pro_sitelink_{ad_id}_{source_type}&utm_term={keyword} | H52: =LEN(A52)
A53: Сервис и гарантия | B53: Бесплатный вывоз СДЭК при гарантийном случае | C53: =LEN(B53) | D53: https://luxhomme.store/service?utm_source=yandex&utm_medium=cpc&utm_campaign=lux_search_aerogrili_{campaign_id}&utm_content=airchef-dual-pro_sitelink_{ad_id}_{source_type}&utm_term={keyword} | H53: =LEN(A53)
A54: Аэрогриль AirChef 5,5 л | B54: 12 программ, окно с подсветкой, сушка | C54: =LEN(B54) | D54: https://luxhomme.store/products/airgrill?utm_source=yandex&utm_medium=cpc&utm_campaign=lux_search_aerogrili_{campaign_id}&utm_content=airchef-dual-pro_sitelink_{ad_id}_{source_type}&utm_term={keyword} | H54: =LEN(A54)
A56: Уточнения
A57: Уточнение | B57: ≤25
A58: Гарантия 3 года | B58: =LEN(A58)
A59: Скидка 20% по промокоду | B59: =LEN(A59)
A60: Доставка через Ozon | B60: =LEN(A60)
A61: Служба заботы 9–21 МСК | B61: =LEN(A61)
A62: Сервисный центр в РФ | B62: =LEN(A62)
A64: Объявления — Сети (РСЯ, ЕПК)
A65: № | B65: Заголовок | C65: ≤56 | D65: Текст | E65: ≤81 | F65: Бриф на картинку | H65: Фото с сайта
A66: 1 | B66: Два блюда одновременно: аэрогриль на 2 чаши | C66: =LEN(B66) | D66: AirChef Dual Pro: 7 + 5 л, 18 программ. Промокод DIRECT20 — скидка 20%. | E66: =LEN(D66) | F66: Аэрогриль с двумя открытыми чашами: мясо и овощи; надпись «2 чаши · 7 + 5 л». Форматы: квадрат 1:1 и широкий 16:9; фото товара с карточки, светлый фон, плашка «−20% по промокоду» | H66: https://luxhomme.store/wp-content/uploads/2026/07/aerogril-14-1.png
A67: 2 | B67: Аэрогриль AirChef Dual Pro со скидкой 20% | C67: =LEN(B67) | D67: Синхронизация чаш, 2 окна. С промокодом 13 592 ₽ вместо 16 990 ₽. | E67: =LEN(D67) | F67: Аэрогриль с двумя открытыми чашами: мясо и овощи; надпись «2 чаши · 7 + 5 л». Форматы: квадрат 1:1 и широкий 16:9; фото товара с карточки, светлый фон, плашка «−20% по промокоду» | H67: https://luxhomme.store/wp-content/uploads/2026/07/aerogril-14-1.png
A68: Ссылка (UTM) | B68: https://luxhomme.store/products/airgrill-dual-pro?utm_source=yandex&utm_medium=cpc&utm_campaign=lux_epk_aerogrili_{campaign_id}&utm_content=airchef-dual-pro_{ad_id}_{source_type}&utm_term={keyword}
A70: Ссылки с UTM
A71: Поиск | B71: https://luxhomme.store/products/airgrill-dual-pro?utm_source=yandex&utm_medium=cpc&utm_campaign=lux_search_aerogrili_{campaign_id}&utm_content=airchef-dual-pro_{ad_id}_{source_type}&utm_term={keyword}
A72: Сети | B72: https://luxhomme.store/products/airgrill-dual-pro?utm_source=yandex&utm_medium=cpc&utm_campaign=lux_epk_aerogrili_{campaign_id}&utm_content=airchef-dual-pro_{ad_id}_{source_type}&utm_term={keyword}
A73: Фид | B73: https://luxhomme.store/products/airgrill-dual-pro?utm_source=yandex&utm_medium=cpc&utm_campaign=lux_feed_{campaign_id}&utm_content=airchef-dual-pro_{ad_id}_{source_type}&utm_term={keyword}

Sheet uFit 2D Standard
A1: Виброплатформа uFit 2D Standard
A2: Страница | B2: https://luxhomme.store/products/ufit-2d
A3: SKU | B3: VIPLATB
A4: Цена, ₽ | B4: 6190
A5: С промокодом, ₽ | B5: =ROUND(B4*(1-Товары!$B$1),0)
A6: Промокод | B6: DIRECT20
A7: Категория | B7: Виброплатформы
A9: УТП (факты из карточки)
A10: • | B10: 5 программ, 180 уровней скорости
A11: • | B11: Нагрузка до 150 кг
A12: • | B12: 150 Вт, сенсорный дисплей, музыка
A13: • | B13: Пульт ДУ
A14: • | B14: Эспандеры 2 шт. и фитнес-резинка в комплекте
A15: • | B15: Высота 12 см — компактно хранить
A16: • | B16: Гарантия 2 года
A18: Семантика
A19: Группа | B19: Фраза
A20: Тип + покупка | B20: виброплатформа купить
A21: Тип + покупка | B21: виброплатформа для дома купить
A22: Тип + покупка | B22: виброплатформа цена
A23: Тип + покупка | B23: виброплатформа недорого
A24: Тип + покупка | B24: вибротренажер для дома купить
A25: Назначение | B25: виброплатформа для дома
A26: Назначение | B26: виброплатформа для похудения купить
A27: Назначение | B27: виброплатформа тренажер
A28: Назначение | B28: вибротренажер для дома
A29: Характеристики | B29: виброплатформа с эспандерами
A30: Характеристики | B30: виброплатформа до 150 кг
... A34: Модель | B34: виброплатформа ufit
A36: Минус-слова товара (+ общие и конкуренты — лист «Минус-слова»)
A37: Товар | B37: ems, емс, миостимуляция, миотоки, нагрев, нагревом, подогрев, 3d, вред, противопоказания, польза, врачей, спортзал, аренда
A38: Конкуренты | B38: bradex, брадекс, torneo, торнео, clear fit, planta, планта, oxygen, hasttings, evo fitness, proxima, dfc, body sculpture, unix fit, юникс, yamaguchi, ямагучи, casada, gezatone, us medica
A40: Объявления — Поиск
A41: № | B41: Заголовок 1 | C41: ≤56 | D41: Заголовок 2 | E41: ≤30 | F41: Текст | G41: ≤81 | H41: Отображаемая ссылка (≤20)
A42: 1 | B42: Виброплатформа uFit 2D для дома — скидка 20% | C42: =LEN(B42) | D42: Промокод DIRECT20 | E42: =LEN(D42) | F42: 5 программ, 180 скоростей, нагрузка до 150 кг. Эспандеры и пульт в комплекте. | G42: =LEN(F42) | H42: uFit-2D
A43: 2 | B43: Виброплатформа с эспандерами и пультом | C43: =LEN(B43) | D43: Скидка 20% на сайте | E43: =LEN(D43) | F43: uFit 2D Standard: 150 Вт, сенсорный дисплей, музыка. Гарантия 2 года. | G43: =LEN(F43) | H43: uFit-2D
A44: 3 | B44: Купить виброплатформу uFit 2D за 4 952 ₽ | C44: =LEN(B44) | D44: Промокод DIRECT20 | E44: =LEN(D44) | F44: Тренировки дома в удобное время: 5 программ и 180 уровней скорости. | G44: =LEN(F44) | H44: uFit-2D
A45: Ссылка (UTM) | B45: https://luxhomme.store/products/ufit-2d?utm_source=yandex&utm_medium=cpc&utm_campaign=lux_search_vibro_{campaign_id}&utm_content=ufit-2d_{ad_id}_{source_type}&utm_term={keyword}
A47: Быстрые ссылки
A48: Название | B48: Описание | C48: ≤60 | D48: Ссылка (UTM) | H48: Название ≤30
A49: Каталог техники | B49: Пылесосы, швабры, кофемашины, аэрогрили | C49: =LEN(B49) | D49: https://luxhomme.store/catalog?utm_source=yandex&utm_medium=cpc&utm_campaign=lux_search_vibro_{campaign_id}&utm_content=ufit-2d_sitelink_{ad_id}_{source_type}&utm_term={keyword} | H49: =LEN(A49)
A50: Доставка и оплата | B50: Пункты выдачи и курьер Ozon, срок после ввода адреса | C50: =LEN(B50) | D50: https://luxhomme.store/delivery?utm_source=yandex&utm_medium=cpc&utm_campaign=lux_search_vibro_{campaign_id}&utm_content=ufit-2d_sitelink_{ad_id}_{source_type}&utm_term={keyword} | H50: =LEN(A50)
A51: Сервис и гарантия | B51: Бесплатный вывоз СДЭК при гарантийном случае | C51: =LEN(B51) | D51: https://luxhomme.store/service?utm_source=yandex&utm_medium=cpc&utm_campaign=lux_search_vibro_{campaign_id}&utm_content=ufit-2d_sitelink_{ad_id}_{source_type}&utm_term={keyword} | H51: =LEN(A51)
A52: Виброплатформа uFit 2D Pro | B52: Вибрация, EMS и обогрев, до 150 кг | C52: =LEN(B52) | D52: https://luxhomme.store/products/ufit-2d-ems?utm_source=yandex&utm_medium=cpc&utm_campaign=lux_search_vibro_{campaign_id}&utm_content=ufit-2d_sitelink_{ad_id}_{source_type}&utm_term={keyword} | H52: =LEN(A52)
A54: Уточнения
A55: Уточнение | B55: ≤25
A56: Гарантия 2 года | B56: =LEN(A56)
A57: Скидка 20% по промокоду | B57: =LEN(A57)
A58: Доставка через Ozon | B58: =LEN(A58)
A59: Служба заботы 9–21 МСК | B59: =LEN(A59)
A60: Сервисный центр в РФ | B60: =LEN(A60)
A62: Объявления — Сети (РСЯ, ЕПК)
A63: № | B63: Заголовок | C63: ≤56 | D63: Текст | E63: ≤81 | F63: Бриф на картинку | H63: Фото с сайта
A64: 1 | B64: Виброплатформа для дома со скидкой 20% | C64: =LEN(B64) | D64: uFit 2D: 5 программ, 180 скоростей, до 150 кг. Промокод DIRECT20 на сайте. | E64: =LEN(D64) | F64: Платформа в гостиной + эспандеры рядом, без фигур «до/после»; надпись «5 программ · до 150 кг». Форматы: квадрат 1:1 и широкий 16:9; фото товара с карточки, светлый фон, плашка «−20% по промокоду» | H64: https://luxhomme.store/wp-content/uploads/2025/06/VMP-stranitsa-tovara-26-2-.png
A65: 2 | B65: Виброплатформа uFit 2D с эспандерами | C65: =LEN(B65) | D65: Высота 12 см, пульт в комплекте. С промокодом 4 952 ₽ вместо 6 190 ₽. | E65: =LEN(D65) | F65: Платформа в гостиной + эспандеры рядом, без фигур «до/после»; надпись «5 программ · до 150 кг». Форматы: квадрат 1:1 и широкий 16:9; фото товара с карточки, светлый фон, плашка «−20% по промокоду» | H65: https://luxhomme.store/wp-content/uploads/2025/06/VMP-stranitsa-tovara-26-2-.png
A66: Ссылка (UTM) | B66: https://luxhomme.store/products/ufit-2d?utm_source=yandex&utm_medium=cpc&utm_campaign=lux_epk_vibro_{campaign_id}&utm_content=ufit-2d_{ad_id}_{source_type}&utm_term={keyword}
A68: Ссылки с UTM
A69: Поиск | B69: https://luxhomme.store/products/ufit-2d?utm_source=yandex&utm_medium=cpc&utm_campaign=lux_search_vibro_{campaign_id}&utm_content=ufit-2d_{ad_id}_{source_type}&utm_term={keyword}
A70: Сети | B70: https://luxhomme.store/products/ufit-2d?utm_source=yandex&utm_medium=cpc&utm_campaign=lux_epk_vibro_{campaign_id}&utm_content=ufit-2d_{ad_id}_{source_type}&utm_term={keyword}
A71: Фид | B71: https://luxhomme.store/products/ufit-2d?utm_source=yandex&utm_medium=cpc&utm_campaign=lux_feed_{campaign_id}&utm_content=ufit-2d_{ad_id}_{source_type}&utm_term={keyword}

Sheet uFit 2D Pro
A1: Виброплатформа uFit 2D Pro с EMS токами
A2: Страница | B2: https://luxhomme.store/products/ufit-2d-ems
A3: SKU | B3: VIPLATEL2D
A4: Цена, ₽ | B4: 7490
A5: С промокодом, ₽ | B5: =ROUND(B4*(1-Товары!$B$1),0)
A6: Промокод | B6: DIRECT20
A7: Категория | B7: Виброплатформы
A9: УТП (факты из карточки)
A10: • | B10: Вибрация + EMS + обогрев
A11: • | B11: 5 программ, 180 уровней скорости, амплитуда 0–12 мм
A12: • | B12: Нагрузка до 150 кг, 200 Вт
A13: • | B13: Фитнес-браслет и пульт ДУ
A14: • | B14: Bluetooth, динамик, голосовое сопровождение
A15: • | B15: Эспандеры, фитнес-резинка, план питания и тренировок в подарок
A16: • | B16: Гарантия 3 года
A18: Семантика
A19: Группа | B19: Фраза
A20: Тип + покупка | B20: виброплатформа с ems купить
A21: Тип + покупка | B21: виброплатформа для дома купить
A22: Тип + покупка | B22: виброплатформа ems цена
A23: Характеристики | B23: виброплатформа с ems
A24: Характеристики | B24: виброплатформа с миостимуляцией
A25: Характеристики | B25: виброплатформа с подогревом
A26: Характеристики | B26: виброплатформа с нагревом
A27: Характеристики | B27: виброплатформа с браслетом
A28: Характеристики | B28: вибротренажер с ems
A29: Характеристики | B29: виброплатформа 2d ems
A30: Характеристики | B30: виброплатформа с bluetooth
... A34: Модель | B34: ufit ems
A36: Минус-слова товара (+ общие и конкуренты — лист «Минус-слова»)
A37: Товар | B37: 3d, вред, противопоказания, польза, врачей, спортзал, аренда, лица, пояс, шорты
A38: Конкуренты | B38: bradex, брадекс, torneo, торнео, clear fit, planta, планта, oxygen, hasttings, evo fitness, proxima, dfc, body sculpture, unix fit, юникс, yamaguchi, ямагучи, casada, gezatone, us medica
A40: Объявления — Поиск
A41: № | B41: Заголовок 1 | C41: ≤56 | D41: Заголовок 2 | E41: ≤30 | F41: Текст | G41: ≤81 | H41: Отображаемая ссылка (≤20)
A42: 1 | B42: Виброплатформа uFit 2D Pro с EMS и обогревом | C42: =LEN(B42) | D42: Скидка 20% на сайте | E42: =LEN(D42) | F42: 5 программ, 180 скоростей, до 150 кг, 200 Вт. Промокод DIRECT20. | G42: =LEN(F42) | H42: uFit-2D-Pro-EMS
A43: 2 | B43: Виброплатформа с EMS для домашних тренировок | C43: =LEN(B43) | D43: Скидка 20% по промокоду | E43: =LEN(D43) | F43: uFit 2D Pro: браслет, эспандеры, планы тренировок и питания. Гарантия 3 года. | G43: =LEN(F43) | H43: uFit-2D-Pro-EMS
A44: 3 | B44: Купить виброплатформу с EMS за 5 992 ₽ | C44: =LEN(B44) | D44: Промокод DIRECT20 | E44: =LEN(D44) | F44: Вибрация, EMS и обогрев в одном тренажёре. Нагрузка до 150 кг. | G44: =LEN(F44) | H44: uFit-2D-Pro-EMS
A45: Ссылка (UTM) | B45: https://luxhomme.store/products/ufit-2d-ems?utm_source=yandex&utm_medium=cpc&utm_campaign=lux_search_vibro_{campaign_id}&utm_content=ufit-2d-pro-ems_{ad_id}_{source_type}&utm_term={keyword}
A47: Быстрые ссылки
A48: Название | B48: Описание | C48: ≤60 | D48: Ссылка (UTM) | H48: Название ≤30
A49: Каталог техники | B49: Пылесосы, швабры, кофемашины, аэрогрили | C49: =LEN(B49) | D49: https://luxhomme.store/catalog?utm_source=yandex&utm_medium=cpc&utm_campaign=lux_search_vibro_{campaign_id}&utm_content=ufit-2d-pro-ems_sitelink_{ad_id}_{source_type}&utm_term={keyword} | H49: =LEN(A49)
A50: Доставка и оплата | B50: Пункты выдачи и курьер Ozon, срок после ввода адреса | C50: =LEN(B50) | D50: https://luxhomme.store/delivery?utm_source=yandex&utm_medium=cpc&utm_campaign=lux_search_vibro_{campaign_id}&utm_content=ufit-2d-pro-ems_sitelink_{ad_id}_{source_type}&utm_term={keyword} | H50: =LEN(A50)
A51: Сервис и гарантия | B51: Бесплатный вывоз СДЭК при гарантийном случае | C51: =LEN(B51) | D51: https://luxhomme.store/service?utm_source=yandex&utm_medium=cpc&utm_campaign=lux_search_vibro_{campaign_id}&utm_content=ufit-2d-pro-ems_sitelink_{ad_id}_{source_type}&utm_term={keyword} | H51: =LEN(A51)
A52: Виброплатформа uFit 3D Max | B52: 3D-вибрация, EMS и нагрев, 400 Вт | C52: =LEN(B52) | D52: https://luxhomme.store/products/vibroplatforma-dlya-pohudeniya-3d-c-ems-tokami-i-nagrevom-do-150-kg?utm_source=yandex&utm_medium=cpc&utm_campaign=lux_search_vibro_{campaign_id}&utm_content=ufit-2d-pro-ems_sitelink_{ad_id}_{source_type}&utm_term={keyword} | H52: =LEN(A52)
A54: Уточнения
A55: Уточнение | B55: ≤25
A56: Гарантия 3 года | B56: =LEN(A56)
A57: Скидка 20% по промокоду | B57: =LEN(A57)
A58: Доставка через Ozon | B58: =LEN(A58)
A59: Служба заботы 9–21 МСК | B59: =LEN(A59)
A60: Сервисный центр в РФ | B60: =LEN(A60)
A62: Объявления — Сети (РСЯ, ЕПК)
A63: № | B63: Заголовок | C63: ≤56 | D63: Текст | E63: ≤81 | F63: Бриф на картинку | H63: Фото с сайта
A64: 1 | B64: Виброплатформа с EMS и обогревом — скидка 20% | C64: =LEN(B64) | D64: uFit 2D Pro: 5 программ, до 150 кг. Промокод DIRECT20 на сайте. | E64: =LEN(D64) | F64: Платформа + браслет и эспандеры, нейтральный кадр без фигур «до/после»; надпись «Вибрация + EMS + обогрев». Форматы: квадрат 1:1 и широкий 16:9; фото товара с карточки, светлый фон, плашка «−20% по промокоду» | H64: https://luxhomme.store/wp-content/uploads/2026/01/VMP-stranitsa-tovara-89.png
A65: 2 | B65: Тренировки дома: вибрация, EMS и обогрев | C65: =LEN(B65) | D65: Браслет и эспандеры в комплекте. 5 992 ₽ с промокодом. | E65: =LEN(D65) | F65: Платформа + браслет и эспандеры, нейтральный кадр без фигур «до/после»; надпись «Вибрация + EMS + обогрев». Форматы: квадрат 1:1 и широкий 16:9; фото товара с карточки, светлый фон, плашка «−20% по промокоду» | H65: https://luxhomme.store/wp-content/uploads/2026/01/VMP-stranitsa-tovara-89.png
A66: Ссылка (UTM) | B66: https://luxhomme.store/products/ufit-2d-ems?utm_source=yandex&utm_medium=cpc&utm_campaign=lux_epk_vibro_{campaign_id}&utm_content=ufit-2d-pro-ems_{ad_id}_{source_type}&utm_term={keyword}
A68: Ссылки с UTM
A69: Поиск | B69: https://luxhomme.store/products/ufit-2d-ems?utm_source=yandex&utm_medium=cpc&utm_campaign=lux_search_vibro_{campaign_id}&utm_content=ufit-2d-pro-ems_{ad_id}_{source_type}&utm_term={keyword}
A70: Сети | B70: https://luxhomme.store/products/ufit-2d-ems?utm_source=yandex&utm_medium=cpc&utm_campaign=lux_epk_vibro_{campaign_id}&utm_content=ufit-2d-pro-ems_{ad_id}_{source_type}&utm_term={keyword}
A71: Фид | B71: https://luxhomme.store/products/ufit-2d-ems?utm_source=yandex&utm_medium=cpc&utm_campaign=lux_feed_{campaign_id}&utm_content=ufit-2d-pro-ems_{ad_id}_{source_type}&utm_term={keyword}

Sheet uFit 3D Max
A1: Виброплатформа для похудения 3D c EMS токами и нагревом, нагрузка до 150 кг
A2: Страница | B2: https://luxhomme.store/products/vibroplatforma-dlya-pohudeniya-3d-c-ems-tokami-i-nagrevom-do-150-kg
A3: SKU | B3: нет в разметке сайта
A4: Цена, ₽ | B4: 16990
A5: С промокодом, ₽ | B5: =ROUND(B4*(1-Товары!$B$1),0)
A6: Промокод | B6: DIRECT20
A7: Категория | B7: Виброплатформы
A9: УТП (факты из карточки)
A10: • | B10: 3 технологии: 3D-вибрация, EMS, нагрев
A11: • | B11: 400 Вт, нагрузка до 150 кг
A12: • | B12: Bluetooth-браслет и пульт ДУ
A13: • | B13: Музыка по Bluetooth
A14: • | B14: Антискользящее покрытие, без поручней — компактно
A15: • | B15: Эспандеры, резинка, план тренировок и питания
A16: • | B16: Гарантия 3 года
A18: Семантика
A19: Группа | B19: Фраза
A20: Тип + покупка | B20: виброплатформа 3d купить
A21: Тип + покупка | B21: виброплатформа купить
A22: Тип + покупка | B22: виброплатформа для дома купить
A23: Характеристики | B23: виброплатформа 3d
A24: Характеристики | B24: 3d виброплатформа для дома
A25: Характеристики | B25: виброплатформа 3d с ems
A26: Характеристики | B26: виброплатформа с ems и нагревом
A27: Характеристики | B27: виброплатформа с bluetooth
A28: Характеристики | B28: мощная виброплатформа
A29: Характеристики | B29: виброплатформа 400 вт
A30: Характеристики | B30: вибротренажер 3d
... A34: Модель | B34: ufit 3d
A36: Минус-слова товара (+ общие и конкуренты — лист «Минус-слова»)
A37: Товар | B37: 2d, вред, противопоказания, польза, врачей, спортзал, аренда, лица, пояс, шорты
A38: Конкуренты | B38: bradex, брадекс, torneo, торнео, clear fit, planta, планта, oxygen, hasttings, evo fitness, proxima, dfc, body sculpture, unix fit, юникс, yamaguchi, ямагучи, casada, gezatone, us medica
A40: Объявления — Поиск
A41: № | B41: Заголовок 1 | C41: ≤56 | D41: Заголовок 2 | E41: ≤30 | F41: Текст | G41: ≤81 | H41: Отображаемая ссылка (≤20)
A42: 1 | B42: Виброплатформа 3D с EMS и нагревом — скидка 20% | C42: =LEN(B42) | D42: Промокод DIRECT20 | E42: =LEN(D42) | F42: uFit 3D Max: 400 Вт, Bluetooth-браслет и пульт. Нагрузка до 150 кг. | G42: =LEN(F42) | H42: uFit-3D-Max
A43: 2 | B43: Виброплатформа uFit 3D Max: вибрация, EMS, нагрев | C43: =LEN(B43) | D43: Скидка 20% на сайте | E43: =LEN(D43) | F43: 400 Вт, музыка по Bluetooth, антискользящее покрытие. Гарантия 3 года. | G43: =LEN(F43) | H43: uFit-3D-Max
A44: 3 | B44: Купить виброплатформу 3D с EMS за 13 592 ₽ | C44: =LEN(B44) | D44: Промокод DIRECT20 | E44: =LEN(D44) | F44: Мощность 400 Вт, нагрузка до 150 кг, эспандеры и план тренировок. | G44: =LEN(F44) | H44: uFit-3D-Max
A45: Ссылка (UTM) | B45: https://luxhomme.store/products/vibroplatforma-dlya-pohudeniya-3d-c-ems-tokami-i-nagrevom-do-150-kg?utm_source=yandex&utm_medium=cpc&utm_campaign=lux_search_vibro_{campaign_id}&utm_content=ufit-3d-max_{ad_id}_{source_type}&utm_term={keyword}
A47: Быстрые ссылки
A48: Название | B48: Описание | C48: ≤60 | D48: Ссылка (UTM) | H48: Название ≤30
A49: Каталог техники | B49: Пылесосы, швабры, кофемашины, аэрогрили | C49: =LEN(B49) | D49: https://luxhomme.store/catalog?utm_source=yandex&utm_medium=cpc&utm_campaign=lux_search_vibro_{campaign_id}&utm_content=ufit-3d-max_sitelink_{ad_id}_{source_type}&utm_term={keyword} | H49: =LEN(A49)
A50: Доставка и оплата | B50: Пункты выдачи и курьер Ozon, срок после ввода адреса | C50: =LEN(B50) | D50: https://luxhomme.store/delivery?utm_source=yandex&utm_medium=cpc&utm_campaign=lux_search_vibro_{campaign_id}&utm_content=ufit-3d-max_sitelink_{ad_id}_{source_type}&utm_term={keyword} | H50: =LEN(A50)
A51: Сервис и гарантия | B51: Бесплатный вывоз СДЭК при гарантийном случае | C51: =LEN(B51) | D51: https://luxhomme.store/service?utm_source=yandex&utm_medium=cpc&utm_campaign=lux_search_vibro_{campaign_id}&utm_content=ufit-3d-max_sitelink_{ad_id}_{source_type}&utm_term={keyword} | H51: =LEN(A51)
A52: Виброплатформа uFit 2D Pro | B52: Вибрация, EMS и обогрев, до 150 кг | C52: =LEN(B52) | D52: https://luxhomme.store/products/ufit-2d-ems?utm_source=yandex&utm_medium=cpc&utm_campaign=lux_search_vibro_{campaign_id}&utm_content=ufit-3d-max_sitelink_{ad_id}_{source_type}&utm_term={keyword} | H52: =LEN(A52)
A54: Уточнения
A55: Уточнение | B55: ≤25
A56: Гарантия 3 года | B56: =LEN(A56)
A57: Скидка 20% по промокоду | B57: =LEN(A57)
A58: Доставка через Ozon | B58: =LEN(A58)
A59: Служба заботы 9–21 МСК | B59: =LEN(A59)
A60: Сервисный центр в РФ | B60: =LEN(A60)
A62: Объявления — Сети (РСЯ, ЕПК)
A63: № | B63: Заголовок | C63: ≤56 | D63: Текст | E63: ≤81 | F63: Бриф на картинку | H63: Фото с сайта
A64: 1 | B64: 3D-виброплатформа с EMS и нагревом со скидкой 20% | C64: =LEN(B64) | D64: uFit 3D Max: 400 Вт, браслет и пульт. Промокод DIRECT20 на сайте. | E64: =LEN(D64) | F64: Белая платформа в интерьере + браслет; без фигур «до/после»; надпись «3D · EMS · нагрев». Форматы: квадрат 1:1 и широкий 16:9; фото товара с карточки, светлый фон, плашка «−20% по промокоду» | H64: https://luxhomme.store/wp-content/uploads/2026/07/hf_20260601_122621_948b5ac2_1879_4fd6_b191_3dfe3add6664_1_1.png
A65: 2 | B65: Три технологии в одном тренажёре для дома | C65: =LEN(B65) | D65: 3D-вибрация, EMS, нагрев. С промокодом 13 592 ₽ вместо 16 990 ₽. | E65: =LEN(D65) | F65: Белая платформа в интерьере + браслет; без фигур «до/после»; надпись «3D · EMS · нагрев». Форматы: квадрат 1:1 и широкий 16:9; фото товара с карточки, светлый фон, плашка «−20% по промокоду» | H65: https://luxhomme.store/wp-content/uploads/2026/07/hf_20260601_122621_948b5ac2_1879_4fd6_b191_3dfe3add6664_1_1.png
A66: Ссылка (UTM) | B66: https://luxhomme.store/products/vibroplatforma-dlya-pohudeniya-3d-c-ems-tokami-i-nagrevom-do-150-kg?utm_source=yandex&utm_medium=cpc&utm_campaign=lux_epk_vibro_{campaign_id}&utm_content=ufit-3d-max_{ad_id}_{source_type}&utm_term={keyword}
A68: Ссылки с UTM
A69: Поиск | B69: https://luxhomme.store/products/vibroplatforma-dlya-pohudeniya-3d-c-ems-tokami-i-nagrevom-do-150-kg?utm_source=yandex&utm_medium=cpc&utm_campaign=lux_search_vibro_{campaign_id}&utm_content=ufit-3d-max_{ad_id}_{source_type}&utm_term={keyword}
A70: Сети | B70: https://luxhomme.store/products/vibroplatforma-dlya-pohudeniya-3d-c-ems-tokami-i-nagrevom-do-150-kg?utm_source=yandex&utm_medium=cpc&utm_campaign=lux_epk_vibro_{campaign_id}&utm_content=ufit-3d-max_{ad_id}_{source_type}&utm_term={keyword}
A71: Фид | B71: https://luxhomme.store/products/vibroplatforma-dlya-pohudeniya-3d-c-ems-tokami-i-nagrevom-do-150-kg?utm_source=yandex&utm_medium=cpc&utm_campaign=lux_feed_{campaign_id}&utm_content=ufit-3d-max_{ad_id}_{source_type}&utm_term={keyword}

Sheet uClean Max
A1: Робот мойщик Luxhommè uClean Max
A2: Страница | B2: https://luxhomme.store/products/window
A3: SKU | B3: ROBOTOKONKVADR
A4: Цена, ₽ | B4: 9990
A5: С промокодом, ₽ | B5: =ROUND(B4*(1-Товары!$B$1),0)
A6: Промокод | B6: DIRECT20
A7: Категория | B7: Роботы-мойщики окон
A9: УТП (факты из карточки)
A10: • | B10: Двойное автоматическое распыление
A11: • | B11: Всасывание 3000 Па
A12: • | B12: Приложение iOS/Android и пульт ДУ
A13: • | B13: 3 маршрута: Z, N и двойной
A14: • | B14: 2,5–3 минуты на 1 м²
A15: • | B15: Страховочный трос 5 м (до 150 кг), 40 минут на стекле при отключении питания
A16: • | B16: Безрамочные поверхности, голос на русском
A17: • | B17: В подарок: 5 доп. салфеток, арома-саше
A18: • | B18: Гарантия 3 года
A20: Семантика
A21: Группа | B21: Фраза
A22: Тип + покупка | B22: робот мойщик окон купить
A23: Тип + покупка | B23: робот для мытья окон купить
A24: Тип + покупка | B24: мойщик окон робот цена
A25: Тип + покупка | B25: робот для мытья окон
A26: Характеристики | B26: робот мойщик окон с распылением
A27: Характеристики | B27: робот для мытья окон с распылителем
A28: Характеристики | B28: робот мойщик окон квадратный
A29: Характеристики | B29: робот для мытья окон с пультом
A30: Характеристики | B30: робот мойщик окон с приложением
A31: Характеристики | B31: робот мойщик окон с тросом
A32: Назначение | B32: робот для мытья стекол
... A37: Модель | B37: робот uclean
A39: Минус-слова товара (+ общие и конкуренты — лист «Минус-слова»)
A40: Товар | B40: пылесос, газонокосилка, бассейн, бассейна, аквариум, солнечных, панелей, салфетки, жидкость, средство, промышленный, альпинист, услуги
A41: Конкуренты | B41: hobot, хобот, ecovacs, winbot, винбот, xiaomi, kitfort, китфорт, cecotec, mamibot, liectroux, hutt, atvel, атвел
A43: Объявления — Поиск
A44: № | B44: Заголовок 1 | C44: ≤56 | D44: Заголовок 2 | E44: ≤30 | F44: Текст | G44: ≤81 | H44: Отображаемая ссылка (≤20)
A45: 1 | B45: Робот-мойщик окон uClean Max с двойным распылением | C45: =LEN(B45) | D45: Скидка 20% на сайте | E45: =LEN(D45) | F45: 3000 Па, приложение и пульт, 3 маршрута, трос 5 м. Промокод DIRECT20. | G45: =LEN(F45) | H45: uClean-Max
A46: 2 | B46: Робот для мытья окон с приложением и пультом | C46: =LEN(B46) | D46: Скидка 20% по промокоду | E46: =LEN(D46) | F46: uClean Max: 2,5–3 минуты на 1 м², голос на русском. Гарантия 3 года. | G46: =LEN(F46) | H46: uClean-Max
A47: 3 | B47: Купить робот-мойщик окон uClean Max за 7 992 ₽ | C47: =LEN(B47) | D47: Промокод DIRECT20 | E47: =LEN(D47) | F47: Для безрамочных поверхностей. 40 минут на стекле при отключении питания. | G47: =LEN(F47) | H47: uClean-Max
A48: Ссылка (UTM) | B48: https://luxhomme.store/products/window?utm_source=yandex&utm_medium=cpc&utm_campaign=lux_search_okna_{campaign_id}&utm_content=uclean-max_{ad_id}_{source_type}&utm_term={keyword}
A50: Быстрые ссылки
A51: Название | B51: Описание | C51: ≤60 | D51: Ссылка (UTM) | H51: Название ≤30
A52: Каталог техники | B52: Пылесосы, швабры, кофемашины, аэрогрили | C52: =LEN(B52) | D52: https://luxhomme.store/catalog?utm_source=yandex&utm_medium=cpc&utm_campaign=lux_search_okna_{campaign_id}&utm_content=uclean-max_sitelink_{ad_id}_{source_type}&utm_term={keyword} | H52: =LEN(A52)
A53: Доставка и оплата | B53: Пункты выдачи и курьер Ozon, срок после ввода адреса | C53: =LEN(B53) | D53: https://luxhomme.store/delivery?utm_source=yandex&utm_medium=cpc&utm_campaign=lux_search_okna_{campaign_id}&utm_content=uclean-max_sitelink_{ad_id}_{source_type}&utm_term={keyword} | H53: =LEN(A53)
A54: Сервис и гарантия | B54: Бесплатный вывоз СДЭК при гарантийном случае | C54: =LEN(B54) | D54: https://luxhomme.store/service?utm_source=yandex&utm_medium=cpc&utm_campaign=lux_search_okna_{campaign_id}&utm_content=uclean-max_sitelink_{ad_id}_{source_type}&utm_term={keyword} | H54: =LEN(A54)
A55: Правила возврата | B55: Возврат товара надлежащего качества в течение 7 дней | C55: =LEN(B55) | D55: https://luxhomme.store/returns?utm_source=yandex&utm_medium=cpc&utm_campaign=lux_search_okna_{campaign_id}&utm_content=uclean-max_sitelink_{ad_id}_{source_type}&utm_term={keyword} | H55: =LEN(A55)
A57: Уточнения
A58: Уточнение | B58: ≤25
A59: Гарантия 3 года | B59: =LEN(A59)
A60: Скидка 20% по промокоду | B60: =LEN(A60)
A61: Доставка через Ozon | B61: =LEN(A61)
A62: Служба заботы 9–21 МСК | B62: =LEN(A62)
A63: Сервисный центр в РФ | B63: =LEN(A63)
A65: Объявления — Сети (РСЯ, ЕПК)
A66: № | B66: Заголовок | C66: ≤56 | D66: Текст | E66: ≤81 | F66: Бриф на картинку | H66: Фото с сайта
A67: 1 | B67: Робот моет окна сам — скидка 20% | C67: =LEN(B67) | D67: uClean Max: двойное распыление, приложение, трос 5 м. Промокод DIRECT20. | E67: =LEN(D67) | F67: Робот на панорамном окне с видом на город; надпись «Моет окна сам». Форматы: квадрат 1:1 и широкий 16:9; фото товара с карточки, светлый фон, плашка «−20% по промокоду» | H67: https://luxhomme.store/wp-content/uploads/2017/10/VMP-stranitsa-tovara-40.png
A68: 2 | B68: Робот-мойщик окон uClean Max | C68: =LEN(B68) | D68: 3 маршрута, голос на русском, 3000 Па. 7 992 ₽ с промокодом. | E68: =LEN(D68) | F68: Робот на панорамном окне с видом на город; надпись «Моет окна сам». Форматы: квадрат 1:1 и широкий 16:9; фото товара с карточки, светлый фон, плашка «−20% по промокоду» | H68: https://luxhomme.store/wp-content/uploads/2017/10/VMP-stranitsa-tovara-40.png
A69: Ссылка (UTM) | B69: https://luxhomme.store/products/window?utm_source=yandex&utm_medium=cpc&utm_campaign=lux_epk_okna_{campaign_id}&utm_content=uclean-max_{ad_id}_{source_type}&utm_term={keyword}
A71: Ссылки с UTM
A72: Поиск | B72: https://luxhomme.store/products/window?utm_source=yandex&utm_medium=cpc&utm_campaign=lux_search_okna_{campaign_id}&utm_content=uclean-max_{ad_id}_{source_type}&utm_term={keyword}
A73: Сети | B73: https://luxhomme.store/products/window?utm_source=yandex&utm_medium=cpc&utm_campaign=lux_epk_okna_{campaign_id}&utm_content=uclean-max_{ad_id}_{source_type}&utm_term={keyword}
A74: Фид | B74: https://luxhomme.store/products/window?utm_source=yandex&utm_medium=cpc&utm_campaign=lux_feed_{campaign_id}&utm_content=uclean-max_{ad_id}_{source_type}&utm_term={keyword}

Sheet Минус-слова
A1: Общие — на все кампании
A2: Нецелевые | B2: бесплатно, скачать, своими руками, ремонт, запчасти, запчасть, комплектующие, разборка, схема, инструкция, руководство, неисправность, сломался, бу, авито, юла, аренда, прокат, напрокат, вакансия, работа, оптом, опт, реферат, фото, картинки, рисунок, игрушка, игрушечный, детский, раскраска, википедия
A3: Магазины и маркетплейсы | B3: озон, ozon, wildberries, вайлдберриз, валберис, вб, маркет, мегамаркет, днс, dns, мвидео, эльдорадо, ситилинк, леруа, ашан, aliexpress, алиэкспресс, temu
A4: Информационные (на старте) | B4: отзывы, отзыв, обзор, рейтинг, топ, лучший, сравнение, сравнить, какой, выбрать, видео
A5: Свой бренд (идёт в брендовой кампании) | B5: luxhomme, luxhommè, люксхом, люксхомм
A7: Конкуренты — на кампании категории
A8: Пылесосы | B8: dyson, дайсон, dreame, дриме, дрими, дреаме, dream, roborock, роборок, tineco, тинеко, xiaomi, сяоми, ксиоми, karcher, керхер, tefal, тефаль, polaris, поларис, kitfort, китфорт, redmond, редмонд, philips, филипс, bosch, бош, samsung, самсунг, lg, vitek, витек, thomas, томас, deerma, jimmy, hwnd, atvel, атвел, puppyoo, viomi, midea, electrolux, haier, x clean, f16, ultimate, neatsvor, karingbee, chovery, ксиаоми, house up
A9: Паровые швабры | B9: karcher, керхер, tefal, тефаль, kitfort, китфорт, polaris, поларис, bissell, биссел, black decker, vileda, виледа, leifheit, vax, endever, clatronic, kelli, bort, redmond, редмонд, philips, филипс
A10: Кофемашины | B10: delonghi, делонги, philips, филипс, saeco, krups, крупс, jura, nivona, melitta, bosch, siemens, polaris, поларис, kitfort, китфорт, redmond, редмонд, garlyn, гарлин, vitek, xiaomi, smeg, gaggia, sage, breville, oursson, starwind, dauken
A11: Аэрогрили | B11: tefal, тефаль, philips, филипс, ninja, ниндзя, cosori, косори, xiaomi, redmond, редмонд, polaris, поларис, kitfort, китфорт, moulinex, мулинекс, instant, hotter, gfgril, oberhof, garlyn, гарлин, proficook, vitek, dexp, dauken
A12: Виброплатформы | B12: bradex, брадекс, torneo, торнео, clear fit, planta, планта, oxygen, hasttings, evo fitness, proxima, dfc, body sculpture, unix fit, юникс, yamaguchi, ямагучи, casada, gezatone, us medica
A13: Роботы-мойщики окон | B13: hobot, хобот, ecovacs, winbot, винбот, xiaomi, kitfort, китфорт, cecotec, mamibot, liectroux, hutt, atvel, атвел
A15: По товарам — на группу
A16: Aqvion Pro | B16: робот, ручной, автомобильный, машины, щетка, валик, фильтр, аккумулятор, средство, сменные, запасные
A17: Cleneo Pro | B17: вертикальный, робот, беспроводной, аккумуляторный, ручной, средство, шампунь, сменные
A18: Aerlyn | B18: моющий, моет, влажной, влажная, робот, автомобильный, машины, строительный, садовый, щетка, сменные
A19: EcoSteam Pro | B19: ручная, отжим, отжимом, тряпка, веревочная, spin, сменные, запасные, салфетки, щетка
A20: AirSteam Pro | B20: ручная, отжим, отжимом, тряпка, веревочная, spin, сменные, запасные, салфетки, щетка, вертикальный
A21: SC-100 Max | B21: ручная, отжим, отжимом, тряпка, веревочная, spin, сменные, запасные, салфетки, щетка
A22: CoffeeMaker Classic | B22: зерновая, зерно, кофемолка, рожковая, капельная, турка, гейзерная, декальцинация, чистка, таблетки, многоразовые
A23: Caffio Professional | B23: зерновая, зерно, кофемолка, капельная, турка, гейзерная, декальцинация, чистка, таблетки, многоразовые
A24: CremaX | B24: капельная, турка, гейзерная, ручная, декальцинация, чистка, таблетки, многоразовые
A25: AirChef | B25: рецепт, рецепты, рецептами, приготовить, готовить, сколько, минут, книга, пергамент, бумага, форма, решетка, подставка, две, двумя, двойной, двухкамерный, dual
A26: AirChef Dual Pro | B26: рецепт, рецепты, рецептами, приготовить, готовить, сколько, минут, книга, пергамент, бумага, форма, решетка, подставка
A27: uFit 2D Standard | B27: ems, емс, миостимуляция, миотоки, нагрев, нагревом, подогрев, 3d, вред, противопоказания, польза, врачей, спортзал, аренда
... A30: uClean Max | B30: пылесос, газонокосилка, бассейн, бассейна, аквариум, солнечных, панелей, салфетки, жидкость, средство, промышленный, альпинист, услуги

Sheet Импорт Поиск
A1: Кампания | B1: Доп. объявление группы | C1: Тип объявления | D1: Мобильное объявление | E1: Название группы | F1: Номер группы | G1: Фраза (с минус-словами) | H1: Заголовок 1 | I1: Заголовок 2 | J1: Текст | K1: Ссылка | L1: Отображаемая ссылка | M1: Регион | N1: Заголовки быстрых ссылок | O1: Описания быстрых ссылок | P1: Адреса быстрых ссылок | Q1: Уточнения | R1: Минус-слова на группу
A2: Lux | Поиск | Пылесосы | B2: - | C2: Текстово-графическое | D2: - | E2: Aqvion Pro | F2: 1 | G2: вертикальный моющий пылесос купить | H2: Вертикальный моющий пылесос Aqvion Pro со скидкой 20% | I2: Самоочистка и сушка | J2: Беспроводной, 15 000 Па, до 60 минут работы. Промокод DIRECT20 на сайте. | K2: https://luxhomme.store/products/vertikalnyj-moyushhij-pylesos-aqvion-pro?utm_source=yandex&utm_medium=cpc&utm_campaign=lux_search_pylesosy_{campaign_id}&utm_content=aqvion-pro_{ad_id}_{source_type}&utm_term={keyword} | L2: Aqvion-Pro | M2: Россия | N2: Каталог техники||Доставка и оплата||Сервис и гарантия||Моющий пылесос Cleneo Pro | O2: Пылесосы, швабры, кофемашины, аэрогрили||Пункты выдачи и курьер Ozon, срок после ввода адреса||Бесплатный вывоз СДЭК при гарантийном случае||Пар и распыление: полы, ковры, мебель, авто | P2: https://luxhomme.store/catalog?utm_source=yandex&utm_medium=cpc&utm_campaign=lux_search_pylesosy_{campaign_id}&utm_content=aqvion-pro_sitelink_{ad_id}_{source_type}&utm_term={keyword}||https://luxhomme.store/delivery?utm_source=yandex&utm_medium=cpc&utm_campaign=lux_search_pylesosy_{campaign_id}&utm_content=aqvion-pro_sitelink_{ad_id}_{source_type}&utm_term={keyword}||https://luxhomme.store/service?utm_source=yandex&utm_medium=cpc&utm_campaign=lux_search_pylesosy_{campaign_id}&utm_content=aqvion-pro_sitelink_{ad_id}_{source_type}&utm_term={keyword}||https://luxhomme.store/products/kompaktnyj-moyushhij-pylesos-cleneo-pro?utm_source=yandex&utm_medium=cpc&utm_campaign=lux_search_pylesosy_{campaign_id}&utm_content=aqvion-pro_sitelink_{ad_id}_{source_type}&utm_term={keyword} | Q2: Гарантия 3 года||Скидка 20% по промокоду||Доставка через Ozon||Служба заботы 9–21 МСК||Сервисный центр в РФ | R2: робот, ручной, автомобильный, машины, щетка, валик, фильтр, аккумулятор, средство, сменные, запасные
A3: Lux | Поиск | Пылесосы | B3: - | C3: Текстово-графическое | D3: - | E3: Aqvion Pro | F3: 1 | G3: моющий вертикальный пылесос для дома купить | H3: Вертикальный моющий пылесос Aqvion Pro со скидкой 20% | I3: Самоочистка и сушка | J3: Беспроводной, 15 000 Па, до 60 минут работы. Промокод DIRECT20 на сайте. | K3: https://luxhomme.store/products/vertikalnyj-moyushhij-pylesos-aqvion-pro?utm_source=yandex&utm_medium=cpc&utm_campaign=lux_search_pylesosy_{campaign_id}&utm_content=aqvion-pro_{ad_id}_{source_type}&utm_term={keyword} | L3: Aqvion-Pro | M3: Россия | N3: Каталог техники||Доставка и оплата||Сервис и гарантия||Моющий пылесос Cleneo Pro | O3: Пылесосы, швабры, кофемашины, аэрогрили||Пункты выдачи и курьер Ozon, срок после ввода адреса||Бесплатный вывоз СДЭК при гарантийном случае||Пар и распыление: полы, ковры, мебель, авто | P3: https://luxhomme.store/catalog?utm_source=yandex&utm_medium=cpc&utm_campaign=lux_search_pylesosy_{campaign_id}&utm_content=aqvion-pro_sitelink_{ad_id}_{source_type}&utm_term={keyword}||https://luxhomme.store/delivery?utm_source=yandex&utm_medium=cpc&utm_campaign=lux_search_pylesosy_{campaign_id}&utm_content=aqvion-pro_sitelink_{ad_id}_{source_type}&utm_term={keyword}||https://luxhomme.store/service?utm_source=yandex&utm_medium=cpc&utm_campaign=lux_search_pylesosy_{campaign_id}&utm_content=aqvion-pro_sitelink_{ad_id}_{source_type}&utm_term={keyword}||https://luxhomme.store/products/kompaktnyj-moyushhij-pylesos-cleneo-pro?utm_source=yandex&utm_medium=cpc&utm_campaign=lux_search_pylesosy_{campaign_id}&utm_content=aqvion-pro_sitelink_{ad_id}_{source_type}&utm_term={keyword} | Q3: Гарантия 3 года||Скидка 20% по промокоду||Доставка через Ozon||Служба заботы 9–21 МСК||Сервисный центр в РФ
A4: Lux | Поиск | Пылесосы | B4: - | C4: Текстово-графическое | D4: - | E4: Aqvion Pro | F4: 1 | G4: вертикальный моющий пылесос цена | H4: Вертикальный моющий пылесос Aqvion Pro со скидкой 20% | I4: Самоочистка и сушка | J4: Беспроводной, 15 000 Па, до 60 минут работы. Промокод DIRECT20 на сайте. | K4: https://luxhomme.store/products/vertikalnyj-moyushhij-pylesos-aqvion-pro?utm_source=yandex&utm_medium=cpc&utm_campaign=lux_search_pylesosy_{campaign_id}&utm_content=aqvion-pro_{ad_id}_{source_type}&utm_term={keyword} | L4: Aqvion-Pro | M4: Россия | N4: Каталог техники||Доставка и оплата||Сервис и гарантия||Моющий пылесос Cleneo Pro | O4: Пылесосы, швабры, кофемашины, аэрогрили||Пункты выдачи и курьер Ozon, срок после ввода адреса||Бесплатный вывоз СДЭК при гарантийном случае||Пар и распыление: полы, ковры, мебель, авто | P4: https://luxhomme.store/catalog?utm_source=yandex&utm_medium=cpc&utm_campaign=lux_search_pylesosy_{campaign_id}&utm_content=aqvion-pro_sitelink_{ad_id}_{source_type}&utm_term={keyword}||https://luxhomme.store/delivery?utm_source=yandex&utm_medium=cpc&utm_campaign=lux_search_pylesosy_{campaign_id}&utm_content=aqvion-pro_sitelink_{ad_id}_{source_type}&utm_term={keyword}||https://luxhomme.store/service?utm_source=yandex&utm_medium=cpc&utm_campaign=lux_search_pylesosy_{campaign_id}&utm_content=aqvion-pro_sitelink_{ad_id}_{source_type}&utm_term={keyword}||https://luxhomme.store/products/kompaktnyj-moyushhij-pylesos-cleneo-pro?utm_source=yandex&utm_medium=cpc&utm_campaign=lux_search_pylesosy_{campaign_id}&utm_content=aqvion-pro_sitelink_{ad_id}_{source_type}&utm_term={keyword} | Q4: Гарантия 3 года||Скидка 20% по промокоду||Доставка через Ozon||Служба заботы 9–21 МСК||Сервисный центр в РФ
A5: Lux | Поиск | Пылесосы | B5: - | C5: Текстово-графическое | D5: - | E5: Aqvion Pro | F5: 1 | G5: недорогие вертикальные моющие пылесосы | H5: Вертикальный моющий пылесос Aqvion Pro со скидкой 20% | I5: Самоочистка и сушка | J5: Беспроводной, 15 000 Па, до 60 минут работы. Промокод DIRECT20 на сайте. | K5: https://luxhomme.store/products/vertikalnyj-moyushhij-pylesos-aqvion-pro?utm_source=yandex&utm_medium=cpc&utm_campaign=lux_search_pylesosy_{campaign_id}&utm_content=aqvion-pro_{ad_id}_{source_type}&utm_term={keyword} | L5: Aqvion-Pro | M5: Россия | N5: Каталог техники||Доставка и оплата||Сервис и гарантия||Моющий пылесос Cleneo Pro | O5: Пылесосы, швабры, кофемашины, аэрогрили||Пункты выдачи и курьер Ozon, срок после ввода адреса||Бесплатный вывоз СДЭК при гарантийном случае||Пар и распыление: полы, ковры, мебель, авто | P5: https://luxhomme.store/catalog?utm_source=yandex&utm_medium=cpc&utm_campaign=lux_search_pylesosy_{campaign_id}&utm_content=aqvion-pro_sitelink_{ad_id}_{source_type}&utm_term={keyword}||https://luxhomme.store/delivery?utm_source=yandex&utm_medium=cpc&utm_campaign=lux_search_pylesosy_{campaign_id}&utm_content=aqvion-pro_sitelink_{ad_id}_{source_type}&utm_term={keyword}||https://luxhomme.store/service?utm_source=yandex&utm_medium=cpc&utm_campaign=lux_search_pylesosy_{campaign_id}&utm_content=aqvion-pro_sitelink_{ad_id}_{source_type}&utm_term={keyword}||https://luxhomme.store/products/kompaktnyj-moyushhij-pylesos-cleneo-pro?utm_source=yandex&utm_medium=cpc&utm_campaign=lux_search_pylesosy_{campaign_id}&utm_content=aqvion-pro_sitelink_{ad_id}_{source_type}&utm_term={keyword} | Q5: Гарантия 3 года||Скидка 20% по промокоду||Доставка через Ozon||Служба заботы 9–21 МСК||Сервисный центр в РФ
A6: Lux | Поиск | Пылесосы | B6: - | C6: Текстово-графическое | D6: - | E6: Aqvion Pro | F6: 1 | G6: бюджетный вертикальный моющий пылесос | H6: Вертикальный моющий пылесос Aqvion Pro со скидкой 20% | I6: Самоочистка и сушка | J6: Беспроводной, 15 000 Па, до 60 минут работы. Промокод DIRECT20 на сайте. | K6: https://luxhomme.store/products/vertikalnyj-moyushhij-pylesos-aqvion-pro?utm_source=yandex&utm_medium=cpc&utm_campaign=lux_search_pylesosy_{campaign_id}&utm_content=aqvion-pro_{ad_id}_{source_type}&utm_term={keyword} | L6: Aqvion-Pro | M6: Россия | N6: Каталог техники||Доставка и оплата||Сервис и гарантия||Моющий пылесос Cleneo Pro | O6: Пылесосы, швабры, кофемашины, аэрогрили||Пункты выдачи и курьер Ozon, срок после ввода адреса||Бесплатный вывоз СДЭК при гарантийном случае||Пар и распыление: полы, ковры, мебель, авто | P6: https://luxhomme.store/catalog?utm_source=yandex&utm_medium=cpc&utm_campaign=lux_search_pylesosy_{campaign_id}&utm_content=aqvion-pro_sitelink_{ad_id}_{source_type}&utm_term={keyword}||https://luxhomme.store/delivery?utm_source=yandex&utm_medium=cpc&utm_campaign=lux_search_pylesosy_{campaign_id}&utm_content=aqvion-pro_sitelink_{ad_id}_{source_type}&utm_term={keyword}||https://luxhomme.store/service?utm_source=yandex&utm_medium=cpc&utm_campaign=lux_search_pylesosy_{campaign_id}&utm_content=aqvion-pro_sitelink_{ad_id}_{source_type}&utm_term={keyword}||https://luxhomme.store/products/kompaktnyj-moyushhij-pylesos-cleneo-pro?utm_source=yandex&utm_medium=cpc&utm_campaign=lux_search_pylesosy_{campaign_id}&utm_content=aqvion-pro_sitelink_{ad_id}_{source_type}&utm_term={keyword} | Q6: Гарантия 3 года||Скидка 20% по промокоду||Доставка через Ozon||Служба заботы 9–21 МСК||Сервисный центр в РФ
A7: Lux | Поиск | Пылесосы | B7: - | C7: Текстово-графическое | D7: - | E7: Aqvion Pro | F7: 1 | G7: моющие беспроводные вертикальные пылесосы цены | H7: Вертикальный моющий пылесос Aqvion Pro со скидкой 20% | I7: Самоочистка и сушка | J7: Беспроводной, 15 000 Па, до 60 минут работы. Промокод DIRECT20 на сайте. | K7: https://luxhomme.store/products/vertikalnyj-moyushhij-pylesos-aqvion-pro?utm_source=yandex&utm_medium=cpc&utm_campaign=lux_search_pylesosy_{campaign_id}&utm_content=aqvion-pro_{ad_id}_{source_type}&utm_term={keyword} | L7: Aqvion-Pro | M7: Россия | N7: Каталог техники||Доставка и оплата||Сервис и гарантия||Моющий пылесос Cleneo Pro | O7: Пылесосы, швабры, кофемашины, аэрогрили||Пункты выдачи и курьер Ozon, срок после ввода адреса||Бесплатный вывоз СДЭК при гарантийном случае||Пар и распыление: полы, ковры, мебель, авто | P7: https://luxhomme.store/catalog?utm_source=yandex&utm_medium=cpc&utm_campaign=lux_search_pylesosy_{campaign_id}&utm_content=aqvion-pro_sitelink_{ad_id}_{source_type}&utm_term={keyword}||https://luxhomme.store/delivery?utm_source=yandex&utm_medium=cpc&utm_campaign=lux_search_pylesosy_{campaign_id}&utm_content=aqvion-pro_sitelink_{ad_id}_{source_type}&utm_term={keyword}||https://luxhomme.store/service?utm_source=yandex&utm_medium=cpc&utm_campaign=lux_search_pylesosy_{campaign_id}&utm_content=aqvion-pro_sitelink_{ad_id}_{source_type}&utm_term={keyword}||https://luxhomme.store/products/kompaktnyj-moyushhij-pylesos-cleneo-pro?utm_source=yandex&utm_medium=cpc&utm_campaign=lux_search_pylesosy_{campaign_id}&utm_content=aqvion-pro_sitelink_{ad_id}_{source_type}&utm_term={keyword} | Q7: Гарантия 3 года||Скидка 20% по промокоду||Доставка через Ozon||Служба заботы 9–21 МСК||Сервисный центр в РФ
A8: Lux | Поиск | Пылесосы | B8: - | C8: Текстово-графическое | D8: - | E8: Aqvion Pro | F8: 1 | G8: вертикальные моющие пылесосы с сушкой | H8: Вертикальный моющий пылесос Aqvion Pro со скидкой 20% | I8: Самоочистка и сушка | J8: Беспроводной, 15 000 Па, до 60 минут работы. Промокод DIRECT20 на сайте. | K8: https://luxhomme.store/products/vertikalnyj-moyushhij-pylesos-aqvion-pro?utm_source=yandex&utm_medium=cpc&utm_campaign=lux_search_pylesosy_{campaign_id}&utm_content=aqvion-pro_{ad_id}_{source_type}&utm_term={keyword} | L8: Aqvion-Pro | M8: Россия | N8: Каталог техники||Доставка и оплата||Сервис и гарантия||Моющий пылесос Cleneo Pro | O8: Пылесосы, швабры, кофемашины, аэрогрили||Пункты выдачи и курьер Ozon, срок после ввода адреса||Бесплатный вывоз СДЭК при гарантийном случае||Пар и распыление: полы, ковры, мебель, авто | P8: https://luxhomme.store/catalog?utm_source=yandex&utm_medium=cpc&utm_campaign=lux_search_pylesosy_{campaign_id}&utm_content=aqvion-pro_sitelink_{ad_id}_{source_type}&utm_term={keyword}||https://luxhomme.store/delivery?utm_source=yandex&utm_medium=cpc&utm_campaign=lux_search_pylesosy_{campaign_id}&utm_content=aqvion-pro_sitelink_{ad_id}_{source_type}&utm_term={keyword}||https://luxhomme.store/service?utm_source=yandex&utm_medium=cpc&utm_campaign=lux_search_pylesosy_{campaign_id}&utm_content=aqvion-pro_sitelink_{ad_id}_{source_type}&utm_term={keyword}||https://luxhomme.store/products/kompaktnyj-moyushhij-pylesos-cleneo-pro?utm_source=yandex&utm_medium=cpc&utm_campaign=lux_search_pylesosy_{campaign_id}&utm_content=aqvion-pro_sitelink_{ad_id}_{source_type}&utm_term={keyword} | Q8: Гарантия 3 года||Скидка 20% по промокоду||Доставка через Ozon||Служба заботы 9–21 МСК||Сервисный центр в РФ
A9: Lux | Поиск | Пылесосы | B9: - | C9: Текстово-графическое | D9: - | E9: Aqvion Pro | F9: 1 | G9: моющий пылесос вертикальный станция | H9: Вертикальный моющий пылесос Aqvion Pro со скидкой 20% | I9: Самоочистка и сушка | J9: Беспроводной, 15 000 Па, до 60 минут работы. Промокод DIRECT20 на сайте. | K9: https://luxhomme.store/products/vertikalnyj-moyushhij-pylesos-aqvion-pro?utm_source=yandex&utm_medium=cpc&utm_campaign=lux_search_pylesosy_{campaign_id}&utm_content=aqvion-pro_{ad_id}_{source_type}&utm_term={keyword} | L9: Aqvion-Pro | M9: Россия | N9: Каталог техники||Доставка и оплата||Сервис и гарантия||Моющий пылесос Cleneo Pro | O9: Пылесосы, швабры, кофемашины, аэрогрили||Пункты выдачи и курьер Ozon, срок после ввода адреса||Бесплатный вывоз СДЭК при гарантийном случае||Пар и распыление: полы, ковры, мебель, авто | P9: https://luxhomme.store/catalog?utm_source=yandex&utm_medium=cpc&utm_campaign=lux_search_pylesosy_{campaign_id}&utm_content=aqvion-pro_sitelink_{ad_id}_{source_type}&utm_term={keyword}||https://luxhomme.store/delivery?utm_source=yandex&utm_medium=cpc&utm_campaign=lux_search_pylesosy_{campaign_id}&utm_content=aqvion-pro_sitelink_{ad_id}_{source_type}&utm_term={keyword}||https://luxhomme.store/service?utm_source=yandex&utm_medium=cpc&utm_campaign=lux_search_pylesosy_{campaign_id}&utm_content=aqvion-pro_sitelink_{ad_id}_{source_type}&utm_term={keyword}||https://luxhomme.store/products/kompaktnyj-moyushhij-pylesos-cleneo-pro?utm_source=yandex&utm_medium=cpc&utm_campaign=lux_search_pylesosy_{campaign_id}&utm_content=aqvion-pro_sitelink_{ad_id}_{source_type}&utm_term={keyword} | Q9: Гарантия 3 года||Скидка 20% по промокоду||Доставка через Ozon||Служба заботы 9–21 МСК||Сервисный центр в РФ
A10: Lux | Поиск | Пылесосы | B10: - | C10: Текстово-графическое | D10: - | E10: Aqvion Pro | F10: 1 | G10: моющий пылесос вертикальный со станцией | H10: Вертикальный моющий пылесос Aqvion Pro со скидкой 20% | I10: Самоочистка и сушка | J10: Беспроводной, 15 000 Па, до 60 минут работы. Промокод DIRECT20 на сайте. | K10: https://luxhomme.store/products/vertikalnyj-moyushhij-pylesos-aqvion-pro?utm_source=yandex&utm_medium=cpc&utm_campaign=lux_search_pylesosy_{campaign_id}&utm_content=aqvion-pro_{ad_id}_{source_type}&utm_term={keyword} | L10: Aqvion-Pro | M10: Россия | N10: Каталог техники||Доставка и оплата||Сервис и гарантия||Моющий пылесос Cleneo Pro | O10: Пылесосы, швабры, кофемашины, аэрогрили||Пункты выдачи и курьер Ozon, срок после ввода адреса||Бесплатный вывоз СДЭК при гарантийном случае||Пар и распыление: полы, ковры, мебель, авто | P10: https://luxhomme.store/catalog?utm_source=yandex&utm_medium=cpc&utm_campaign=lux_search_pylesosy_{campaign_id}&utm_content=aqvion-pro_sitelink_{ad_id}_{source_type}&utm_term={keyword}||https://luxhomme.store/delivery?utm_source=yandex&utm_medium=cpc&utm_campaign=lux_search_pylesosy_{campaign_id}&utm_content=aqvion-pro_sitelink_{ad_id}_{source_type}&utm_term={keyword}||https://luxhomme.store/service?utm_source=yandex&utm_medium=cpc&utm_campaign=lux_search_pylesosy_{campaign_id}&utm_content=aqvion-pro_sitelink_{ad_id}_{source_type}&utm_term={keyword}||https://luxhomme.store/products/kompaktnyj-moyushhij-pylesos-cleneo-pro?utm_source=yandex&utm_medium=cpc&utm_campaign=lux_search_pylesosy_{campaign_id}&utm_content=aqvion-pro_sitelink_{ad_id}_{source_type}&utm_term={keyword} | Q10: Гарантия 3 года||Скидка 20% по промокоду||Доставка через Ozon||Служба заботы 9–21 МСК||Сервисный центр в РФ
A11: Lux | Поиск | Пылесосы | B11: - | C11: Текстово-графическое | D11: - | E11: Aqvion Pro | F11: 1 | G11: беспроводные моющие пылесосы для дома вертикальные | H11: Вертикальный моющий пылесос Aqvion Pro со скидкой 20% | I11: Самоочистка и сушка | J11: Беспроводной, 15 000 Па, до 60 минут работы. Промокод DIRECT20 на сайте. | K11: https://luxhomme.store/products/vertikalnyj-moyushhij-pylesos-aqvion-pro?utm_source=yandex&utm_medium=cpc&utm_campaign=lux_search_pylesosy_{campaign_id}&utm_content=aqvion-pro_{ad_id}_{source_type}&utm_term={keyword} | L11: Aqvion-Pro | M11: Россия | N11: Каталог техники||Доставка и оплата||Сервис и гарантия||Моющий пылесос Cleneo Pro | O11: Пылесосы, швабры, кофемашины, аэрогрили||Пункты выдачи и курьер Ozon, срок после ввода адреса||Бесплатный вывоз СДЭК при гарантийном случае||Пар и распыление: полы, ковры, мебель, авто | P11: https://luxhomme.store/catalog?utm_source=yandex&utm_medium=cpc&utm_campaign=lux_search_pylesosy_{campaign_id}&utm_content=aqvion-pro_sitelink_{ad_id}_{source_type}&utm_term={keyword}||https://luxhomme.store/delivery?utm_source=yandex&utm_medium=cpc&utm_campaign=lux_search_pylesosy_{campaign_id}&utm_content=aqvion-pro_sitelink_{ad_id}_{source_type}&utm_term={keyword}||https://luxhomme.store/service?utm_source=yandex&utm_medium=cpc&utm_campaign=lux_search_pylesosy_{campaign_id}&utm_content=aqvion-pro_sitelink_{ad_id}_{source_type}&utm_term={keyword}||https://luxhomme.store/products/kompaktnyj-moyushhij-pylesos-cleneo-pro?utm_source=yandex&utm_medium=cpc&utm_campaign=lux_search_pylesosy_{campaign_id}&utm_content=aqvion-pro_sitelink_{ad_id}_{source_type}&utm_term={keyword} | Q11: Гарантия 3 года||Скидка 20% по промокоду||Доставка через Ozon||Служба заботы 9–21 МСК||Сервисный центр в РФ
A12: Lux | Поиск | Пылесосы | B12: - | C12: Текстово-графическое | D12: - | E12: Aqvion Pro | F12: 1 | G12: вертикальный моющий пылесос для дома | H12: Вертикальный моющий пылесос Aqvion Pro со скидкой 20% | I12: Самоочистка и сушка | J12: Беспроводной, 15 000 Па, до 60 минут работы. Промокод DIRECT20 на сайте. | K12: https://luxhomme.store/products/vertikalnyj-moyushhij-pylesos-aqvion-pro?utm_source=yandex&utm_medium=cpc&utm_campaign=lux_search_pylesosy_{campaign_id}&utm_content=aqvion-pro_{ad_id}_{source_type}&utm_term={keyword} | L12: Aqvion-Pro | M12: Россия | N12: Каталог техники||Доставка и оплата||Сервис и гарантия||Моющий пылесос Cleneo Pro | O12: Пылесосы, швабры, кофемашины, аэрогрили||Пункты выдачи и курьер Ozon, срок после ввода адреса||Бесплатный вывоз СДЭК при гарантийном случае||Пар и распыление: полы, ковры, мебель, авто | P12: https://luxhomme.store/catalog?utm_source=yandex&utm_medium=cpc&utm_campaign=lux_search_pylesosy_{campaign_id}&utm_content=aqvion-pro_sitelink_{ad_id}_{source_type}&utm_term={keyword}||https://luxhomme.store/delivery?utm_source=yandex&utm_medium=cpc&utm_campaign=lux_search_pylesosy_{campaign_id}&utm_content=aqvion-pro_sitelink_{ad_id}_{source_type}&utm_term={keyword}||https://luxhomme.store/service?utm_source=yandex&utm_medium=cpc&utm_campaign=lux_search_pylesosy_{campaign_id}&utm_content=aqvion-pro_sitelink_{ad_id}_{source_type}&utm_term={keyword}||https://luxhomme.store/products/kompaktnyj-moyushhij-pylesos-cleneo-pro?utm_source=yandex&utm_medium=cpc&utm_campaign=lux_search_pylesosy_{campaign_id}&utm_content=aqvion-pro_sitelink_{ad_id}_{source_type}&utm_term={keyword} | Q12: Гарантия 3 года||Скидка 20% по промокоду||Доставка через Ozon||Служба заботы 9–21 МСК||Сервисный центр в РФ
A13: Lux | Поиск | Пылесосы | B13: - | C13: Текстово-графическое | D13: - | E13: Aqvion Pro | F13: 1 | G13: вертикальный моющий пылесос сухая | H13: Вертикальный моющий пылесос Aqvion Pro со скидкой 20% | I13: Самоочистка и сушка | J13: Беспроводной, 15 000 Па, до 60 минут работы. Промокод DIRECT20 на сайте. | K13: https://luxhomme.store/products/vertikalnyj-moyushhij-pylesos-aqvion-pro?utm_source=yandex&utm_medium=cpc&utm_campaign=lux_search_pylesosy_{campaign_id}&utm_content=aqvion-pro_{ad_id}_{source_type}&utm_term={keyword} | L13: Aqvion-Pro | M13: Россия | N13: Каталог техники||Доставка и оплата||Сервис и гарантия||Моющий пылесос Cleneo Pro | O13: Пылесосы, швабры, кофемашины, аэрогрили||Пункты выдачи и курьер Ozon, срок после ввода адреса||Бесплатный вывоз СДЭК при гарантийном случае||Пар и распыление: полы, ковры, мебель, авто | P13: https://luxhomme.store/catalog?utm_source=yandex&utm_medium=cpc&utm_campaign=lux_search_pylesosy_{campaign_id}&utm_content=aqvion-pro_sitelink_{ad_id}_{source_type}&utm_term={keyword}||https://luxhomme.store/delivery?utm_source=yandex&utm_medium=cpc&utm_campaign=lux_search_pylesosy_{campaign_id}&utm_content=aqvion-pro_sitelink_{ad_id}_{source_type}&utm_term={keyword}||https://luxhomme.store/service?utm_source=yandex&utm_medium=cpc&utm_campaign=lux_search_pylesosy_{campaign_id}&utm_content=aqvion-pro_sitelink_{ad_id}_{source_type}&utm_term={keyword}||https://luxhomme.store/products/kompaktnyj-moyushhij-pylesos-cleneo-pro?utm_source=yandex&utm_medium=cpc&utm_campaign=lux_search_pylesosy_{campaign_id}&utm_content=aqvion-pro_sitelink_{ad_id}_{source_type}&utm_term={keyword} | Q13: Гарантия 3 года||Скидка 20% по промокоду||Доставка через Ozon||Служба заботы 9–21 МСК||Сервисный центр в РФ
A14: Lux | Поиск | Пылесосы | B14: - | C14: Текстово-графическое | D14: - | E14: Aqvion Pro | F14: 1 | G14: вертикальный пылесос моющий сухая и влажная | H14: Вертикальный моющий пылесос Aqvion Pro со скидкой 20% | I14: Самоочистка и сушка | J14: Беспроводной, 15 000 Па, до 60 минут работы. Промокод DIRECT20 на сайте. | K14: https://luxhomme.store/products/vertikalnyj-moyushhij-pylesos-aqvion-pro?utm_source=yandex&utm_medium=cpc&utm_campaign=lux_search_pylesosy_{campaign_id}&utm_content=aqvion-pro_{ad_id}_{source_type}&utm_term={keyword} | L14: Aqvion-Pro | M14: Россия | N14: Каталог техники||Доставка и оплата||Сервис и гарантия||Моющий пылесос Cleneo Pro | O14: Пылесосы, швабры, кофемашины, аэрогрили||Пункты выдачи и курьер Ozon, срок после ввода адреса||Бесплатный вывоз СДЭК при гарантийном случае||Пар и распыление: полы, ковры, мебель, авто | P14: https://luxhomme.store/catalog?utm_source=yandex&utm_medium=cpc&utm_campaign=lux_search_pylesosy_{campaign_id}&utm_content=aqvion-pro_sitelink_{ad_id}_{source_type}&utm_term={keyword}||https://luxhomme.store/delivery?utm_source=yandex&utm_medium=cpc&utm_campaign=lux_search_pylesosy_{campaign_id}&utm_content=aqvion-pro_sitelink_{ad_id}_{source_type}&utm_term={keyword}||https://luxhomme.store/service?utm_source=yandex&utm_medium=cpc&utm_campaign=lux_search_pylesosy_{campaign_id}&utm_content=aqvion-pro_sitelink_{ad_id}_{source_type}&utm_term={keyword}||https://luxhomme.store/products/kompaktnyj-moyushhij-pylesos-cleneo-pro?utm_source=yandex&utm_medium=cpc&utm_campaign=lux_search_pylesosy_{campaign_id}&utm_content=aqvion-pro_sitelink_{ad_id}_{source_type}&utm_term={keyword} | Q14: Гарантия 3 года||Скидка 20% по промокоду||Доставка через Ozon||Служба заботы 9–21 МСК||Сервисный центр в РФ
... A29: Lux | Поиск | Пылесосы | B29: - | C29: Текстово-графическое | D29: - | E29: Aqvion Pro | F29: 1 | G29: aqvion pro купить | H29: Вертикальный моющий пылесос Aqvion Pro со скидкой 20% | I29: Самоочистка и сушка | J29: Беспроводной, 15 000 Па, до 60 минут работы. Промокод DIRECT20 на сайте. | K29: https://luxhomme.store/products/vertikalnyj-moyushhij-pylesos-aqvion-pro?utm_source=yandex&utm_medium=cpc&utm_campaign=lux_search_pylesosy_{campaign_id}&utm_content=aqvion-pro_{ad_id}_{source_type}&utm_term={keyword} | L29: Aqvion-Pro | M29: Россия | N29: Каталог техники||Доставка и оплата||Сервис и гарантия||Моющий пылесос Cleneo Pro | O29: Пылесосы, швабры, кофемашины, аэрогрили||Пункты выдачи и курьер Ozon, срок после ввода адреса||Бесплатный вывоз СДЭК при гарантийном случае||Пар и распыление: полы, ковры, мебель, авто | P29: https://luxhomme.store/catalog?utm_source=yandex&utm_medium=cpc&utm_campaign=lux_search_pylesosy_{campaign_id}&utm_content=aqvion-pro_sitelink_{ad_id}_{source_type}&utm_term={keyword}||https://luxhomme.store/delivery?utm_source=yandex&utm_medium=cpc&utm_campaign=lux_search_pylesosy_{campaign_id}&utm_content=aqvion-pro_sitelink_{ad_id}_{source_type}&utm_term={keyword}||https://luxhomme.store/service?utm_source=yandex&utm_medium=cpc&utm_campaign=lux_search_pylesosy_{campaign_id}&utm_content=aqvion-pro_sitelink_{ad_id}_{source_type}&utm_term={keyword}||https://luxhomme.store/products/kompaktnyj-moyushhij-pylesos-cleneo-pro?utm_source=yandex&utm_medium=cpc&utm_campaign=lux_search_pylesosy_{campaign_id}&utm_content=aqvion-pro_sitelink_{ad_id}_{source_type}&utm_term={keyword} | Q29: Гарантия 3 года||Скидка 20% по промокоду||Доставка через Ozon||Служба заботы 9–21 МСК||Сервисный центр в РФ
A30: Lux | Поиск | Пылесосы | B30: + | C30: Текстово-графическое | D30: - | E30: Aqvion Pro | F30: 1 | H30: Беспроводной моющий пылесос с самоочисткой | I30: Скидка 20% на сайте | J30: Aqvion Pro: сушка на базе, LED-подсветка, наклон 170°. Гарантия 3 года. | K30: https://luxhomme.store/products/vertikalnyj-moyushhij-pylesos-aqvion-pro?utm_source=yandex&utm_medium=cpc&utm_campaign=lux_search_pylesosy_{campaign_id}&utm_content=aqvion-pro_{ad_id}_{source_type}&utm_term={keyword} | L30: Aqvion-Pro | M30: Россия | N30: Каталог техники||Доставка и оплата||Сервис и гарантия||Моющий пылесос Cleneo Pro | O30: Пылесосы, швабры, кофемашины, аэрогрили||Пункты выдачи и курьер Ozon, срок после ввода адреса||Бесплатный вывоз СДЭК при гарантийном случае||Пар и распыление: полы, ковры, мебель, авто | P30: https://luxhomme.store/catalog?utm_source=yandex&utm_medium=cpc&utm_campaign=lux_search_pylesosy_{campaign_id}&utm_content=aqvion-pro_sitelink_{ad_id}_{source_type}&utm_term={keyword}||https://luxhomme.store/delivery?utm_source=yandex&utm_medium=cpc&utm_campaign=lux_search_pylesosy_{campaign_id}&utm_content=aqvion-pro_sitelink_{ad_id}_{source_type}&utm_term={keyword}||https://luxhomme.store/service?utm_source=yandex&utm_medium=cpc&utm_campaign=lux_search_pylesosy_{campaign_id}&utm_content=aqvion-pro_sitelink_{ad_id}_{source_type}&utm_term={keyword}||https://luxhomme.store/products/kompaktnyj-moyushhij-pylesos-cleneo-pro?utm_source=yandex&utm_medium=cpc&utm_campaign=lux_search_pylesosy_{campaign_id}&utm_content=aqvion-pro_sitelink_{ad_id}_{source_type}&utm_term={keyword} | Q30: Гарантия 3 года||Скидка 20% по промокоду||Доставка через Ozon||Служба заботы 9–21 МСК||Сервисный центр в РФ
A31: Lux | Поиск | Пылесосы | B31: + | C31: Текстово-графическое | D31: - | E31: Aqvion Pro | F31: 1 | H31: Купить моющий пылесос Aqvion Pro за 15 992 ₽ | I31: Промокод DIRECT20 | J31: Баки 550 и 600 мл, аккумулятор 5000 мАч, голосовые подсказки, IPX4. | K31: https://luxhomme.store/products/vertikalnyj-moyushhij-pylesos-aqvion-pro?utm_source=yandex&utm_medium=cpc&utm_campaign=lux_search_pylesosy_{campaign_id}&utm_content=aqvion-pro_{ad_id}_{source_type}&utm_term={keyword} | L31: Aqvion-Pro | M31: Россия | N31: Каталог техники||Доставка и оплата||Сервис и гарантия||Моющий пылесос Cleneo Pro | O31: Пылесосы, швабры, кофемашины, аэрогрили||Пункты выдачи и курьер Ozon, срок после ввода адреса||Бесплатный вывоз СДЭК при гарантийном случае||Пар и распыление: полы, ковры, мебель, авто | P31: https://luxhomme.store/catalog?utm_source=yandex&utm_medium=cpc&utm_campaign=lux_search_pylesosy_{campaign_id}&utm_content=aqvion-pro_sitelink_{ad_id}_{source_type}&utm_term={keyword}||https://luxhomme.store/delivery?utm_source=yandex&utm_medium=cpc&utm_campaign=lux_search_pylesosy_{campaign_id}&utm_content=aqvion-pro_sitelink_{ad_id}_{source_type}&utm_term={keyword}||https://luxhomme.store/service?utm_source=yandex&utm_medium=cpc&utm_campaign=lux_search_pylesosy_{campaign_id}&utm_content=aqvion-pro_sitelink_{ad_id}_{source_type}&utm_term={keyword}||https://luxhomme.store/products/kompaktnyj-moyushhij-pylesos-cleneo-pro?utm_source=yandex&utm_medium=cpc&utm_campaign=lux_search_pylesosy_{campaign_id}&utm_content=aqvion-pro_sitelink_{ad_id}_{source_type}&utm_term={keyword} | Q31: Гарантия 3 года||Скидка 20% по промокоду||Доставка через Ozon||Служба заботы 9–21 МСК||Сервисный центр в РФ
A32: Lux | Поиск | Пылесосы | B32: - | C32: Текстово-графическое | D32: - | E32: Cleneo Pro | F32: 2 | G32: моющий пылесос купить | H32: Моющий пылесос Cleneo Pro для дома и авто со скидкой 20% | I32: Пар и распыление | J32: Полы, ковры, мебель и салон авто. 11 насадок, баки 1,8 и 1,2 л. Промокод DIRECT20 | K32: https://luxhomme.store/products/kompaktnyj-moyushhij-pylesos-cleneo-pro?utm_source=yandex&utm_medium=cpc&utm_campaign=lux_search_pylesosy_{campaign_id}&utm_content=cleneo-pro_{ad_id}_{source_type}&utm_term={keyword} | L32: Cleneo-Pro | M32: Россия | N32: Каталог техники||Доставка и оплата||Сервис и гарантия||Моющий пылесос Aqvion Pro | O32: Пылесосы, швабры, кофемашины, аэрогрили||Пункты выдачи и курьер Ozon, срок после ввода адреса||Бесплатный вывоз СДЭК при гарантийном случае||Беспроводной, 15 000 Па, самоочистка и сушка | P32: https://luxhomme.store/catalog?utm_source=yandex&utm_medium=cpc&utm_campaign=lux_search_pylesosy_{campaign_id}&utm_content=cleneo-pro_sitelink_{ad_id}_{source_type}&utm_term={keyword}||https://luxhomme.store/delivery?utm_source=yandex&utm_medium=cpc&utm_campaign=lux_search_pylesosy_{campaign_id}&utm_content=cleneo-pro_sitelink_{ad_id}_{source_type}&utm_term={keyword}||https://luxhomme.store/service?utm_source=yandex&utm_medium=cpc&utm_campaign=lux_search_pylesosy_{campaign_id}&utm_content=cleneo-pro_sitelink_{ad_id}_{source_type}&utm_term={keyword}||https://luxhomme.store/products/vertikalnyj-moyushhij-pylesos-aqvion-pro?utm_source=yandex&utm_medium=cpc&utm_campaign=lux_search_pylesosy_{campaign_id}&utm_content=cleneo-pro_sitelink_{ad_id}_{source_type}&utm_term={keyword} | Q32: Гарантия 3 года||Скидка 20% по промокоду||Доставка через Ozon||Служба заботы 9–21 МСК||Сервисный центр в РФ | R32: вертикальный, робот, беспроводной, аккумуляторный, ручной, средство, шампунь, сменные
A33: Lux | Поиск | Пылесосы | B33: - | C33: Текстово-графическое | D33: - | E33: Cleneo Pro | F33: 2 | G33: моющий пылесос для дома купить | H33: Моющий пылесос Cleneo Pro для дома и авто со скидкой 20% | I33: Пар и распыление | J33: Полы, ковры, мебель и салон авто. 11 насадок, баки 1,8 и 1,2 л. Промокод DIRECT20 | K33: https://luxhomme.store/products/kompaktnyj-moyushhij-pylesos-cleneo-pro?utm_source=yandex&utm_medium=cpc&utm_campaign=lux_search_pylesosy_{campaign_id}&utm_content=cleneo-pro_{ad_id}_{source_type}&utm_term={keyword} | L33: Cleneo-Pro | M33: Россия | N33: Каталог техники||Доставка и оплата||Сервис и гарантия||Моющий пылесос Aqvion Pro | O33: Пылесосы, швабры, кофемашины, аэрогрили||Пункты выдачи и курьер Ozon, срок после ввода адреса||Бесплатный вывоз СДЭК при гарантийном случае||Беспроводной, 15 000 Па, самоочистка и сушка | P33: https://luxhomme.store/catalog?utm_source=yandex&utm_medium=cpc&utm_campaign=lux_search_pylesosy_{campaign_id}&utm_content=cleneo-pro_sitelink_{ad_id}_{source_type}&utm_term={keyword}||https://luxhomme.store/delivery?utm_source=yandex&utm_medium=cpc&utm_campaign=lux_search_pylesosy_{campaign_id}&utm_content=cleneo-pro_sitelink_{ad_id}_{source_type}&utm_term={keyword}||https://luxhomme.store/service?utm_source=yandex&utm_medium=cpc&utm_campaign=lux_search_pylesosy_{campaign_id}&utm_content=cleneo-pro_sitelink_{ad_id}_{source_type}&utm_term={keyword}||https://luxhomme.store/products/vertikalnyj-moyushhij-pylesos-aqvion-pro?utm_source=yandex&utm_medium=cpc&utm_campaign=lux_search_pylesosy_{campaign_id}&utm_content=cleneo-pro_sitelink_{ad_id}_{source_type}&utm_term={keyword} | Q33: Гарантия 3 года||Скидка 20% по промокоду||Доставка через Ozon||Служба заботы 9–21 МСК||Сервисный центр в РФ
A34: Lux | Поиск | Пылесосы | B34: - | C34: Текстово-графическое | D34: - | E34: Cleneo Pro | F34: 2 | G34: компактный моющий пылесос | H34: Моющий пылесос Cleneo Pro для дома и авто со скидкой 20% | I34: Пар и распыление | J34: Полы, ковры, мебель и салон авто. 11 насадок, баки 1,8 и 1,2 л. Промокод DIRECT20 | K34: https://luxhomme.store/products/kompaktnyj-moyushhij-pylesos-cleneo-pro?utm_source=yandex&utm_medium=cpc&utm_campaign=lux_search_pylesosy_{campaign_id}&utm_content=cleneo-pro_{ad_id}_{source_type}&utm_term={keyword} | L34: Cleneo-Pro | M34: Россия | N34: Каталог техники||Доставка и оплата||Сервис и гарантия||Моющий пылесос Aqvion Pro | O34: Пылесосы, швабры, кофемашины, аэрогрили||Пункты выдачи и курьер Ozon, срок после ввода адреса||Бесплатный вывоз СДЭК при гарантийном случае||Беспроводной, 15 000 Па, самоочистка и сушка | P34: https://luxhomme.store/catalog?utm_source=yandex&utm_medium=cpc&utm_campaign=lux_search_pylesosy_{campaign_id}&utm_content=cleneo-pro_sitelink_{ad_id}_{source_type}&utm_term={keyword}||https://luxhomme.store/delivery?utm_source=yandex&utm_medium=cpc&utm_campaign=lux_search_pylesosy_{campaign_id}&utm_content=cleneo-pro_sitelink_{ad_id}_{source_type}&utm_term={keyword}||https://luxhomme.store/service?utm_source=yandex&utm_medium=cpc&utm_campaign=lux_search_pylesosy_{campaign_id}&utm_content=cleneo-pro_sitelink_{ad_id}_{source_type}&utm_term={keyword}||https://luxhomme.store/products/vertikalnyj-moyushhij-pylesos-aqvion-pro?utm_source=yandex&utm_medium=cpc&utm_campaign=lux_search_pylesosy_{campaign_id}&utm_content=cleneo-pro_sitelink_{ad_id}_{source_type}&utm_term={keyword} | Q34: Гарантия 3 года||Скидка 20% по промокоду||Доставка через Ozon||Служба заботы 9–21 МСК||Сервисный центр в РФ
A35: Lux | Поиск | Пылесосы | B35: - | C35: Текстово-графическое | D35: - | E35: Cleneo Pro | F35: 2 | G35: моющий пылесос цена | H35: Моющий пылесос Cleneo Pro для дома и авто со скидкой 20% | I35: Пар и распыление | J35: Полы, ковры, мебель и салон авто. 11 насадок, баки 1,8 и 1,2 л. Промокод DIRECT20 | K35: https://luxhomme.store/products/kompaktnyj-moyushhij-pylesos-cleneo-pro?utm_source=yandex&utm_medium=cpc&utm_campaign=lux_search_pylesosy_{campaign_id}&utm_content=cleneo-pro_{ad_id}_{source_type}&utm_term={keyword} | L35: Cleneo-Pro | M35: Россия | N35: Каталог техники||Доставка и оплата||Сервис и гарантия||Моющий пылесос Aqvion Pro | O35: Пылесосы, швабры, кофемашины, аэрогрили||Пункты выдачи и курьер Ozon, срок после ввода адреса||Бесплатный вывоз СДЭК при гарантийном случае||Беспроводной, 15 000 Па, самоочистка и сушка | P35: https://luxhomme.store/catalog?utm_source=yandex&utm_medium=cpc&utm_campaign=lux_search_pylesosy_{campaign_id}&utm_content=cleneo-pro_sitelink_{ad_id}_{source_type}&utm_term={keyword}||https://luxhomme.store/delivery?utm_source=yandex&utm_medium=cpc&utm_campaign=lux_search_pylesosy_{campaign_id}&utm_content=cleneo-pro_sitelink_{ad_id}_{source_type}&utm_term={keyword}||https://luxhomme.store/service?utm_source=yandex&utm_medium=cpc&utm_campaign=lux_search_pylesosy_{campaign_id}&utm_content=cleneo-pro_sitelink_{ad_id}_{source_type}&utm_term={keyword}||https://luxhomme.store/products/vertikalnyj-moyushhij-pylesos-aqvion-pro?utm_source=yandex&utm_medium=cpc&utm_campaign=lux_search_pylesosy_{campaign_id}&utm_content=cleneo-pro_sitelink_{ad_id}_{source_type}&utm_term={keyword} | Q35: Гарантия 3 года||Скидка 20% по промокоду||Доставка через Ozon||Служба заботы 9–21 МСК||Сервисный центр в РФ
A36: Lux | Поиск | Пылесосы | B36: - | C36: Текстово-графическое | D36: - | E36: Cleneo Pro | F36: 2 | G36: моющий пылесос для мебели | H36: Моющий пылесос Cleneo Pro для дома и авто со скидкой 20% | I36: Пар и распыление | J36: Полы, ковры, мебель и салон авто. 11 насадок, баки 1,8 и 1,2 л. Промокод DIRECT20 | K36: https://luxhomme.store/products/kompaktnyj-moyushhij-pylesos-cleneo-pro?utm_source=yandex&utm_medium=cpc&utm_campaign=lux_search_pylesosy_{campaign_id}&utm_content=cleneo-pro_{ad_id}_{source_type}&utm_term={keyword} | L36: Cleneo-Pro | M36: Россия | N36: Каталог техники||Доставка и оплата||Сервис и гарантия||Моющий пылесос Aqvion Pro | O36: Пылесосы, швабры, кофемашины, аэрогрили||Пункты выдачи и курьер Ozon, срок после ввода адреса||Бесплатный вывоз СДЭК при гарантийном случае||Беспроводной, 15 000 Па, самоочистка и сушка | P36: https://luxhomme.store/catalog?utm_source=yandex&utm_medium=cpc&utm_campaign=lux_search_pylesosy_{campaign_id}&utm_content=cleneo-pro_sitelink_{ad_id}_{source_type}&utm_term={keyword}||https://luxhomme.store/delivery?utm_source=yandex&utm_medium=cpc&utm_campaign=lux_search_pylesosy_{campaign_id}&utm_content=cleneo-pro_sitelink_{ad_id}_{source_type}&utm_term={keyword}||https://luxhomme.store/service?utm_source=yandex&utm_medium=cpc&utm_campaign=lux_search_pylesosy_{campaign_id}&utm_content=cleneo-pro_sitelink_{ad_id}_{source_type}&utm_term={keyword}||https://luxhomme.store/products/vertikalnyj-moyushhij-pylesos-aqvion-pro?utm_source=yandex&utm_medium=cpc&utm_campaign=lux_search_pylesosy_{campaign_id}&utm_content=cleneo-pro_sitelink_{ad_id}_{source_type}&utm_term={keyword} | Q36: Гарантия 3 года||Скидка 20% по промокоду||Доставка через Ozon||Служба заботы 9–21 МСК||Сервисный центр в РФ
A37: Lux | Поиск | Пылесосы | B37: - | C37: Текстово-графическое | D37: - | E37: Cleneo Pro | F37: 2 | G37: моющий пылесос для химчистки мебели | H37: Моющий пылесос Cleneo Pro для дома и авто со скидкой 20% | I37: Пар и распыление | J37: Полы, ковры, мебель и салон авто. 11 насадок, баки 1,8 и 1,2 л. Промокод DIRECT20 | K37: https://luxhomme.store/products/kompaktnyj-moyushhij-pylesos-cleneo-pro?utm_source=yandex&utm_medium=cpc&utm_campaign=lux_search_pylesosy_{campaign_id}&utm_content=cleneo-pro_{ad_id}_{source_type}&utm_term={keyword} | L37: Cleneo-Pro | M37: Россия | N37: Каталог техники||Доставка и оплата||Сервис и гарантия||Моющий пылесос Aqvion Pro | O37: Пылесосы, швабры, кофемашины, аэрогрили||Пункты выдачи и курьер Ozon, срок после ввода адреса||Бесплатный вывоз СДЭК при гарантийном случае||Беспроводной, 15 000 Па, самоочистка и сушка | P37: https://luxhomme.store/catalog?utm_source=yandex&utm_medium=cpc&utm_campaign=lux_search_pylesosy_{campaign_id}&utm_content=cleneo-pro_sitelink_{ad_id}_{source_type}&utm_term={keyword}||https://luxhomme.store/delivery?utm_source=yandex&utm_medium=cpc&utm_campaign=lux_search_pylesosy_{campaign_id}&utm_content=cleneo-pro_sitelink_{ad_id}_{source_type}&utm_term={keyword}||https://luxhomme.store/service?utm_source=yandex&utm_medium=cpc&utm_campaign=lux_search_pylesosy_{campaign_id}&utm_content=cleneo-pro_sitelink_{ad_id}_{source_type}&utm_term={keyword}||https://luxhomme.store/products/vertikalnyj-moyushhij-pylesos-aqvion-pro?utm_source=yandex&utm_medium=cpc&utm_campaign=lux_search_pylesosy_{campaign_id}&utm_content=cleneo-pro_sitelink_{ad_id}_{source_type}&utm_term={keyword} | Q37: Гарантия 3 года||Скидка 20% по промокоду||Доставка через Ozon||Служба заботы 9–21 МСК||Сервисный центр в РФ
A38: Lux | Поиск | Пылесосы | B38: - | C38: Текстово-графическое | D38: - | E38: Cleneo Pro | F38: 2 | G38: пылесос для химчистки дивана | H38: Моющий пылесос Cleneo Pro для дома и авто со скидкой 20% | I38: Пар и распыление | J38: Полы, ковры, мебель и салон авто. 11 насадок, баки 1,8 и 1,2 л. Промокод DIRECT20 | K38: https://luxhomme.store/products/kompaktnyj-moyushhij-pylesos-cleneo-pro?utm_source=yandex&utm_medium=cpc&utm_campaign=lux_search_pylesosy_{campaign_id}&utm_content=cleneo-pro_{ad_id}_{source_type}&utm_term={keyword} | L38: Cleneo-Pro | M38: Россия | N38: Каталог техники||Доставка и оплата||Сервис и гарантия||Моющий пылесос Aqvion Pro | O38: Пылесосы, швабры, кофемашины, аэрогрили||Пункты выдачи и курьер Ozon, срок после ввода адреса||Бесплатный вывоз СДЭК при гарантийном случае||Беспроводной, 15 000 Па, самоочистка и сушка | P38: https://luxhomme.store/catalog?utm_source=yandex&utm_medium=cpc&utm_campaign=lux_search_pylesosy_{campaign_id}&utm_content=cleneo-pro_sitelink_{ad_id}_{source_type}&utm_term={keyword}||https://luxhomme.store/delivery?utm_source=yandex&utm_medium=cpc&utm_campaign=lux_search_pylesosy_{campaign_id}&utm_content=cleneo-pro_sitelink_{ad_id}_{source_type}&utm_term={keyword}||https://luxhomme.store/service?utm_source=yandex&utm_medium=cpc&utm_campaign=lux_search_pylesosy_{campaign_id}&utm_content=cleneo-pro_sitelink_{ad_id}_{source_type}&utm_term={keyword}||https://luxhomme.store/products/vertikalnyj-moyushhij-pylesos-aqvion-pro?utm_source=yandex&utm_medium=cpc&utm_campaign=lux_search_pylesosy_{campaign_id}&utm_content=cleneo-pro_sitelink_{ad_id}_{source_type}&utm_term={keyword} | Q38: Гарантия 3 года||Скидка 20% по промокоду||Доставка через Ozon||Служба заботы 9–21 МСК||Сервисный центр в РФ
A39: Lux | Поиск | Пылесосы | B39: - | C39: Текстово-графическое | D39: - | E39: Cleneo Pro | F39: 2 | G39: пылесос для химчистки мягкой мебели | H39: Моющий пылесос Cleneo Pro для дома и авто со скидкой 20% | I39: Пар и распыление | J39: Полы, ковры, мебель и салон авто. 11 насадок, баки 1,8 и 1,2 л. Промокод DIRECT20 | K39: https://luxhomme.store/products/kompaktnyj-moyushhij-pylesos-cleneo-pro?utm_source=yandex&utm_medium=cpc&utm_campaign=lux_search_pylesosy_{campaign_id}&utm_content=cleneo-pro_{ad_id}_{source_type}&utm_term={keyword} | L39: Cleneo-Pro | M39: Россия | N39: Каталог техники||Доставка и оплата||Сервис и гарантия||Моющий пылесос Aqvion Pro | O39: Пылесосы, швабры, кофемашины, аэрогрили||Пункты выдачи и курьер Ozon, срок после ввода адреса||Бесплатный вывоз СДЭК при гарантийном случае||Беспроводной, 15 000 Па, самоочистка и сушка | P39: https://luxhomme.store/catalog?utm_source=yandex&utm_medium=cpc&utm_campaign=lux_search_pylesosy_{campaign_id}&utm_content=cleneo-pro_sitelink_{ad_id}_{source_type}&utm_term={keyword}||https://luxhomme.store/delivery?utm_source=yandex&utm_medium=cpc&utm_campaign=lux_search_pylesosy_{campaign_id}&utm_content=cleneo-pro_sitelink_{ad_id}_{source_type}&utm_term={keyword}||https://luxhomme.store/service?utm_source=yandex&utm_medium=cpc&utm_campaign=lux_search_pylesosy_{campaign_id}&utm_content=cleneo-pro_sitelink_{ad_id}_{source_type}&utm_term={keyword}||https://luxhomme.store/products/vertikalnyj-moyushhij-pylesos-aqvion-pro?utm_source=yandex&utm_medium=cpc&utm_campaign=lux_search_pylesosy_{campaign_id}&utm_content=cleneo-pro_sitelink_{ad_id}_{source_type}&utm_term={keyword} | Q39: Гарантия 3 года||Скидка 20% по промокоду||Доставка через Ozon||Служба заботы 9–21 МСК||Сервисный центр в РФ
A40: Lux | Поиск | Пылесосы | B40: - | C40: Текстово-графическое | D40: - | E40: Cleneo Pro | F40: 2 | G40: моющий пылесос для дивана | H40: Моющий пылесос Cleneo Pro для дома и авто со скидкой 20% | I40: Пар и распыление | J40: Полы, ковры, мебель и салон авто. 11 насадок, баки 1,8 и 1,2 л. Промокод DIRECT20 | K40: https://luxhomme.store/products/kompaktnyj-moyushhij-pylesos-cleneo-pro?utm_source=yandex&utm_medium=cpc&utm_campaign=lux_search_pylesosy_{campaign_id}&utm_content=cleneo-pro_{ad_id}_{source_type}&utm_term={keyword} | L40: Cleneo-Pro | M40: Россия | N40: Каталог техники||Доставка и оплата||Сервис и гарантия||Моющий пылесос Aqvion Pro | O40: Пылесосы, швабры, кофемашины, аэрогрили||Пункты выдачи и курьер Ozon, срок после ввода адреса||Бесплатный вывоз СДЭК при гарантийном случае||Беспроводной, 15 000 Па, самоочистка и сушка | P40: https://luxhomme.store/catalog?utm_source=yandex&utm_medium=cpc&utm_campaign=lux_search_pylesosy_{campaign_id}&utm_content=cleneo-pro_sitelink_{ad_id}_{source_type}&utm_term={keyword}||https://luxhomme.store/delivery?utm_source=yandex&utm_medium=cpc&utm_campaign=lux_search_pylesosy_{campaign_id}&utm_content=cleneo-pro_sitelink_{ad_id}_{source_type}&utm_term={keyword}||https://luxhomme.store/service?utm_source=yandex&utm_medium=cpc&utm_campaign=lux_search_pylesosy_{campaign_id}&utm_content=cleneo-pro_sitelink_{ad_id}_{source_type}&utm_term={keyword}||https://luxhomme.store/products/vertikalnyj-moyushhij-pylesos-aqvion-pro?utm_source=yandex&utm_medium=cpc&utm_campaign=lux_search_pylesosy_{campaign_id}&utm_content=cleneo-pro_sitelink_{ad_id}_{source_type}&utm_term={keyword} | Q40: Гарантия 3 года||Скидка 20% по промокоду||Доставка через Ozon||Служба заботы 9–21 МСК||Сервисный центр в РФ
A41: Lux | Поиск | Пылесосы | B41: - | C41: Текстово-графическое | D41: - | E41: Cleneo Pro | F41: 2 | G41: пылесос для химчистки купить | H41: Моющий пылесос Cleneo Pro для дома и авто со скидкой 20% | I41: Пар и распыление | J41: Полы, ковры, мебель и салон авто. 11 насадок, баки 1,8 и 1,2 л. Промокод DIRECT20 | K41: https://luxhomme.store/products/kompaktnyj-moyushhij-pylesos-cleneo-pro?utm_source=yandex&utm_medium=cpc&utm_campaign=lux_search_pylesosy_{campaign_id}&utm_content=cleneo-pro_{ad_id}_{source_type}&utm_term={keyword} | L41: Cleneo-Pro | M41: Россия | N41: Каталог техники||Доставка и оплата||Сервис и гарантия||Моющий пылесос Aqvion Pro | O41: Пылесосы, швабры, кофемашины, аэрогрили||Пункты выдачи и курьер Ozon, срок после ввода адреса||Бесплатный вывоз СДЭК при гарантийном случае||Беспроводной, 15 000 Па, самоочистка и сушка | P41: https://luxhomme.store/catalog?utm_source=yandex&utm_medium=cpc&utm_campaign=lux_search_pylesosy_{campaign_id}&utm_content=cleneo-pro_sitelink_{ad_id}_{source_type}&utm_term={keyword}||https://luxhomme.store/delivery?utm_source=yandex&utm_medium=cpc&utm_campaign=lux_search_pylesosy_{campaign_id}&utm_content=cleneo-pro_sitelink_{ad_id}_{source_type}&utm_term={keyword}||https://luxhomme.store/service?utm_source=yandex&utm_medium=cpc&utm_campaign=lux_search_pylesosy_{campaign_id}&utm_content=cleneo-pro_sitelink_{ad_id}_{source_type}&utm_term={keyword}||https://luxhomme.store/products/vertikalnyj-moyushhij-pylesos-aqvion-pro?utm_source=yandex&utm_medium=cpc&utm_campaign=lux_search_pylesosy_{campaign_id}&utm_content=cleneo-pro_sitelink_{ad_id}_{source_type}&utm_term={keyword} | Q41: Гарантия 3 года||Скидка 20% по промокоду||Доставка через Ozon||Служба заботы 9–21 МСК||Сервисный центр в РФ
A42: Lux | Поиск | Пылесосы | B42: - | C42: Текстово-графическое | D42: - | E42: Cleneo Pro | F42: 2 | G42: моющий пылесос для автомобиля | H42: Моющий пылесос Cleneo Pro для дома и авто со скидкой 20% | I42: Пар и распыление | J42: Полы, ковры, мебель и салон авто. 11 насадок, баки 1,8 и 1,2 л. Промокод DIRECT20 | K42: https://luxhomme.store/products/kompaktnyj-moyushhij-pylesos-cleneo-pro?utm_source=yandex&utm_medium=cpc&utm_campaign=lux_search_pylesosy_{campaign_id}&utm_content=cleneo-pro_{ad_id}_{source_type}&utm_term={keyword} | L42: Cleneo-Pro | M42: Россия | N42: Каталог техники||Доставка и оплата||Сервис и гарантия||Моющий пылесос Aqvion Pro | O42: Пылесосы, швабры, кофемашины, аэрогрили||Пункты выдачи и курьер Ozon, срок после ввода адреса||Бесплатный вывоз СДЭК при гарантийном случае||Беспроводной, 15 000 Па, самоочистка и сушка | P42: https://luxhomme.store/catalog?utm_source=yandex&utm_medium=cpc&utm_campaign=lux_search_pylesosy_{campaign_id}&utm_content=cleneo-pro_sitelink_{ad_id}_{source_type}&utm_term={keyword}||https://luxhomme.store/delivery?utm_source=yandex&utm_medium=cpc&utm_campaign=lux_search_pylesosy_{campaign_id}&utm_content=cleneo-pro_sitelink_{ad_id}_{source_type}&utm_term={keyword}||https://luxhomme.store/service?utm_source=yandex&utm_medium=cpc&utm_campaign=lux_search_pylesosy_{campaign_id}&utm_content=cleneo-pro_sitelink_{ad_id}_{source_type}&utm_term={keyword}||https://luxhomme.store/products/vertikalnyj-moyushhij-pylesos-aqvion-pro?utm_source=yandex&utm_medium=cpc&utm_campaign=lux_search_pylesosy_{campaign_id}&utm_content=cleneo-pro_sitelink_{ad_id}_{source_type}&utm_term={keyword} | Q42: Гарантия 3 года||Скидка 20% по промокоду||Доставка через Ozon||Служба заботы 9–21 МСК||Сервисный центр в РФ
A43: Lux | Поиск | Пылесосы | B43: - | C43: Текстово-графическое | D43: - | E43: Cleneo Pro | F43: 2 | G43: пылесос для химчистки салона автомобиля | H43: Моющий пылесос Cleneo Pro для дома и авто со скидкой 20% | I43: Пар и распыление | J43: Полы, ковры, мебель и салон авто. 11 насадок, баки 1,8 и 1,2 л. Промокод DIRECT20 | K43: https://luxhomme.store/products/kompaktnyj-moyushhij-pylesos-cleneo-pro?utm_source=yandex&utm_medium=cpc&utm_campaign=lux_search_pylesosy_{campaign_id}&utm_content=cleneo-pro_{ad_id}_{source_type}&utm_term={keyword} | L43: Cleneo-Pro | M43: Россия | N43: Каталог техники||Доставка и оплата||Сервис и гарантия||Моющий пылесос Aqvion Pro | O43: Пылесосы, швабры, кофемашины, аэрогрили||Пункты выдачи и курьер Ozon, срок после ввода адреса||Бесплатный вывоз СДЭК при гарантийном случае||Беспроводной, 15 000 Па, самоочистка и сушка | P43: https://luxhomme.store/catalog?utm_source=yandex&utm_medium=cpc&utm_campaign=lux_search_pylesosy_{campaign_id}&utm_content=cleneo-pro_sitelink_{ad_id}_{source_type}&utm_term={keyword}||https://luxhomme.store/delivery?utm_source=yandex&utm_medium=cpc&utm_campaign=lux_search_pylesosy_{campaign_id}&utm_content=cleneo-pro_sitelink_{ad_id}_{source_type}&utm_term={keyword}||https://luxhomme.store/service?utm_source=yandex&utm_medium=cpc&utm_campaign=lux_search_pylesosy_{campaign_id}&utm_content=cleneo-pro_sitelink_{ad_id}_{source_type}&utm_term={keyword}||https://luxhomme.store/products/vertikalnyj-moyushhij-pylesos-aqvion-pro?utm_source=yandex&utm_medium=cpc&utm_campaign=lux_search_pylesosy_{campaign_id}&utm_content=cleneo-pro_sitelink_{ad_id}_{source_type}&utm_term={keyword} | Q43: Гарантия 3 года||Скидка 20% по промокоду||Доставка через Ozon||Служба заботы 9–21 МСК||Сервисный центр в РФ
A44: Lux | Поиск | Пылесосы | B44: - | C44: Текстово-графическое | D44: - | E44: Cleneo Pro | F44: 2 | G44: моющий пылесос для авто и дома | H44: Моющий пылесос Cleneo Pro для дома и авто со скидкой 20% | I44: Пар и распыление | J44: Полы, ковры, мебель и салон авто. 11 насадок, баки 1,8 и 1,2 л. Промокод DIRECT20 | K44: https://luxhomme.store/products/kompaktnyj-moyushhij-pylesos-cleneo-pro?utm_source=yandex&utm_medium=cpc&utm_campaign=lux_search_pylesosy_{campaign_id}&utm_content=cleneo-pro_{ad_id}_{source_type}&utm_term={keyword} | L44: Cleneo-Pro | M44: Россия | N44: Каталог техники||Доставка и оплата||Сервис и гарантия||Моющий пылесос Aqvion Pro | O44: Пылесосы, швабры, кофемашины, аэрогрили||Пункты выдачи и курьер Ozon, срок после ввода адреса||Бесплатный вывоз СДЭК при гарантийном случае||Беспроводной, 15 000 Па, самоочистка и сушка | P44: https://luxhomme.store/catalog?utm_source=yandex&utm_medium=cpc&utm_campaign=lux_search_pylesosy_{campaign_id}&utm_content=cleneo-pro_sitelink_{ad_id}_{source_type}&utm_term={keyword}||https://luxhomme.store/delivery?utm_source=yandex&utm_medium=cpc&utm_campaign=lux_search_pylesosy_{campaign_id}&utm_content=cleneo-pro_sitelink_{ad_id}_{source_type}&utm_term={keyword}||https://luxhomme.store/service?utm_source=yandex&utm_medium=cpc&utm_campaign=lux_search_pylesosy_{campaign_id}&utm_content=cleneo-pro_sitelink_{ad_id}_{source_type}&utm_term={keyword}||https://luxhomme.store/products/vertikalnyj-moyushhij-pylesos-aqvion-pro?utm_source=yandex&utm_medium=cpc&utm_campaign=lux_search_pylesosy_{campaign_id}&utm_content=cleneo-pro_sitelink_{ad_id}_{source_type}&utm_term={keyword} | Q44: Гарантия 3 года||Скидка 20% по промокоду||Доставка через Ozon||Служба заботы 9–21 МСК||Сервисный центр в РФ
... A52: Lux | Поиск | Пылесосы | B52: - | C52: Текстово-графическое | D52: - | E52: Cleneo Pro | F52: 2 | G52: cleneo pro купить | H52: Моющий пылесос Cleneo Pro для дома и авто со скидкой 20% | I52: Пар и распыление | J52: Полы, ковры, мебель и салон авто. 11 насадок, баки 1,8 и 1,2 л. Промокод DIRECT20 | K52: https://luxhomme.store/products/kompaktnyj-moyushhij-pylesos-cleneo-pro?utm_source=yandex&utm_medium=cpc&utm_campaign=lux_search_pylesosy_{campaign_id}&utm_content=cleneo-pro_{ad_id}_{source_type}&utm_term={keyword} | L52: Cleneo-Pro | M52: Россия | N52: Каталог техники||Доставка и оплата||Сервис и гарантия||Моющий пылесос Aqvion Pro | O52: Пылесосы, швабры, кофемашины, аэрогрили||Пункты выдачи и курьер Ozon, срок после ввода адреса||Бесплатный вывоз СДЭК при гарантийном случае||Беспроводной, 15 000 Па, самоочистка и сушка | P52: https://luxhomme.store/catalog?utm_source=yandex&utm_medium=cpc&utm_campaign=lux_search_pylesosy_{campaign_id}&utm_content=cleneo-pro_sitelink_{ad_id}_{source_type}&utm_term={keyword}||https://luxhomme.store/delivery?utm_source=yandex&utm_medium=cpc&utm_campaign=lux_search_pylesosy_{campaign_id}&utm_content=cleneo-pro_sitelink_{ad_id}_{source_type}&utm_term={keyword}||https://luxhomme.store/service?utm_source=yandex&utm_medium=cpc&utm_campaign=lux_search_pylesosy_{campaign_id}&utm_content=cleneo-pro_sitelink_{ad_id}_{source_type}&utm_term={keyword}||https://luxhomme.store/products/vertikalnyj-moyushhij-pylesos-aqvion-pro?utm_source=yandex&utm_medium=cpc&utm_campaign=lux_search_pylesosy_{campaign_id}&utm_content=cleneo-pro_sitelink_{ad_id}_{source_type}&utm_term={keyword} | Q52: Гарантия 3 года||Скидка 20% по промокоду||Доставка через Ozon||Служба заботы 9–21 МСК||Сервисный центр в РФ
A53: Lux | Поиск | Пылесосы | B53: + | C53: Текстово-графическое | D53: - | E53: Cleneo Pro | F53: 2 | H53: Пылесос для химчистки мебели и ковров с паром | I53: Скидка 20% на сайте | J53: Cleneo Pro: всасывание от 15 000 Па, пар 20–26 г/мин, нагрев 30 секунд. | K53: https://luxhomme.store/products/kompaktnyj-moyushhij-pylesos-cleneo-pro?utm_source=yandex&utm_medium=cpc&utm_campaign=lux_search_pylesosy_{campaign_id}&utm_content=cleneo-pro_{ad_id}_{source_type}&utm_term={keyword} | L53: Cleneo-Pro | M53: Россия | N53: Каталог техники||Доставка и оплата||Сервис и гарантия||Моющий пылесос Aqvion Pro | O53: Пылесосы, швабры, кофемашины, аэрогрили||Пункты выдачи и курьер Ozon, срок после ввода адреса||Бесплатный вывоз СДЭК при гарантийном случае||Беспроводной, 15 000 Па, самоочистка и сушка | P53: https://luxhomme.store/catalog?utm_source=yandex&utm_medium=cpc&utm_campaign=lux_search_pylesosy_{campaign_id}&utm_content=cleneo-pro_sitelink_{ad_id}_{source_type}&utm_term={keyword}||https://luxhomme.store/delivery?utm_source=yandex&utm_medium=cpc&utm_campaign=lux_search_pylesosy_{campaign_id}&utm_content=cleneo-pro_sitelink_{ad_id}_{source_type}&utm_term={keyword}||https://luxhomme.store/service?utm_source=yandex&utm_medium=cpc&utm_campaign=lux_search_pylesosy_{campaign_id}&utm_content=cleneo-pro_sitelink_{ad_id}_{source_type}&utm_term={keyword}||https://luxhomme.store/products/vertikalnyj-moyushhij-pylesos-aqvion-pro?utm_source=yandex&utm_medium=cpc&utm_campaign=lux_search_pylesosy_{campaign_id}&utm_content=cleneo-pro_sitelink_{ad_id}_{source_type}&utm_term={keyword} | Q53: Гарантия 3 года||Скидка 20% по промокоду||Доставка через Ozon||Служба заботы 9–21 МСК||Сервисный центр в РФ
A54: Lux | Поиск | Пылесосы | B54: + | C54: Текстово-графическое | D54: - | E54: Cleneo Pro | F54: 2 | H54: Купить моющий пылесос Cleneo Pro за 13 592 ₽ | I54: Промокод DIRECT20 | J54: Сухая и влажная уборка, 4 режима, кабель 4,5 м. Гарантия 3 года. | K54: https://luxhomme.store/products/kompaktnyj-moyushhij-pylesos-cleneo-pro?utm_source=yandex&utm_medium=cpc&utm_campaign=lux_search_pylesosy_{campaign_id}&utm_content=cleneo-pro_{ad_id}_{source_type}&utm_term={keyword} | L54: Cleneo-Pro | M54: Россия | N54: Каталог техники||Доставка и оплата||Сервис и гарантия||Моющий пылесос Aqvion Pro | O54: Пылесосы, швабры, кофемашины, аэрогрили||Пункты выдачи и курьер Ozon, срок после ввода адреса||Бесплатный вывоз СДЭК при гарантийном случае||Беспроводной, 15 000 Па, самоочистка и сушка | P54: https://luxhomme.store/catalog?utm_source=yandex&utm_medium=cpc&utm_campaign=lux_search_pylesosy_{campaign_id}&utm_content=cleneo-pro_sitelink_{ad_id}_{source_type}&utm_term={keyword}||https://luxhomme.store/delivery?utm_source=yandex&utm_medium=cpc&utm_campaign=lux_search_pylesosy_{campaign_id}&utm_content=cleneo-pro_sitelink_{ad_id}_{source_type}&utm_term={keyword}||https://luxhomme.store/service?utm_source=yandex&utm_medium=cpc&utm_campaign=lux_search_pylesosy_{campaign_id}&utm_content=cleneo-pro_sitelink_{ad_id}_{source_type}&utm_term={keyword}||https://luxhomme.store/products/vertikalnyj-moyushhij-pylesos-aqvion-pro?utm_source=yandex&utm_medium=cpc&utm_campaign=lux_search_pylesosy_{campaign_id}&utm_content=cleneo-pro_sitelink_{ad_id}_{source_type}&utm_term={keyword} | Q54: Гарантия 3 года||Скидка 20% по промокоду||Доставка через Ozon||Служба заботы 9–21 МСК||Сервисный центр в РФ
A55: Lux | Поиск | Пылесосы | B55: - | C55: Текстово-графическое | D55: - | E55: Aerlyn | F55: 3 | G55: вертикальный пылесос купить | H55: Беспроводной пылесос Aerlyn 2 в 1 — до 35 кПа | I55: Скидка 20% на сайте | J55: До 60 минут работы, HEPA-фильтр, турбощётка, 8 насадок. Промокод DIRECT20. | K55: https://luxhomme.store/products/vertikalnyj-suhoj-pylesos-aerlyn?utm_source=yandex&utm_medium=cpc&utm_campaign=lux_search_pylesosy_{campaign_id}&utm_content=aerlyn_{ad_id}_{source_type}&utm_term={keyword} | L55: Aerlyn | M55: Россия | N55: Каталог техники||Доставка и оплата||Сервис и гарантия||Моющий пылесос Aqvion Pro | O55: Пылесосы, швабры, кофемашины, аэрогрили||Пункты выдачи и курьер Ozon, срок после ввода адреса||Бесплатный вывоз СДЭК при гарантийном случае||Беспроводной, 15 000 Па, самоочистка и сушка | P55: https://luxhomme.store/catalog?utm_source=yandex&utm_medium=cpc&utm_campaign=lux_search_pylesosy_{campaign_id}&utm_content=aerlyn_sitelink_{ad_id}_{source_type}&utm_term={keyword}||https://luxhomme.store/delivery?utm_source=yandex&utm_medium=cpc&utm_campaign=lux_search_pylesosy_{campaign_id}&utm_content=aerlyn_sitelink_{ad_id}_{source_type}&utm_term={keyword}||https://luxhomme.store/service?utm_source=yandex&utm_medium=cpc&utm_campaign=lux_search_pylesosy_{campaign_id}&utm_content=aerlyn_sitelink_{ad_id}_{source_type}&utm_term={keyword}||https://luxhomme.store/products/vertikalnyj-moyushhij-pylesos-aqvion-pro?utm_source=yandex&utm_medium=cpc&utm_campaign=lux_search_pylesosy_{campaign_id}&utm_content=aerlyn_sitelink_{ad_id}_{source_type}&utm_term={keyword} | Q55: Гарантия 3 года||Скидка 20% по промокоду||Доставка через Ozon||Служба заботы 9–21 МСК||Сервисный центр в РФ | R55: моющий, моет, влажной, влажная, робот, автомобильный, машины, строительный, садовый, щетка, сменные
A56: Lux | Поиск | Пылесосы | B56: - | C56: Текстово-графическое | D56: - | E56: Aerlyn | F56: 3 | G56: беспроводной пылесос купить | H56: Беспроводной пылесос Aerlyn 2 в 1 — до 35 кПа | I56: Скидка 20% на сайте | J56: До 60 минут работы, HEPA-фильтр, турбощётка, 8 насадок. Промокод DIRECT20. | K56: https://luxhomme.store/products/vertikalnyj-suhoj-pylesos-aerlyn?utm_source=yandex&utm_medium=cpc&utm_campaign=lux_search_pylesosy_{campaign_id}&utm_content=aerlyn_{ad_id}_{source_type}&utm_term={keyword} | L56: Aerlyn | M56: Россия | N56: Каталог техники||Доставка и оплата||Сервис и гарантия||Моющий пылесос Aqvion Pro | O56: Пылесосы, швабры, кофемашины, аэрогрили||Пункты выдачи и курьер Ozon, срок после ввода адреса||Бесплатный вывоз СДЭК при гарантийном случае||Беспроводной, 15 000 Па, самоочистка и сушка | P56: https://luxhomme.store/catalog?utm_source=yandex&utm_medium=cpc&utm_campaign=lux_search_pylesosy_{campaign_id}&utm_content=aerlyn_sitelink_{ad_id}_{source_type}&utm_term={keyword}||https://luxhomme.store/delivery?utm_source=yandex&utm_medium=cpc&utm_campaign=lux_search_pylesosy_{campaign_id}&utm_content=aerlyn_sitelink_{ad_id}_{source_type}&utm_term={keyword}||https://luxhomme.store/service?utm_source=yandex&utm_medium=cpc&utm_campaign=lux_search_pylesosy_{campaign_id}&utm_content=aerlyn_sitelink_{ad_id}_{source_type}&utm_term={keyword}||https://luxhomme.store/products/vertikalnyj-moyushhij-pylesos-aqvion-pro?utm_source=yandex&utm_medium=cpc&utm_campaign=lux_search_pylesosy_{campaign_id}&utm_content=aerlyn_sitelink_{ad_id}_{source_type}&utm_term={keyword} | Q56: Гарантия 3 года||Скидка 20% по промокоду||Доставка через Ozon||Служба заботы 9–21 МСК||Сервисный центр в РФ
A57: Lux | Поиск | Пылесосы | B57: - | C57: Текстово-графическое | D57: - | E57: Aerlyn | F57: 3 | G57: беспроводной пылесос для дома купить | H57: Беспроводной пылесос Aerlyn 2 в 1 — до 35 кПа | I57: Скидка 20% на сайте | J57: До 60 минут работы, HEPA-фильтр, турбощётка, 8 насадок. Промокод DIRECT20. | K57: https://luxhomme.store/products/vertikalnyj-suhoj-pylesos-aerlyn?utm_source=yandex&utm_medium=cpc&utm_campaign=lux_search_pylesosy_{campaign_id}&utm_content=aerlyn_{ad_id}_{source_type}&utm_term={keyword} | L57: Aerlyn | M57: Россия | N57: Каталог техники||Доставка и оплата||Сервис и гарантия||Моющий пылесос Aqvion Pro | O57: Пылесосы, швабры, кофемашины, аэрогрили||Пункты выдачи и курьер Ozon, срок после ввода адреса||Бесплатный вывоз СДЭК при гарантийном случае||Беспроводной, 15 000 Па, самоочистка и сушка | P57: https://luxhomme.store/catalog?utm_source=yandex&utm_medium=cpc&utm_campaign=lux_search_pylesosy_{campaign_id}&utm_content=aerlyn_sitelink_{ad_id}_{source_type}&utm_term={keyword}||https://luxhomme.store/delivery?utm_source=yandex&utm_medium=cpc&utm_campaign=lux_search_pylesosy_{campaign_id}&utm_content=aerlyn_sitelink_{ad_id}_{source_type}&utm_term={keyword}||https://luxhomme.store/service?utm_source=yandex&utm_medium=cpc&utm_campaign=lux_search_pylesosy_{campaign_id}&utm_content=aerlyn_sitelink_{ad_id}_{source_type}&utm_term={keyword}||https://luxhomme.store/products/vertikalnyj-moyushhij-pylesos-aqvion-pro?utm_source=yandex&utm_medium=cpc&utm_campaign=lux_search_pylesosy_{campaign_id}&utm_content=aerlyn_sitelink_{ad_id}_{source_type}&utm_term={keyword} | Q57: Гарантия 3 года||Скидка 20% по промокоду||Доставка через Ozon||Служба заботы 9–21 МСК||Сервисный центр в РФ
A58: Lux | Поиск | Пылесосы | B58: - | C58: Текстово-графическое | D58: - | E58: Aerlyn | F58: 3 | G58: вертикальный пылесос цена | H58: Беспроводной пылесос Aerlyn 2 в 1 — до 35 кПа | I58: Скидка 20% на сайте | J58: До 60 минут работы, HEPA-фильтр, турбощётка, 8 насадок. Промокод DIRECT20. | K58: https://luxhomme.store/products/vertikalnyj-suhoj-pylesos-aerlyn?utm_source=yandex&utm_medium=cpc&utm_campaign=lux_search_pylesosy_{campaign_id}&utm_content=aerlyn_{ad_id}_{source_type}&utm_term={keyword} | L58: Aerlyn | M58: Россия | N58: Каталог техники||Доставка и оплата||Сервис и гарантия||Моющий пылесос Aqvion Pro | O58: Пылесосы, швабры, кофемашины, аэрогрили||Пункты выдачи и курьер Ozon, срок после ввода адреса||Бесплатный вывоз СДЭК при гарантийном случае||Беспроводной, 15 000 Па, самоочистка и сушка | P58: https://luxhomme.store/catalog?utm_source=yandex&utm_medium=cpc&utm_campaign=lux_search_pylesosy_{campaign_id}&utm_content=aerlyn_sitelink_{ad_id}_{source_type}&utm_term={keyword}||https://luxhomme.store/delivery?utm_source=yandex&utm_medium=cpc&utm_campaign=lux_search_pylesosy_{campaign_id}&utm_content=aerlyn_sitelink_{ad_id}_{source_type}&utm_term={keyword}||https://luxhomme.store/service?utm_source=yandex&utm_medium=cpc&utm_campaign=lux_search_pylesosy_{campaign_id}&utm_content=aerlyn_sitelink_{ad_id}_{source_type}&utm_term={keyword}||https://luxhomme.store/products/vertikalnyj-moyushhij-pylesos-aqvion-pro?utm_source=yandex&utm_medium=cpc&utm_campaign=lux_search_pylesosy_{campaign_id}&utm_content=aerlyn_sitelink_{ad_id}_{source_type}&utm_term={keyword} | Q58: Гарантия 3 года||Скидка 20% по промокоду||Доставка через Ozon||Служба заботы 9–21 МСК||Сервисный центр в РФ
A59: Lux | Поиск | Пылесосы | B59: - | C59: Текстово-графическое | D59: - | E59: Aerlyn | F59: 3 | G59: аккумуляторный пылесос вертикальный | H59: Беспроводной пылесос Aerlyn 2 в 1 — до 35 кПа | I59: Скидка 20% на сайте | J59: До 60 минут работы, HEPA-фильтр, турбощётка, 8 насадок. Промокод DIRECT20. | K59: https://luxhomme.store/products/vertikalnyj-suhoj-pylesos-aerlyn?utm_source=yandex&utm_medium=cpc&utm_campaign=lux_search_pylesosy_{campaign_id}&utm_content=aerlyn_{ad_id}_{source_type}&utm_term={keyword} | L59: Aerlyn | M59: Россия | N59: Каталог техники||Доставка и оплата||Сервис и гарантия||Моющий пылесос Aqvion Pro | O59: Пылесосы, швабры, кофемашины, аэрогрили||Пункты выдачи и курьер Ozon, срок после ввода адреса||Бесплатный вывоз СДЭК при гарантийном случае||Беспроводной, 15 000 Па, самоочистка и сушка | P59: https://luxhomme.store/catalog?utm_source=yandex&utm_medium=cpc&utm_campaign=lux_search_pylesosy_{campaign_id}&utm_content=aerlyn_sitelink_{ad_id}_{source_type}&utm_term={keyword}||https://luxhomme.store/delivery?utm_source=yandex&utm_medium=cpc&utm_campaign=lux_search_pylesosy_{campaign_id}&utm_content=aerlyn_sitelink_{ad_id}_{source_type}&utm_term={keyword}||https://luxhomme.store/service?utm_source=yandex&utm_medium=cpc&utm_campaign=lux_search_pylesosy_{campaign_id}&utm_content=aerlyn_sitelink_{ad_id}_{source_type}&utm_term={keyword}||https://luxhomme.store/products/vertikalnyj-moyushhij-pylesos-aqvion-pro?utm_source=yandex&utm_medium=cpc&utm_campaign=lux_search_pylesosy_{campaign_id}&utm_content=aerlyn_sitelink_{ad_id}_{source_type}&utm_term={keyword} | Q59: Гарантия 3 года||Скидка 20% по промокоду||Доставка через Ozon||Служба заботы 9–21 МСК||Сервисный центр в РФ
A60: Lux | Поиск | Пылесосы | B60: - | C60: Текстово-графическое | D60: - | E60: Aerlyn | F60: 3 | G60: вертикальный пылесос для дома | H60: Беспроводной пылесос Aerlyn 2 в 1 — до 35 кПа | I60: Скидка 20% на сайте | J60: До 60 минут работы, HEPA-фильтр, турбощётка, 8 насадок. Промокод DIRECT20. | K60: https://luxhomme.store/products/vertikalnyj-suhoj-pylesos-aerlyn?utm_source=yandex&utm_medium=cpc&utm_campaign=lux_search_pylesosy_{campaign_id}&utm_content=aerlyn_{ad_id}_{source_type}&utm_term={keyword} | L60: Aerlyn | M60: Россия | N60: Каталог техники||Доставка и оплата||Сервис и гарантия||Моющий пылесос Aqvion Pro | O60: Пылесосы, швабры, кофемашины, аэрогрили||Пункты выдачи и курьер Ozon, срок после ввода адреса||Бесплатный вывоз СДЭК при гарантийном случае||Беспроводной, 15 000 Па, самоочистка и сушка | P60: https://luxhomme.store/catalog?utm_source=yandex&utm_medium=cpc&utm_campaign=lux_search_pylesosy_{campaign_id}&utm_content=aerlyn_sitelink_{ad_id}_{source_type}&utm_term={keyword}||https://luxhomme.store/delivery?utm_source=yandex&utm_medium=cpc&utm_campaign=lux_search_pylesosy_{campaign_id}&utm_content=aerlyn_sitelink_{ad_id}_{source_type}&utm_term={keyword}||https://luxhomme.store/service?utm_source=yandex&utm_medium=cpc&utm_campaign=lux_search_pylesosy_{campaign_id}&utm_content=aerlyn_sitelink_{ad_id}_{source_type}&utm_term={keyword}||https://luxhomme.store/products/vertikalnyj-moyushhij-pylesos-aqvion-pro?utm_source=yandex&utm_medium=cpc&utm_campaign=lux_search_pylesosy_{campaign_id}&utm_content=aerlyn_sitelink_{ad_id}_{source_type}&utm_term={keyword} | Q60: Гарантия 3 года||Скидка 20% по промокоду||Доставка через Ozon||Служба заботы 9–21 МСК||Сервисный центр в РФ
A61: Lux | Поиск | Пылесосы | B61: - | C61: Текстово-графическое | D61: - | E61: Aerlyn | F61: 3 | G61: беспроводной вертикальный пылесос | H61: Беспроводной пылесос Aerlyn 2 в 1 — до 35 кПа | I61: Скидка 20% на сайте | J61: До 60 минут работы, HEPA-фильтр, турбощётка, 8 насадок. Промокод DIRECT20. | K61: https://luxhomme.store/products/vertikalnyj-suhoj-pylesos-aerlyn?utm_source=yandex&utm_medium=cpc&utm_campaign=lux_search_pylesosy_{campaign_id}&utm_content=aerlyn_{ad_id}_{source_type}&utm_term={keyword} | L61: Aerlyn | M61: Россия | N61: Каталог техники||Доставка и оплата||Сервис и гарантия||Моющий пылесос Aqvion Pro | O61: Пылесосы, швабры, кофемашины, аэрогрили||Пункты выдачи и курьер Ozon, срок после ввода адреса||Бесплатный вывоз СДЭК при гарантийном случае||Беспроводной, 15 000 Па, самоочистка и сушка | P61: https://luxhomme.store/catalog?utm_source=yandex&utm_medium=cpc&utm_campaign=lux_search_pylesosy_{campaign_id}&utm_content=aerlyn_sitelink_{ad_id}_{source_type}&utm_term={keyword}||https://luxhomme.store/delivery?utm_source=yandex&utm_medium=cpc&utm_campaign=lux_search_pylesosy_{campaign_id}&utm_content=aerlyn_sitelink_{ad_id}_{source_type}&utm_term={keyword}||https://luxhomme.store/service?utm_source=yandex&utm_medium=cpc&utm_campaign=lux_search_pylesosy_{campaign_id}&utm_content=aerlyn_sitelink_{ad_id}_{source_type}&utm_term={keyword}||https://luxhomme.store/products/vertikalnyj-moyushhij-pylesos-aqvion-pro?utm_source=yandex&utm_medium=cpc&utm_campaign=lux_search_pylesosy_{campaign_id}&utm_content=aerlyn_sitelink_{ad_id}_{source_type}&utm_term={keyword} | Q61: Гарантия 3 года||Скидка 20% по промокоду||Доставка через Ozon||Служба заботы 9–21 МСК||Сервисный центр в РФ
A62: Lux | Поиск | Пылесосы | B62: - | C62: Текстово-графическое | D62: - | E62: Aerlyn | F62: 3 | G62: вертикальный пылесос для ковров | H62: Беспроводной пылесос Aerlyn 2 в 1 — до 35 кПа | I62: Скидка 20% на сайте | J62: До 60 минут работы, HEPA-фильтр, турбощётка, 8 насадок. Промокод DIRECT20. | K62: https://luxhomme.store/products/vertikalnyj-suhoj-pylesos-aerlyn?utm_source=yandex&utm_medium=cpc&utm_campaign=lux_search_pylesosy_{campaign_id}&utm_content=aerlyn_{ad_id}_{source_type}&utm_term={keyword} | L62: Aerlyn | M62: Россия | N62: Каталог техники||Доставка и оплата||Сервис и гарантия||Моющий пылесос Aqvion Pro | O62: Пылесосы, швабры, кофемашины, аэрогрили||Пункты выдачи и курьер Ozon, срок после ввода адреса||Бесплатный вывоз СДЭК при гарантийном случае||Беспроводной, 15 000 Па, самоочистка и сушка | P62: https://luxhomme.store/catalog?utm_source=yandex&utm_medium=cpc&utm_campaign=lux_search_pylesosy_{campaign_id}&utm_content=aerlyn_sitelink_{ad_id}_{source_type}&utm_term={keyword}||https://luxhomme.store/delivery?utm_source=yandex&utm_medium=cpc&utm_campaign=lux_search_pylesosy_{campaign_id}&utm_content=aerlyn_sitelink_{ad_id}_{source_type}&utm_term={keyword}||https://luxhomme.store/service?utm_source=yandex&utm_medium=cpc&utm_campaign=lux_search_pylesosy_{campaign_id}&utm_content=aerlyn_sitelink_{ad_id}_{source_type}&utm_term={keyword}||https://luxhomme.store/products/vertikalnyj-moyushhij-pylesos-aqvion-pro?utm_source=yandex&utm_medium=cpc&utm_campaign=lux_search_pylesosy_{campaign_id}&utm_content=aerlyn_sitelink_{ad_id}_{source_type}&utm_term={keyword} | Q62: Гарантия 3 года||Скидка 20% по промокоду||Доставка через Ozon||Служба заботы 9–21 МСК||Сервисный центр в РФ
A63: Lux | Поиск | Пылесосы | B63: - | C63: Текстово-графическое | D63: - | E63: Aerlyn | F63: 3 | G63: беспроводной пылесос для квартиры | H63: Беспроводной пылесос Aerlyn 2 в 1 — до 35 кПа | I63: Скидка 20% на сайте | J63: До 60 минут работы, HEPA-фильтр, турбощётка, 8 насадок. Промокод DIRECT20. | K63: https://luxhomme.store/products/vertikalnyj-suhoj-pylesos-aerlyn?utm_source=yandex&utm_medium=cpc&utm_campaign=lux_search_pylesosy_{campaign_id}&utm_content=aerlyn_{ad_id}_{source_type}&utm_term={keyword} | L63: Aerlyn | M63: Россия | N63: Каталог техники||Доставка и оплата||Сервис и гарантия||Моющий пылесос Aqvion Pro | O63: Пылесосы, швабры, кофемашины, аэрогрили||Пункты выдачи и курьер Ozon, срок после ввода адреса||Бесплатный вывоз СДЭК при гарантийном случае||Беспроводной, 15 000 Па, самоочистка и сушка | P63: https://luxhomme.store/catalog?utm_source=yandex&utm_medium=cpc&utm_campaign=lux_search_pylesosy_{campaign_id}&utm_content=aerlyn_sitelink_{ad_id}_{source_type}&utm_term={keyword}||https://luxhomme.store/delivery?utm_source=yandex&utm_medium=cpc&utm_campaign=lux_search_pylesosy_{campaign_id}&utm_content=aerlyn_sitelink_{ad_id}_{source_type}&utm_term={keyword}||https://luxhomme.store/service?utm_source=yandex&utm_medium=cpc&utm_campaign=lux_search_pylesosy_{campaign_id}&utm_content=aerlyn_sitelink_{ad_id}_{source_type}&utm_term={keyword}||https://luxhomme.store/products/vertikalnyj-moyushhij-pylesos-aqvion-pro?utm_source=yandex&utm_medium=cpc&utm_campaign=lux_search_pylesosy_{campaign_id}&utm_content=aerlyn_sitelink_{ad_id}_{source_type}&utm_term={keyword} | Q63: Гарантия 3 года||Скидка 20% по промокоду||Доставка через Ozon||Служба заботы 9–21 МСК||Сервисный центр в РФ
A64: Lux | Поиск | Пылесосы | B64: - | C64: Текстово-графическое | D64: - | E64: Aerlyn | F64: 3 | G64: вертикальный пылесос 2 в 1 | H64: Беспроводной пылесос Aerlyn 2 в 1 — до 35 кПа | I64: Скидка 20% на сайте | J64: До 60 минут работы, HEPA-фильтр, турбощётка, 8 насадок. Промокод DIRECT20. | K64: https://luxhomme.store/products/vertikalnyj-suhoj-pylesos-aerlyn?utm_source=yandex&utm_medium=cpc&utm_campaign=lux_search_pylesosy_{campaign_id}&utm_content=aerlyn_{ad_id}_{source_type}&utm_term={keyword} | L64: Aerlyn | M64: Россия | N64: Каталог техники||Доставка и оплата||Сервис и гарантия||Моющий пылесос Aqvion Pro | O64: Пылесосы, швабры, кофемашины, аэрогрили||Пункты выдачи и курьер Ozon, срок после ввода адреса||Бесплатный вывоз СДЭК при гарантийном случае||Беспроводной, 15 000 Па, самоочистка и сушка | P64: https://luxhomme.store/catalog?utm_source=yandex&utm_medium=cpc&utm_campaign=lux_search_pylesosy_{campaign_id}&utm_content=aerlyn_sitelink_{ad_id}_{source_type}&utm_term={keyword}||https://luxhomme.store/delivery?utm_source=yandex&utm_medium=cpc&utm_campaign=lux_search_pylesosy_{campaign_id}&utm_content=aerlyn_sitelink_{ad_id}_{source_type}&utm_term={keyword}||https://luxhomme.store/service?utm_source=yandex&utm_medium=cpc&utm_campaign=lux_search_pylesosy_{campaign_id}&utm_content=aerlyn_sitelink_{ad_id}_{source_type}&utm_term={keyword}||https://luxhomme.store/products/vertikalnyj-moyushhij-pylesos-aqvion-pro?utm_source=yandex&utm_medium=cpc&utm_campaign=lux_search_pylesosy_{campaign_id}&utm_content=aerlyn_sitelink_{ad_id}_{source_type}&utm_term={keyword} | Q64: Гарантия 3 года||Скидка 20% по промокоду||Доставка через Ozon||Служба заботы 9–21 МСК||Сервисный центр в РФ
A65: Lux | Поиск | Пылесосы | B65: - | C65: Текстово-графическое | D65: - | E65: Aerlyn | F65: 3 | G65: пылесос вертикальный ручной 2 в 1 | H65: Беспроводной пылесос Aerlyn 2 в 1 — до 35 кПа | I65: Скидка 20% на сайте | J65: До 60 минут работы, HEPA-фильтр, турбощётка, 8 насадок. Промокод DIRECT20. | K65: https://luxhomme.store/products/vertikalnyj-suhoj-pylesos-aerlyn?utm_source=yandex&utm_medium=cpc&utm_campaign=lux_search_pylesosy_{campaign_id}&utm_content=aerlyn_{ad_id}_{source_type}&utm_term={keyword} | L65: Aerlyn | M65: Россия | N65: Каталог техники||Доставка и оплата||Сервис и гарантия||Моющий пылесос Aqvion Pro | O65: Пылесосы, швабры, кофемашины, аэрогрили||Пункты выдачи и курьер Ozon, срок после ввода адреса||Бесплатный вывоз СДЭК при гарантийном случае||Беспроводной, 15 000 Па, самоочистка и сушка | P65: https://luxhomme.store/catalog?utm_source=yandex&utm_medium=cpc&utm_campaign=lux_search_pylesosy_{campaign_id}&utm_content=aerlyn_sitelink_{ad_id}_{source_type}&utm_term={keyword}||https://luxhomme.store/delivery?utm_source=yandex&utm_medium=cpc&utm_campaign=lux_search_pylesosy_{campaign_id}&utm_content=aerlyn_sitelink_{ad_id}_{source_type}&utm_term={keyword}||https://luxhomme.store/service?utm_source=yandex&utm_medium=cpc&utm_campaign=lux_search_pylesosy_{campaign_id}&utm_content=aerlyn_sitelink_{ad_id}_{source_type}&utm_term={keyword}||https://luxhomme.store/products/vertikalnyj-moyushhij-pylesos-aqvion-pro?utm_source=yandex&utm_medium=cpc&utm_campaign=lux_search_pylesosy_{campaign_id}&utm_content=aerlyn_sitelink_{ad_id}_{source_type}&utm_term={keyword} | Q65: Гарантия 3 года||Скидка 20% по промокоду||Доставка через Ozon||Служба заботы 9–21 МСК||Сервисный центр в РФ
A66: Lux | Поиск | Пылесосы | B66: - | C66: Текстово-графическое | D66: - | E66: Aerlyn | F66: 3 | G66: вертикальный пылесос с hepa фильтром | H66: Беспроводной пылесос Aerlyn 2 в 1 — до 35 кПа | I66: Скидка 20% на сайте | J66: До 60 минут работы, HEPA-фильтр, турбощётка, 8 насадок. Промокод DIRECT20. | K66: https://luxhomme.store/products/vertikalnyj-suhoj-pylesos-aerlyn?utm_source=yandex&utm_medium=cpc&utm_campaign=lux_search_pylesosy_{campaign_id}&utm_content=aerlyn_{ad_id}_{source_type}&utm_term={keyword} | L66: Aerlyn | M66: Россия | N66: Каталог техники||Доставка и оплата||Сервис и гарантия||Моющий пылесос Aqvion Pro | O66: Пылесосы, швабры, кофемашины, аэрогрили||Пункты выдачи и курьер Ozon, срок после ввода адреса||Бесплатный вывоз СДЭК при гарантийном случае||Беспроводной, 15 000 Па, самоочистка и сушка | P66: https://luxhomme.store/catalog?utm_source=yandex&utm_medium=cpc&utm_campaign=lux_search_pylesosy_{campaign_id}&utm_content=aerlyn_sitelink_{ad_id}_{source_type}&utm_term={keyword}||https://luxhomme.store/delivery?utm_source=yandex&utm_medium=cpc&utm_campaign=lux_search_pylesosy_{campaign_id}&utm_content=aerlyn_sitelink_{ad_id}_{source_type}&utm_term={keyword}||https://luxhomme.store/service?utm_source=yandex&utm_medium=cpc&utm_campaign=lux_search_pylesosy_{campaign_id}&utm_content=aerlyn_sitelink_{ad_id}_{source_type}&utm_term={keyword}||https://luxhomme.store/products/vertikalnyj-moyushhij-pylesos-aqvion-pro?utm_source=yandex&utm_medium=cpc&utm_campaign=lux_search_pylesosy_{campaign_id}&utm_content=aerlyn_sitelink_{ad_id}_{source_type}&utm_term={keyword} | Q66: Гарантия 3 года||Скидка 20% по промокоду||Доставка через Ozon||Служба заботы 9–21 МСК||Сервисный центр в РФ
A67: Lux | Поиск | Пылесосы | B67: - | C67: Текстово-графическое | D67: - | E67: Aerlyn | F67: 3 | G67: беспроводной пылесос с турбощеткой | H67: Беспроводной пылесос Aerlyn 2 в 1 — до 35 кПа | I67: Скидка 20% на сайте | J67: До 60 минут работы, HEPA-фильтр, турбощётка, 8 насадок. Промокод DIRECT20. | K67: https://luxhomme.store/products/vertikalnyj-suhoj-pylesos-aerlyn?utm_source=yandex&utm_medium=cpc&utm_campaign=lux_search_pylesosy_{campaign_id}&utm_content=aerlyn_{ad_id}_{source_type}&utm_term={keyword} | L67: Aerlyn | M67: Россия | N67: Каталог техники||Доставка и оплата||Сервис и гарантия||Моющий пылесос Aqvion Pro | O67: Пылесосы, швабры, кофемашины, аэрогрили||Пункты выдачи и курьер Ozon, срок после ввода адреса||Бесплатный вывоз СДЭК при гарантийном случае||Беспроводной, 15 000 Па, самоочистка и сушка | P67: https://luxhomme.store/catalog?utm_source=yandex&utm_medium=cpc&utm_campaign=lux_search_pylesosy_{campaign_id}&utm_content=aerlyn_sitelink_{ad_id}_{source_type}&utm_term={keyword}||https://luxhomme.store/delivery?utm_source=yandex&utm_medium=cpc&utm_campaign=lux_search_pylesosy_{campaign_id}&utm_content=aerlyn_sitelink_{ad_id}_{source_type}&utm_term={keyword}||https://luxhomme.store/service?utm_source=yandex&utm_medium=cpc&utm_campaign=lux_search_pylesosy_{campaign_id}&utm_content=aerlyn_sitelink_{ad_id}_{source_type}&utm_term={keyword}||https://luxhomme.store/products/vertikalnyj-moyushhij-pylesos-aqvion-pro?utm_source=yandex&utm_medium=cpc&utm_campaign=lux_search_pylesosy_{campaign_id}&utm_content=aerlyn_sitelink_{ad_id}_{source_type}&utm_term={keyword} | Q67: Гарантия 3 года||Скидка 20% по промокоду||Доставка через Ozon||Служба заботы 9–21 МСК||Сервисный центр в РФ
... A72: Lux | Поиск | Пылесосы | B72: - | C72: Текстово-графическое | D72: - | E72: Aerlyn | F72: 3 | G72: aerlyn купить | H72: Беспроводной пылесос Aerlyn 2 в 1 — до 35 кПа | I72: Скидка 20% на сайте | J72: До 60 минут работы, HEPA-фильтр, турбощётка, 8 насадок. Промокод DIRECT20. | K72: https://luxhomme.store/products/vertikalnyj-suhoj-pylesos-aerlyn?utm_source=yandex&utm_medium=cpc&utm_campaign=lux_search_pylesosy_{campaign_id}&utm_content=aerlyn_{ad_id}_{source_type}&utm_term={keyword} | L72: Aerlyn | M72: Россия | N72: Каталог техники||Доставка и оплата||Сервис и гарантия||Моющий пылесос Aqvion Pro | O72: Пылесосы, швабры, кофемашины, аэрогрили||Пункты выдачи и курьер Ozon, срок после ввода адреса||Бесплатный вывоз СДЭК при гарантийном случае||Беспроводной, 15 000 Па, самоочистка и сушка | P72: https://luxhomme.store/catalog?utm_source=yandex&utm_medium=cpc&utm_campaign=lux_search_pylesosy_{campaign_id}&utm_content=aerlyn_sitelink_{ad_id}_{source_type}&utm_term={keyword}||https://luxhomme.store/delivery?utm_source=yandex&utm_medium=cpc&utm_campaign=lux_search_pylesosy_{campaign_id}&utm_content=aerlyn_sitelink_{ad_id}_{source_type}&utm_term={keyword}||https://luxhomme.store/service?utm_source=yandex&utm_medium=cpc&utm_campaign=lux_search_pylesosy_{campaign_id}&utm_content=aerlyn_sitelink_{ad_id}_{source_type}&utm_term={keyword}||https://luxhomme.store/products/vertikalnyj-moyushhij-pylesos-aqvion-pro?utm_source=yandex&utm_medium=cpc&utm_campaign=lux_search_pylesosy_{campaign_id}&utm_content=aerlyn_sitelink_{ad_id}_{source_type}&utm_term={keyword} | Q72: Гарантия 3 года||Скидка 20% по промокоду||Доставка через Ozon||Служба заботы 9–21 МСК||Сервисный центр в РФ
A73: Lux | Поиск | Пылесосы | B73: + | C73: Текстово-графическое | D73: - | E73: Aerlyn | F73: 3 | H73: Вертикальный беспроводной пылесос с HEPA-фильтром | I73: Скидка 20% по промокоду | J73: Aerlyn: режимы ECO, FLOOR, CARPET, TURBO и авто. Гарантия 3 года. | K73: https://luxhomme.store/products/vertikalnyj-suhoj-pylesos-aerlyn?utm_source=yandex&utm_medium=cpc&utm_campaign=lux_search_pylesosy_{campaign_id}&utm_content=aerlyn_{ad_id}_{source_type}&utm_term={keyword} | L73: Aerlyn | M73: Россия | N73: Каталог техники||Доставка и оплата||Сервис и гарантия||Моющий пылесос Aqvion Pro | O73: Пылесосы, швабры, кофемашины, аэрогрили||Пункты выдачи и курьер Ozon, срок после ввода адреса||Бесплатный вывоз СДЭК при гарантийном случае||Беспроводной, 15 000 Па, самоочистка и сушка | P73: https://luxhomme.store/catalog?utm_source=yandex&utm_medium=cpc&utm_campaign=lux_search_pylesosy_{campaign_id}&utm_content=aerlyn_sitelink_{ad_id}_{source_type}&utm_term={keyword}||https://luxhomme.store/delivery?utm_source=yandex&utm_medium=cpc&utm_campaign=lux_search_pylesosy_{campaign_id}&utm_content=aerlyn_sitelink_{ad_id}_{source_type}&utm_term={keyword}||https://luxhomme.store/service?utm_source=yandex&utm_medium=cpc&utm_campaign=lux_search_pylesosy_{campaign_id}&utm_content=aerlyn_sitelink_{ad_id}_{source_type}&utm_term={keyword}||https://luxhomme.store/products/vertikalnyj-moyushhij-pylesos-aqvion-pro?utm_source=yandex&utm_medium=cpc&utm_campaign=lux_search_pylesosy_{campaign_id}&utm_content=aerlyn_sitelink_{ad_id}_{source_type}&utm_term={keyword} | Q73: Гарантия 3 года||Скидка 20% по промокоду||Доставка через Ozon||Служба заботы 9–21 МСК||Сервисный центр в РФ
